Workbook

Sheet Summary 
A1: AR SUMMARY
A2: STATUS | B2: AMOUNT | C2: NO OF CLAIMS
A3: Claim Paid - EFT | B3: =SUMIFS('Level 1'!J5:J1200, 'Level 1'!M5:M1200,Table1[[#This Row],[Select Status]]) -> 62214.8 | C3: =COUNTIFS('Level 1'!M5:M1200,Table1[[#This Row],[Select Status]]) -> 133
A4: Claim Paid - CHK | B4: =SUMIFS('Level 1'!J5:J1200, 'Level 1'!M5:M1200,Table1[[#This Row],[Select Status]]) -> 19769.6 | C4: =COUNTIFS('Level 1'!M5:M1200,Table1[[#This Row],[Select Status]]) -> 43
A5: Claim in Process | B5: =SUMIFS('Level 1'!J5:J1200, 'Level 1'!M5:M1200,Table1[[#This Row],[Select Status]]) -> 88.8 | C5: =COUNTIFS('Level 1'!M5:M1200,Table1[[#This Row],[Select Status]]) -> 1
A6: Frequency Denial | B6: =SUMIFS('Level 1'!J5:J1200, 'Level 1'!M5:M1200,Table1[[#This Row],[Select Status]]) -> 670.4 | C6: =COUNTIFS('Level 1'!M5:M1200,Table1[[#This Row],[Select Status]]) -> 5
A7: Maxed out Denial | B7: =SUMIFS('Level 1'!J5:J1200, 'Level 1'!M5:M1200,Table1[[#This Row],[Select Status]]) -> 288.8 | C7: =COUNTIFS('Level 1'!M5:M1200,Table1[[#This Row],[Select Status]]) -> 2
A8: Not Covered | B8: =SUMIFS('Level 1'!J5:J1200, 'Level 1'!M5:M1200,Table1[[#This Row],[Select Status]]) -> 5719.6 | C8: =COUNTIFS('Level 1'!M5:M1200,Table1[[#This Row],[Select Status]]) -> 15
A9: Miss Tth Clause Denial | B9: =SUMIFS('Level 1'!J5:J1200, 'Level 1'!M5:M1200,Table1[[#This Row],[Select Status]]) -> 0 | C9: =COUNTIFS('Level 1'!M5:M1200,Table1[[#This Row],[Select Status]]) -> 0
A10: Dup Submission | B10: =SUMIFS('Level 1'!J5:J1200, 'Level 1'!M5:M1200,Table1[[#This Row],[Select Status]]) -> 81.2 | C10: =COUNTIFS('Level 1'!M5:M1200,Table1[[#This Row],[Select Status]]) -> 2
A11: Waiting Pd Denial | B11: =SUMIFS('Level 1'!J5:J1200, 'Level 1'!M5:M1200,Table1[[#This Row],[Select Status]]) -> 0 | C11: =COUNTIFS('Level 1'!M5:M1200,Table1[[#This Row],[Select Status]]) -> 0
A12: Pr Paid Max | B12: =SUMIFS('Level 1'!J5:J1200, 'Level 1'!M5:M1200,Table1[[#This Row],[Select Status]]) -> 1114 | C12: =COUNTIFS('Level 1'!M5:M1200,Table1[[#This Row],[Select Status]]) -> 4
A13: Invd Proc Code | B13: =SUMIFS('Level 1'!J5:J1200, 'Level 1'!M5:M1200,Table1[[#This Row],[Select Status]]) -> 0 | C13: =COUNTIFS('Level 1'!M5:M1200,Table1[[#This Row],[Select Status]]) -> 0
A14: SRP Hist Dts Denial | B14: =SUMIFS('Level 1'!J5:J1200, 'Level 1'!M5:M1200,Table1[[#This Row],[Select Status]]) -> 0 | C14: =COUNTIFS('Level 1'!M5:M1200,Table1[[#This Row],[Select Status]]) -> 0
A15: Init Placement Dt Denial | B15: =SUMIFS('Level 1'!J5:J1200, 'Level 1'!M5:M1200,Table1[[#This Row],[Select Status]]) -> 0 | C15: =COUNTIFS('Level 1'!M5:M1200,Table1[[#This Row],[Select Status]]) -> 0
A16: TFL Denial | B16: =SUMIFS('Level 1'!J5:J1200, 'Level 1'!M5:M1200,Table1[[#This Row],[Select Status]]) -> 1515.6 | C16: =COUNTIFS('Level 1'!M5:M1200,Table1[[#This Row],[Select Status]]) -> 1
A17: Age Limit Denial | B17: =SUMIFS('Level 1'!J5:J1200, 'Level 1'!M5:M1200,Table1[[#This Row],[Select Status]]) -> 0 | C17: =COUNTIFS('Level 1'!M5:M1200,Table1[[#This Row],[Select Status]]) -> 0
A18: Miss Attach Denial | B18: =SUMIFS('Level 1'!J5:J1200, 'Level 1'!M5:M1200,Table1[[#This Row],[Select Status]]) -> 2794.8 | C18: =COUNTIFS('Level 1'!M5:M1200,Table1[[#This Row],[Select Status]]) -> 1
A19: Nd More Info | B19: =SUMIFS('Level 1'!J5:J1200, 'Level 1'!M5:M1200,Table1[[#This Row],[Select Status]]) -> 13999.2 | C19: =COUNTIFS('Level 1'!M5:M1200,Table1[[#This Row],[Select Status]]) -> 32
A20: Claim not on File | B20: =SUMIFS('Level 1'!J5:J1200, 'Level 1'!M5:M1200,Table1[[#This Row],[Select Status]]) -> 16996.4 | C20: =COUNTIFS('Level 1'!M5:M1200,Table1[[#This Row],[Select Status]]) -> 39
A21: No Active Policy | B21: =SUMIFS('Level 1'!J5:J1200, 'Level 1'!M5:M1200,Table1[[#This Row],[Select Status]]) -> 4389.6 | C21: =COUNTIFS('Level 1'!M5:M1200,Table1[[#This Row],[Select Status]]) -> 4
A22: Claim Partially Paid - EFT | B22: =SUMIFS('Level 1'!J5:J1200, 'Level 1'!M5:M1200,Table1[[#This Row],[Select Status]]) -> 991.2 | C22: =COUNTIFS('Level 1'!M5:M1200,Table1[[#This Row],[Select Status]]) -> 3
A23: Claim Partially Paid - CHK | B23: =SUMIFS('Level 1'!J5:J1200, 'Level 1'!M5:M1200,Table1[[#This Row],[Select Status]]) -> 332.4 | C23: =COUNTIFS('Level 1'!M5:M1200,Table1[[#This Row],[Select Status]]) -> 2
A24: Patient Not Found | B24: =SUMIFS('Level 1'!J5:J1200, 'Level 1'!M5:M1200,Table1[[#This Row],[Select Status]]) -> 0 | C24: =COUNTIFS('Level 1'!M5:M1200,Table1[[#This Row],[Select Status]]) -> 0
A25: Other | B25: =SUMIFS('Level 1'!J5:J1200, 'Level 1'!M5:M1200,Table1[[#This Row],[Select Status]]) -> 4026.8 | C25: =COUNTIFS('Level 1'!M6:M1201,Table1[[#This Row],[Select Status]]) -> 10
A26: To be Followed up | B26: ='Level 1'!G3 -> 311311.8 | C26: ='Level 1'!H3 -> 768
A27: Total | B27: =SUM(B3:B26) -> 446305 | C27: =SUM(C3:C26) -> 1065

Sheet Level 1
A1: AR REPORT | F1: OUTSTANDING | G1: =SUM(J5:J1200) -> 440954.6 | H1: =COUNTIF(A5:A1200,"*") -> 1048 | I1: Claims
A2: CLIENT NAME | C2: Sweet Smiles | F2: COMPLETED | G2: =SUM('Summary '!B3:B21) -> 129642.8 | H2: =COUNTIF(AG5:AG1200,"Follow-Up Complete") -> 280 | I2: Claims
A3: Report Date | C3: 44670 | F3: NOT COMPLETED | G3: =SUM(G1-G2) -> 311311.8 | H3: =SUM(H1-H2) -> 768 | I3: Claims | AE3: Level 1
A4: INS Company | B4: INS Ph No | C4: SUBSCRIBER NAME | D4: SUB ID | E4: Patient ID | F4: PATIENT NAME | G4: DOB | H4: DOS | I4: SENT | J4: TOTAL | K4: DAYS | L4: Location | M4: Claim Status | N4: Note | O4: Q1 | Q4: Q2 | S4: Q3 | U4: Q4 | W4: Q5 | Y4: Claim Action | Z4: Additional Notes: | AB4: NXT FLUP DT | AC4: EOB DL | AD4: Team worked | AE4: Worked By | AF4: Worked Dt | AG4: Follow-Up Status
A5: =Data!K4 -> Aetna | B5: =Data!L4 -> 8004517715 | C5: =Data!D4 -> Passehl , Kayla | D5: =Data!F4 -> W237205096 | E5: =Data!B4 -> 9200 | F5: =Data!A4 -> Passehl , Kayla | G5: =Data!C4 -> 7/30/1991 | H5: =Data!H4 -> 44635 | I5: =Data!I4 -> 3/24/2022 | J5: =Data!J4 -> 292.4 | K5: =TODAY()-I5 -> 56 | L5: =Data!M4 -> 0 | M5: Select Status | N5: =VLOOKUP(M5,Table1[#All],3,FALSE) -> Note | O5: =VLOOKUP(M5,Table1[#All],4,FALSE) -> Q1 | Q5: =VLOOKUP(M5,Table1[#All],5,FALSE) -> Q2 | S5: =VLOOKUP(M5,Table1[#All],6,FALSE) -> Q3 | U5: =VLOOKUP(M5,Table1[#All],7,FALSE) -> Q4 | W5: =VLOOKUP(M5,Table1[#All],8,FALSE) -> Q5 | Y5: =VLOOKUP(M5,Table1[#All],2,FALSE) -> Action | Z5: =VLOOKUP(M5,Table1[#All],9,FALSE) -> Additional Notes: | AC5: Select | AD5: Select | AG5: Select
A6: =Data!K5 -> Ameritas | B6: =Data!L5 -> 8006592223 | C6: =Data!D5 -> Brown, Isabella | D6: =Data!F5 -> 016776290 | E6: =Data!B5 -> 7412 | F6: =Data!A5 -> Brown, Isabella | G6: =Data!C5 -> 3/15/1962 | H6: =Data!H5 -> 44470 | I6: =Data!I5 -> 10/7/2021 | J6: =Data!J5 -> 1036.8 | K6: =TODAY()-I6 -> 224 | L6: =Data!M5 -> 0 | M6: CLAIM PAID - CHK | N6: =VLOOKUP(M6,Table1[#All],3,FALSE) -> Claim Paid by Check; | O6: =VLOOKUP(M6,Table1[#All],4,FALSE) -> Issue Date: | P6: 44484 | Q6: =VLOOKUP(M6,Table1[#All],5,FALSE) -> CHK# | R6: 237237308 | S6: =VLOOKUP(M6,Table1[#All],6,FALSE) -> Bulk/Sep: | T6: Single | U6: =VLOOKUP(M6,Table1[#All],7,FALSE) -> Call Ref#: | V6: 2070 | W6: =VLOOKUP(M6,Table1[#All],8,FALSE) -> Cust Rep: | X6: Poni | Y6: =VLOOKUP(M6,Table1[#All],2,FALSE) -> Task Cashed Chk Queue | Z6: =VLOOKUP(M6,Table1[#All],9,FALSE) -> Additional Notes: | AA6: Rep states that clm #043444672190, paid amt $702.40, Its is a V.C.C payment and the draft number #237237308, patient responsibility is 303.60. cashed dt 10/26/2021. | AB6: TASK CREATED | AC6: YES | AD6: V Team | AE6: MU | AF6: 44627 | AG6: Follow-Up Complete
A7: =Data!K6 -> Anthem | B7: =Data!L6 -> 8447291565 | C7: =Data!D6 -> Thom, Keri | D7: =Data!F6 -> GQP130W03886 | E7: =Data!B6 -> 9330 | F7: =Data!A6 -> Thom, Keri | G7: =Data!C6 -> 8/14/2006 | H7: =Data!H6 -> 44642 | I7: =Data!I6 -> 3/25/2022 | J7: =Data!J6 -> 294.8 | K7: =TODAY()-I7 -> 55 | L7: =Data!M6 -> 0 | M7: Select Status | N7: =VLOOKUP(M7,Table1[#All],3,FALSE) -> Note | O7: =VLOOKUP(M7,Table1[#All],4,FALSE) -> Q1 | Q7: =VLOOKUP(M7,Table1[#All],5,FALSE) -> Q2 | S7: =VLOOKUP(M7,Table1[#All],6,FALSE) -> Q3 | U7: =VLOOKUP(M7,Table1[#All],7,FALSE) -> Q4 | W7: =VLOOKUP(M7,Table1[#All],8,FALSE) -> Q5 | Y7: =VLOOKUP(M7,Table1[#All],2,FALSE) -> Action | Z7: =VLOOKUP(M7,Table1[#All],9,FALSE) -> Additional Notes: | AC7: Select | AD7: Select | AG7: Select
A8: =Data!K7 -> Anthem | B8: =Data!L7 -> 8447291565 | C8: =Data!D7 -> Wricks, Derrishia | D8: =Data!F7 -> 201W03443 | E8: =Data!B7 -> 4527 | F8: =Data!A7 -> Wricks, Derrishia | G8: =Data!C7 -> 9/28/1993 | H8: =Data!H7 -> 44545 | I8: =Data!I7 -> 2/10/2022 | J8: =Data!J7 -> 266 | K8: =TODAY()-I8 -> 98 | L8: =Data!M7 -> 0 | M8: CNOF Active | N8: =VLOOKUP(M8,Table1[#All],3,FALSE) -> Claim not on file. Patient is active ; | O8: =VLOOKUP(M8,Table1[#All],4,FALSE) -> Payor ID & Address: | P8: CB950 | Q8: =VLOOKUP(M8,Table1[#All],5,FALSE) -> Fax # (If Fax Yes): | S8: =VLOOKUP(M8,Table1[#All],6,FALSE) -> TFL in Mnths: | T8: 12Months from Dos | U8: =VLOOKUP(M8,Table1[#All],7,FALSE) -> Call Ref#: | V8: LEANDRO | W8: =VLOOKUP(M8,Table1[#All],8,FALSE) -> Cust Rep: | X8: 8719609 | Y8: =VLOOKUP(M8,Table1[#All],2,FALSE) -> Task Sub Pending Claims Queue | Z8: =VLOOKUP(M8,Table1[#All],9,FALSE) -> Additional Notes: | AA8: CNOF - Active | AB8: NV pending | AC8: NO | AD8: V Team | AE8: SF | AF8: 44692 | AG8: Follow-Up Complete
A9: =Data!K8 -> Anthem | B9: =Data!L8 -> 8447291565 | C9: =Data!D8 -> Allen, Janiyah | D9: =Data!F8 -> 201W03443 | E9: =Data!B8 -> 8543 | F9: =Data!A8 -> Allen, Janiyah | G9: =Data!C8 -> 9/28/1993 | H9: =Data!H8 -> 44545 | I9: =Data!I8 -> 2/11/2022 | J9: =Data!J8 -> 307.2 | K9: =TODAY()-I9 -> 97 | L9: =Data!M8 -> 0 | M9: CNOF Active | N9: =VLOOKUP(M9,Table1[#All],3,FALSE) -> Claim not on file. Patient is active ; | O9: =VLOOKUP(M9,Table1[#All],4,FALSE) -> Payor ID & Address: | P9: CB950 | Q9: =VLOOKUP(M9,Table1[#All],5,FALSE) -> Fax # (If Fax Yes): | S9: =VLOOKUP(M9,Table1[#All],6,FALSE) -> TFL in Mnths: | T9: 12 Months from Dos | U9: =VLOOKUP(M9,Table1[#All],7,FALSE) -> Call Ref#: | V9: 87214304 | W9: =VLOOKUP(M9,Table1[#All],8,FALSE) -> Cust Rep: | X9: CELLE | Y9: =VLOOKUP(M9,Table1[#All],2,FALSE) -> Task Sub Pending Claims Queue | Z9: =VLOOKUP(M9,Table1[#All],9,FALSE) -> Additional Notes: | AA9: CNOF - Active. | AB9: NV pending | AC9: NO | AD9: V Team | AE9: SF | AF9: 44693 | AG9: Follow-Up Complete
A10: =Data!K9 -> Cigna | B10: =Data!L9 -> 8002446224 | C10: =Data!D9 -> Sullivan, Jessica | D10: =Data!F9 -> U47262786 | E10: =Data!B9 -> 9345 | F10: =Data!A9 -> Sullivan, Jessica | G10: =Data!C9 -> 7/12/1984 | H10: =Data!H9 -> 44644 | I10: =Data!I9 -> 3/25/2022 | J10: =Data!J9 -> 302.4 | K10: =TODAY()-I10 -> 55 | L10: =Data!M9 -> 0 | M10: Select Status | N10: =VLOOKUP(M10,Table1[#All],3,FALSE) -> Note | O10: =VLOOKUP(M10,Table1[#All],4,FALSE) -> Q1 | Q10: =VLOOKUP(M10,Table1[#All],5,FALSE) -> Q2 | S10: =VLOOKUP(M10,Table1[#All],6,FALSE) -> Q3 | U10: =VLOOKUP(M10,Table1[#All],7,FALSE) -> Q4 | W10: =VLOOKUP(M10,Table1[#All],8,FALSE) -> Q5 | Y10: =VLOOKUP(M10,Table1[#All],2,FALSE) -> Action | Z10: =VLOOKUP(M10,Table1[#All],9,FALSE) -> Additional Notes: | AC10: Select | AD10: Select | AG10: Select
A11: =Data!K10 -> Cigna | B11: =Data!L10 -> 8002446224 | C11: =Data!D10 -> Sullivan, Carter | D11: =Data!F10 -> U47262786 | E11: =Data!B10 -> 2668 | F11: =Data!A10 -> Sullivan, Carter | G11: =Data!C10 -> 7/12/1984 | H11: =Data!H10 -> 44643 | I11: =Data!I10 -> 3/24/2022 | J11: =Data!J10 -> 102 | K11: =TODAY()-I11 -> 56 | L11: =Data!M10 -> 0 | M11: Select Status | N11: =VLOOKUP(M11,Table1[#All],3,FALSE) -> Note | O11: =VLOOKUP(M11,Table1[#All],4,FALSE) -> Q1 | Q11: =VLOOKUP(M11,Table1[#All],5,FALSE) -> Q2 | S11: =VLOOKUP(M11,Table1[#All],6,FALSE) -> Q3 | U11: =VLOOKUP(M11,Table1[#All],7,FALSE) -> Q4 | W11: =VLOOKUP(M11,Table1[#All],8,FALSE) -> Q5 | Y11: =VLOOKUP(M11,Table1[#All],2,FALSE) -> Action | Z11: =VLOOKUP(M11,Table1[#All],9,FALSE) -> Additional Notes: | AC11: Select | AD11: Select | AG11: Select
A12: =Data!K11 -> Cigna | B12: =Data!L11 -> 8002446224 | C12: =Data!D11 -> Arthur, Bernika | D12: =Data!F11 -> U49852743 | E12: =Data!B11 -> 3727 | F12: =Data!A11 -> Arthur, Bernika | G12: =Data!C11 -> 8/26/1988 | H12: =Data!H11 -> 44639 | I12: =Data!I11 -> 3/21/2022 | J12: =Data!J11 -> 123.6 | K12: =TODAY()-I12 -> 59 | L12: =Data!M11 -> 0 | M12: Select Status | N12: =VLOOKUP(M12,Table1[#All],3,FALSE) -> Note | O12: =VLOOKUP(M12,Table1[#All],4,FALSE) -> Q1 | Q12: =VLOOKUP(M12,Table1[#All],5,FALSE) -> Q2 | S12: =VLOOKUP(M12,Table1[#All],6,FALSE) -> Q3 | U12: =VLOOKUP(M12,Table1[#All],7,FALSE) -> Q4 | W12: =VLOOKUP(M12,Table1[#All],8,FALSE) -> Q5 | Y12: =VLOOKUP(M12,Table1[#All],2,FALSE) -> Action | Z12: =VLOOKUP(M12,Table1[#All],9,FALSE) -> Additional Notes: | AC12: Select | AD12: Select | AG12: Select
A13: =Data!K12 -> Cigna | B13: =Data!L12 -> 8002446224 | C13: =Data!D12 -> Arthur, Lilyana | D13: =Data!F12 -> U49852743 | E13: =Data!B12 -> 3729 | F13: =Data!A12 -> Arthur, Lilyana | G13: =Data!C12 -> 8/26/1988 | H13: =Data!H12 -> 44639 | I13: =Data!I12 -> 3/21/2022 | J13: =Data!J12 -> 58.8 | K13: =TODAY()-I13 -> 59 | L13: =Data!M12 -> 0 | M13: Select Status | N13: =VLOOKUP(M13,Table1[#All],3,FALSE) -> Note | O13: =VLOOKUP(M13,Table1[#All],4,FALSE) -> Q1 | Q13: =VLOOKUP(M13,Table1[#All],5,FALSE) -> Q2 | S13: =VLOOKUP(M13,Table1[#All],6,FALSE) -> Q3 | U13: =VLOOKUP(M13,Table1[#All],7,FALSE) -> Q4 | W13: =VLOOKUP(M13,Table1[#All],8,FALSE) -> Q5 | Y13: =VLOOKUP(M13,Table1[#All],2,FALSE) -> Action | Z13: =VLOOKUP(M13,Table1[#All],9,FALSE) -> Additional Notes: | AC13: Select | AD13: Select | AG13: Select
A14: =Data!K13 -> Cigna | B14: =Data!L13 -> 8002446224 | C14: =Data!D13 -> Arthur, Lilyana | D14: =Data!F13 -> U49852743 | E14: =Data!B13 -> 3729 | F14: =Data!A13 -> Arthur, Lilyana | G14: =Data!C13 -> 8/26/1988 | H14: =Data!H13 -> 44639 | I14: =Data!I13 -> 3/21/2022 | J14: =Data!J13 -> 79.2 | K14: =TODAY()-I14 -> 59 | L14: =Data!M13 -> 0 | M14: Select Status | N14: =VLOOKUP(M14,Table1[#All],3,FALSE) -> Note | O14: =VLOOKUP(M14,Table1[#All],4,FALSE) -> Q1 | Q14: =VLOOKUP(M14,Table1[#All],5,FALSE) -> Q2 | S14: =VLOOKUP(M14,Table1[#All],6,FALSE) -> Q3 | U14: =VLOOKUP(M14,Table1[#All],7,FALSE) -> Q4 | W14: =VLOOKUP(M14,Table1[#All],8,FALSE) -> Q5 | Y14: =VLOOKUP(M14,Table1[#All],2,FALSE) -> Action | Z14: =VLOOKUP(M14,Table1[#All],9,FALSE) -> Additional Notes: | AC14: Select | AD14: Select | AG14: Select
A15: =Data!K14 -> Cigna | B15: =Data!L14 -> 8002446224 | C15: =Data!D14 -> Belle , Byron | D15: =Data!F14 -> U72051724 | E15: =Data!B14 -> 4246 | F15: =Data!A14 -> Belle , Byron | G15: =Data!C14 -> 6/10/1992 | H15: =Data!H14 -> 44573 | I15: =Data!I14 -> 1/13/2022 | J15: =Data!J14 -> 266 | K15: =TODAY()-I15 -> 126 | L15: =Data!M14 -> 0 | M15: CLAIM PAID - EFT | N15: =VLOOKUP(M15,Table1[#All],3,FALSE) -> Claim Paid by EFT; | O15: =VLOOKUP(M15,Table1[#All],4,FALSE) -> Issue Date: | P15: 44580 | Q15: =VLOOKUP(M15,Table1[#All],5,FALSE) -> EFT# | R15: 9999761864 | S15: =VLOOKUP(M15,Table1[#All],6,FALSE) -> Bulk/Sep: | T15: single | U15: =VLOOKUP(M15,Table1[#All],7,FALSE) -> Call Ref#: | V15: 2763 | W15: =VLOOKUP(M15,Table1[#All],8,FALSE) -> Cust Rep: | X15: MJ | Y15: =VLOOKUP(M15,Table1[#All],2,FALSE) -> Task Post Pmt Queue | Z15: =VLOOKUP(M15,Table1[#All],9,FALSE) -> Additional Notes: | AA15: Rep State that Code D0120, D0220, D0230 & (Partially) D0274 are applied towards the deductable. D1208 - denied due to Age limit (Age limit under 19) Rep Name: Moises, Call Ref: 4641//Rep States that the Claim Paid,Claim No:D220146565680, paid amt$130 Patient Resp: $136. | AB15: CLAIM CLOSED | AC15: YES | AD15: V Team | AE15: AA | AF15: 44664 | AG15: Follow-Up Complete
A16: =Data!K15 -> Cigna | B16: =Data!L15 -> 8002446224 | C16: =Data!D15 -> Arthur, Devin | D16: =Data!F15 -> U49852743 | E16: =Data!B15 -> 3728 | F16: =Data!A15 -> Arthur, Devin | G16: =Data!C15 -> 8/26/1988 | H16: =Data!H15 -> 44478 | I16: =Data!I15 -> 10/11/2021 | J16: =Data!J15 -> 230 | K16: =TODAY()-I16 -> 220 | L16: =Data!M15 -> 0 | M16: CLAIM PAID - EFT | N16: =VLOOKUP(M16,Table1[#All],3,FALSE) -> Claim Paid by EFT; | O16: =VLOOKUP(M16,Table1[#All],4,FALSE) -> Issue Date: | P16: 44481 | Q16: =VLOOKUP(M16,Table1[#All],5,FALSE) -> EFT# | R16: 9997740967 | S16: =VLOOKUP(M16,Table1[#All],6,FALSE) -> Bulk/Sep: | T16: Bulk | U16: =VLOOKUP(M16,Table1[#All],7,FALSE) -> Call Ref#: | V16: 9764 | W16: =VLOOKUP(M16,Table1[#All],8,FALSE) -> Cust Rep: | X16: sara | Y16: =VLOOKUP(M16,Table1[#All],2,FALSE) -> Task Post Pmt Queue | Z16: =VLOOKUP(M16,Table1[#All],9,FALSE) -> Additional Notes: | AA16: Rep States that Claim Paid,Claim No:D212856143800, paid amt$113 Patient Resp: NIL, All the lines paid on the claim. | AB16: NV pending | AC16: YES | AD16: V Team | AE16: MU | AF16: 44607 | AG16: Follow-Up Complete
A17: =Data!K16 -> Cigna | B17: =Data!L16 -> 8002446224 | C17: =Data!D16 -> Arthur, Bernika | D17: =Data!F16 -> U49852743 | E17: =Data!B16 -> 3727 | F17: =Data!A16 -> Arthur, Bernika | G17: =Data!C16 -> 8/26/1988 | H17: =Data!H16 -> 44478 | I17: =Data!I16 -> 10/11/2021 | J17: =Data!J16 -> 216 | K17: =TODAY()-I17 -> 220 | L17: =Data!M16 -> 0 | M17: CLAIM PAID - EFT | N17: =VLOOKUP(M17,Table1[#All],3,FALSE) -> Claim Paid by EFT; | O17: =VLOOKUP(M17,Table1[#All],4,FALSE) -> Issue Date: | P17: 44482 | Q17: =VLOOKUP(M17,Table1[#All],5,FALSE) -> EFT# | R17: 9997740967 | S17: =VLOOKUP(M17,Table1[#All],6,FALSE) -> Bulk/Sep: | T17: Single | U17: =VLOOKUP(M17,Table1[#All],7,FALSE) -> Call Ref#: | V17: 5334 | W17: =VLOOKUP(M17,Table1[#All],8,FALSE) -> Cust Rep: | X17: Nel | Y17: =VLOOKUP(M17,Table1[#All],2,FALSE) -> Task Post Pmt Queue | Z17: =VLOOKUP(M17,Table1[#All],9,FALSE) -> Additional Notes: | AA17: Pd $4.00 Pt res $76.00 Clm #D212856144410 was cashed on 10/18/2021 | AB17: NV pending | AC17: YES | AD17: V Team | AE17: DK | AF17: 44579 | AG17: Follow-Up Complete
A18: =Data!K17 -> Cigna | B18: =Data!L17 -> 8002446224 | C18: =Data!D17 -> Rasmussen , John | D18: =Data!F17 -> U153667756 | E18: =Data!B17 -> 6734 | F18: =Data!A17 -> Rasmussen , John | G18: =Data!C17 -> 9/25/1954 | H18: =Data!H17 -> 44474 | I18: =Data!I17 -> 10/7/2021 | J18: =Data!J17 -> 88.8 | K18: =TODAY()-I18 -> 224 | L18: =Data!M17 -> 0 | M18: CLAIM PAID - EFT | N18: =VLOOKUP(M18,Table1[#All],3,FALSE) -> Claim Paid by EFT; | O18: =VLOOKUP(M18,Table1[#All],4,FALSE) -> Issue Date: | P18: 44477 | Q18: =VLOOKUP(M18,Table1[#All],5,FALSE) -> EFT# | R18: 9997740965 | S18: =VLOOKUP(M18,Table1[#All],6,FALSE) -> Bulk/Sep: | T18: SEP | U18: =VLOOKUP(M18,Table1[#All],7,FALSE) -> Call Ref#: | V18: 7209 | W18: =VLOOKUP(M18,Table1[#All],8,FALSE) -> Cust Rep: | X18: Erick | Y18: =VLOOKUP(M18,Table1[#All],2,FALSE) -> Task Post Pmt Queue | Z18: =VLOOKUP(M18,Table1[#All],9,FALSE) -> Additional Notes: | AA18: Rep States that Claim Paid,Claim No:R212816304340,Pd Amt $53; Patient Resp: Nil, | AB18: NV pending | AC18: YES | AD18: V Team | AE18: AA | AF18: 44585 | AG18: Follow-Up Complete
A19: =Data!K18 -> Cigna | B19: =Data!L18 -> 8002446224 | C19: =Data!D18 -> Knight, Richard | D19: =Data!F18 -> U72076261 | E19: =Data!B18 -> 5453 | F19: =Data!A18 -> Knight, Richard | G19: =Data!C18 -> 5/5/1970 | H19: =Data!H18 -> 44322 | I19: =Data!I18 -> 5/6/2021 | J19: =Data!J18 -> 890 | K19: =TODAY()-I19 -> 378 | L19: =Data!M18 -> 0 | M19: DENIED - MORE INFO | N19: =VLOOKUP(M19,Table1[#All],3,FALSE) -> Ins needs more info, need to submit; | O19: =VLOOKUP(M19,Table1[#All],4,FALSE) -> Attachments/Info needed? | P19: Prep Date,Seat Date & Initial or Replacement Prior Placement Date | Q19: =VLOOKUP(M19,Table1[#All],5,FALSE) -> Fax # (If Fax Yes): | R19: 8595502662 | S19: =VLOOKUP(M19,Table1[#All],6,FALSE) -> Call Ref#: | T19: 7991 | U19: =VLOOKUP(M19,Table1[#All],7,FALSE) -> Cust Rep: | V19: Michal | W19: =VLOOKUP(M19,Table1[#All],8,FALSE) -> 0 | Y19: =VLOOKUP(M19,Table1[#All],2,FALSE) -> Task Sub Pending Claims Queue | Z19: =VLOOKUP(M19,Table1[#All],9,FALSE) -> Additional Notes: | AA19: Rep State Clm Denied,Claim No: S211306181710,Mailing Address: PO Box 188037. Chattanooga, TN 37422,TFL: 365 Days for Out of Nework Patient,Processed & Denied Date: 07/19/2021 | AB19: NV pending | AC19: NO | AD19: V Team | AE19: AA | AF19: 44655 | AG19: Follow-Up Complete
A20: =Data!K19 -> Cigna Out Of Network | B20: =Data!L19 -> 8004486262 | C20: =Data!D19 -> Mokry, Lila | D20: =Data!F19 -> u34464213 | E20: =Data!B19 -> 7171 | F20: =Data!A19 -> Mokry, Lila | G20: =Data!C19 -> 8/15/2016 | H20: =Data!H19 -> 44343 | I20: =Data!I19 -> 6/2/2021 | J20: =Data!J19 -> 256.4 | K20: =TODAY()-I20 -> 351 | L20: =Data!M19 -> 0 | M20: CNOF Active | N20: =VLOOKUP(M20,Table1[#All],3,FALSE) -> Claim not on file. Patient is active ; | O20: =VLOOKUP(M20,Table1[#All],4,FALSE) -> Payor ID & Address: | P20: 62308 | Q20: =VLOOKUP(M20,Table1[#All],5,FALSE) -> Fax # (If Fax Yes): | R20: 8595502662 | S20: =VLOOKUP(M20,Table1[#All],6,FALSE) -> TFL in Mnths: | T20: No Limit | U20: =VLOOKUP(M20,Table1[#All],7,FALSE) -> Call Ref#: | V20: 1606 | W20: =VLOOKUP(M20,Table1[#All],8,FALSE) -> Cust Rep: | X20: Irvin | Y20: =VLOOKUP(M20,Table1[#All],2,FALSE) -> Task Sub Pending Claims Queue | Z20: =VLOOKUP(M20,Table1[#All],9,FALSE) -> Additional Notes: | AA20: Claim Resubmitted electronically on 05/06/2022 - SN // Rep State that CNOF,Effective Date:01/01/2021, Mailing Adrss: P.O.BOX 188037,Chattanooga,TN 37422 Rep Name: Michal Call Ref: 1569 | AB20: 44701 | AC20: NO | AD20: V Team | AE20: AA | AF20: 44655 | AG20: Further Follow-Up
A21: =Data!K20 -> Cigna | B21: =Data!L20 -> 8002446224 | C21: =Data!D20 -> Johnson , Alina | D21: =Data!F20 -> U26438292 | E21: =Data!B20 -> 5823 | F21: =Data!A20 -> Johnson , Alina | G21: =Data!C20 -> 11/19/1975 | H21: =Data!H20 -> 44643 | I21: =Data!I20 -> 3/24/2022 | J21: =Data!J20 -> 496 | K21: =TODAY()-I21 -> 56 | L21: =Data!M20 -> 0 | M21: Select Status | N21: =VLOOKUP(M21,Table1[#All],3,FALSE) -> Note | O21: =VLOOKUP(M21,Table1[#All],4,FALSE) -> Q1 | Q21: =VLOOKUP(M21,Table1[#All],5,FALSE) -> Q2 | S21: =VLOOKUP(M21,Table1[#All],6,FALSE) -> Q3 | U21: =VLOOKUP(M21,Table1[#All],7,FALSE) -> Q4 | W21: =VLOOKUP(M21,Table1[#All],8,FALSE) -> Q5 | Y21: =VLOOKUP(M21,Table1[#All],2,FALSE) -> Action | Z21: =VLOOKUP(M21,Table1[#All],9,FALSE) -> Additional Notes: | AC21: Select | AD21: Select | AG21: Select
A22: =Data!K21 -> Cigna | B22: =Data!L21 -> 8002446224 | C22: =Data!D21 -> Johnson, Aila | D22: =Data!F21 -> U26438292 | E22: =Data!B21 -> 9036 | F22: =Data!A21 -> Johnson, Aila | G22: =Data!C21 -> 11/19/1975 | H22: =Data!H21 -> 44643 | I22: =Data!I21 -> 3/24/2022 | J22: =Data!J21 -> 396 | K22: =TODAY()-I22 -> 56 | L22: =Data!M21 -> 0 | M22: Select Status | N22: =VLOOKUP(M22,Table1[#All],3,FALSE) -> Note | O22: =VLOOKUP(M22,Table1[#All],4,FALSE) -> Q1 | Q22: =VLOOKUP(M22,Table1[#All],5,FALSE) -> Q2 | S22: =VLOOKUP(M22,Table1[#All],6,FALSE) -> Q3 | U22: =VLOOKUP(M22,Table1[#All],7,FALSE) -> Q4 | W22: =VLOOKUP(M22,Table1[#All],8,FALSE) -> Q5 | Y22: =VLOOKUP(M22,Table1[#All],2,FALSE) -> Action | Z22: =VLOOKUP(M22,Table1[#All],9,FALSE) -> Additional Notes: | AC22: Select | AD22: Select | AG22: Select
A23: =Data!K22 -> Cigna | B23: =Data!L22 -> 8002446224 | C23: =Data!D22 -> Kienia, Jaxon | D23: =Data!F22 -> U53657370 | E23: =Data!B22 -> 7711 | F23: =Data!A22 -> Kienia, Jaxon | G23: =Data!C22 -> 12/2/1990 | H23: =Data!H22 -> 44636 | I23: =Data!I22 -> 3/17/2022 | J23: =Data!J22 -> 940 | K23: =TODAY()-I23 -> 63 | L23: =Data!M22 -> 0 | M23: Select Status | N23: =VLOOKUP(M23,Table1[#All],3,FALSE) -> Note | O23: =VLOOKUP(M23,Table1[#All],4,FALSE) -> Q1 | Q23: =VLOOKUP(M23,Table1[#All],5,FALSE) -> Q2 | S23: =VLOOKUP(M23,Table1[#All],6,FALSE) -> Q3 | U23: =VLOOKUP(M23,Table1[#All],7,FALSE) -> Q4 | W23: =VLOOKUP(M23,Table1[#All],8,FALSE) -> Q5 | Y23: =VLOOKUP(M23,Table1[#All],2,FALSE) -> Action | Z23: =VLOOKUP(M23,Table1[#All],9,FALSE) -> Additional Notes: | AC23: Select | AD23: Select | AG23: Select
A24: =Data!K23 -> Cigna | B24: =Data!L23 -> 8002446224 | C24: =Data!D23 -> Michaelis, Benjamin | D24: =Data!F23 -> U50621274 | E24: =Data!B23 -> 8777 | F24: =Data!A23 -> Michaelis, Benjamin | G24: =Data!C23 -> 12/13/1986 | H24: =Data!H23 -> 44630 | I24: =Data!I23 -> 3/11/2022 | J24: =Data!J23 -> 1062 | K24: =TODAY()-I24 -> 69 | L24: =Data!M23 -> 0 | M24: Select Status | N24: =VLOOKUP(M24,Table1[#All],3,FALSE) -> Note | O24: =VLOOKUP(M24,Table1[#All],4,FALSE) -> Q1 | Q24: =VLOOKUP(M24,Table1[#All],5,FALSE) -> Q2 | S24: =VLOOKUP(M24,Table1[#All],6,FALSE) -> Q3 | U24: =VLOOKUP(M24,Table1[#All],7,FALSE) -> Q4 | W24: =VLOOKUP(M24,Table1[#All],8,FALSE) -> Q5 | Y24: =VLOOKUP(M24,Table1[#All],2,FALSE) -> Action | Z24: =VLOOKUP(M24,Table1[#All],9,FALSE) -> Additional Notes: | AC24: Select | AD24: Select | AG24: Select
A25: =Data!K24 -> Cigna | B25: =Data!L24 -> 8002446224 | C25: =Data!D24 -> Salgado, Manuel | D25: =Data!F24 -> U52668717 | E25: =Data!B24 -> 9237 | F25: =Data!A24 -> Salgado, Manuel | G25: =Data!C24 -> 10/30/1993 | H25: =Data!H24 -> 44630 | I25: =Data!I24 -> 3/11/2022 | J25: =Data!J24 -> 256.4 | K25: =TODAY()-I25 -> 69 | L25: =Data!M24 -> 0 | M25: Select Status | N25: =VLOOKUP(M25,Table1[#All],3,FALSE) -> Note | O25: =VLOOKUP(M25,Table1[#All],4,FALSE) -> Q1 | Q25: =VLOOKUP(M25,Table1[#All],5,FALSE) -> Q2 | S25: =VLOOKUP(M25,Table1[#All],6,FALSE) -> Q3 | U25: =VLOOKUP(M25,Table1[#All],7,FALSE) -> Q4 | W25: =VLOOKUP(M25,Table1[#All],8,FALSE) -> Q5 | Y25: =VLOOKUP(M25,Table1[#All],2,FALSE) -> Action | Z25: =VLOOKUP(M25,Table1[#All],9,FALSE) -> Additional Notes: | AC25: Select | AD25: Select | AG25: Select
A26: =Data!K25 -> Cigna | B26: =Data!L25 -> 8002446224 | C26: =Data!D25 -> Cox, Racheal | D26: =Data!F25 -> U7550053602 | E26: =Data!B25 -> 7471 | F26: =Data!A25 -> Cox, Racheal | G26: =Data!C25 -> 11/27/1996 | H26: =Data!H25 -> 44384 | I26: =Data!I25 -> 3/7/2022 | J26: =Data!J25 -> 820.8 | K26: =TODAY()-I26 -> 73 | L26: =Data!M25 -> 0 | M26: Select Status | N26: =VLOOKUP(M26,Table1[#All],3,FALSE) -> Note | O26: =VLOOKUP(M26,Table1[#All],4,FALSE) -> Q1 | Q26: =VLOOKUP(M26,Table1[#All],5,FALSE) -> Q2 | S26: =VLOOKUP(M26,Table1[#All],6,FALSE) -> Q3 | U26: =VLOOKUP(M26,Table1[#All],7,FALSE) -> Q4 | W26: =VLOOKUP(M26,Table1[#All],8,FALSE) -> Q5 | Y26: =VLOOKUP(M26,Table1[#All],2,FALSE) -> Action | Z26: =VLOOKUP(M26,Table1[#All],9,FALSE) -> Additional Notes: | AC26: Select | AD26: Select | AG26: Select
A27: =Data!K26 -> Cigna | B27: =Data!L26 -> 8002446224 | C27: =Data!D26 -> Sexton Free , Brittney | D27: =Data!F26 -> u65208005 | E27: =Data!B26 -> 5759 | F27: =Data!A26 -> Sexton Free , Brittney | G27: =Data!C26 -> 11/9/1994 | H27: =Data!H26 -> 44624 | I27: =Data!I26 -> 3/7/2022 | J27: =Data!J26 -> 1315.2 | K27: =TODAY()-I27 -> 73 | L27: =Data!M26 -> 0 | M27: Select Status | N27: =VLOOKUP(M27,Table1[#All],3,FALSE) -> Note | O27: =VLOOKUP(M27,Table1[#All],4,FALSE) -> Q1 | Q27: =VLOOKUP(M27,Table1[#All],5,FALSE) -> Q2 | S27: =VLOOKUP(M27,Table1[#All],6,FALSE) -> Q3 | U27: =VLOOKUP(M27,Table1[#All],7,FALSE) -> Q4 | W27: =VLOOKUP(M27,Table1[#All],8,FALSE) -> Q5 | Y27: =VLOOKUP(M27,Table1[#All],2,FALSE) -> Action | Z27: =VLOOKUP(M27,Table1[#All],9,FALSE) -> Additional Notes: | AC27: Select | AD27: Select | AG27: Select
A28: =Data!K27 -> Cigna | B28: =Data!L27 -> 8002446224 | C28: =Data!D27 -> Sexton Free , Brittney | D28: =Data!F27 -> u65208005 | E28: =Data!B27 -> 5759 | F28: =Data!A27 -> Sexton Free , Brittney | G28: =Data!C27 -> 11/9/1994 | H28: =Data!H27 -> 44601 | I28: =Data!I27 -> 2/10/2022 | J28: =Data!J27 -> 253.2 | K28: =TODAY()-I28 -> 98 | L28: =Data!M27 -> 0 | M28: DENIED - NOT COVERED | N28: =VLOOKUP(M28,Table1[#All],3,FALSE) -> Procedure is not a covered benefit; | O28: =VLOOKUP(M28,Table1[#All],4,FALSE) -> Why? | P28: Not covered under pt plan | Q28: =VLOOKUP(M28,Table1[#All],5,FALSE) -> Call Ref#: | R28: 1142 | S28: =VLOOKUP(M28,Table1[#All],6,FALSE) -> Cust Rep: | T28: RHEA | U28: =VLOOKUP(M28,Table1[#All],7,FALSE) -> 0 | W28: =VLOOKUP(M28,Table1[#All],8,FALSE) -> 0 | Y28: =VLOOKUP(M28,Table1[#All],2,FALSE) -> Task Client - Denied Claim Queue | Z28: =VLOOKUP(M28,Table1[#All],9,FALSE) -> Additional Notes: | AA28: CLM#D22042654574,Processed Date: 02/11/2022,Your plan does not provide benefits for this service,Patient Resp: $253.20 | AB28: L2 Pending | AC28: YES | AD28: V Team | AE28: AA | AF28: 44698 | AG28: EOB Downloaded
A29: =Data!K28 -> Cigna | B29: =Data!L28 -> 8002446224 | C29: =Data!D28 -> Sexton Free , Brittney | D29: =Data!F28 -> u65208005 | E29: =Data!B28 -> 5759 | F29: =Data!A28 -> Sexton Free , Brittney | G29: =Data!C28 -> 11/9/1994 | H29: =Data!H28 -> 44573 | I29: =Data!I28 -> 1/17/2022 | J29: =Data!J28 -> 210 | K29: =TODAY()-I29 -> 122 | L29: =Data!M28 -> 0 | M29: CLAIM PAID - EFT | N29: =VLOOKUP(M29,Table1[#All],3,FALSE) -> Claim Paid by EFT; | O29: =VLOOKUP(M29,Table1[#All],4,FALSE) -> Issue Date: | P29: 44580 | Q29: =VLOOKUP(M29,Table1[#All],5,FALSE) -> EFT# | R29: 9999730907 | S29: =VLOOKUP(M29,Table1[#All],6,FALSE) -> Bulk/Sep: | T29: Bulk | U29: =VLOOKUP(M29,Table1[#All],7,FALSE) -> Call Ref#: | V29: 83827 | W29: =VLOOKUP(M29,Table1[#All],8,FALSE) -> Cust Rep: | X29: Mabby | Y29: =VLOOKUP(M29,Table1[#All],2,FALSE) -> Task Post Pmt Queue | Z29: =VLOOKUP(M29,Table1[#All],9,FALSE) -> Additional Notes: | AA29: Rep States that Claim Paid,Claim No:E220186079630,Patient Resp: NIL. | AB29: CLAIM CLOSED | AC29: YES | AD29: V Team | AE29: MA | AF29: 44606 | AG29: Follow-Up Complete
A30: =Data!K29 -> Cigna | B30: =Data!L29 -> 8002446224 | C30: =Data!D29 -> Gibson, Karl | D30: =Data!F29 -> U39194271 | E30: =Data!B29 -> 8803 | F30: =Data!A29 -> Gibson, Karl | G30: =Data!C29 -> 4/7/1988 | H30: =Data!H29 -> 44575 | I30: =Data!I29 -> 1/17/2022 | J30: =Data!J29 -> 294.8 | K30: =TODAY()-I30 -> 122 | L30: =Data!M29 -> 0 | M30: CLAIM PAID - EFT | N30: =VLOOKUP(M30,Table1[#All],3,FALSE) -> Claim Paid by EFT; | O30: =VLOOKUP(M30,Table1[#All],4,FALSE) -> Issue Date: | P30: 44580 | Q30: =VLOOKUP(M30,Table1[#All],5,FALSE) -> EFT# | R30: 9999761865 | S30: =VLOOKUP(M30,Table1[#All],6,FALSE) -> Bulk/Sep: | T30: Bulk | U30: =VLOOKUP(M30,Table1[#All],7,FALSE) -> Call Ref#: | V30: 7994 | W30: =VLOOKUP(M30,Table1[#All],8,FALSE) -> Cust Rep: | X30: Mabby | Y30: =VLOOKUP(M30,Table1[#All],2,FALSE) -> Task Post Pmt Queue | Z30: =VLOOKUP(M30,Table1[#All],9,FALSE) -> Additional Notes: | AA30: Rep States that Claim Paid,Claim No:S220186079630,Patient Resp: NIL All the lines paid on the claim. | AB30: CLAIM CLOSED | AC30: YES | AD30: V Team | AE30: MA | AF30: 44606 | AG30: Follow-Up Complete
A31: =Data!K30 -> Cigna | B31: =Data!L30 -> 8002446224 | C31: =Data!D30 -> Huston, Olivia | D31: =Data!F30 -> U39194271 | E31: =Data!B30 -> 8802 | F31: =Data!A30 -> Huston, Olivia | G31: =Data!C30 -> 4/7/1988 | H31: =Data!H30 -> 44575 | I31: =Data!I30 -> 1/17/2022 | J31: =Data!J30 -> 256.4 | K31: =TODAY()-I31 -> 122 | L31: =Data!M30 -> 0 | M31: CNOF Active | N31: =VLOOKUP(M31,Table1[#All],3,FALSE) -> Claim not on file. Patient is active ; | O31: =VLOOKUP(M31,Table1[#All],4,FALSE) -> Payor ID & Address: | P31: 62308 | Q31: =VLOOKUP(M31,Table1[#All],5,FALSE) -> Fax # (If Fax Yes): | R31: 8595502662 | S31: =VLOOKUP(M31,Table1[#All],6,FALSE) -> TFL in Mnths: | T31: No Limit | U31: =VLOOKUP(M31,Table1[#All],7,FALSE) -> Call Ref#: | V31: 6550 | W31: =VLOOKUP(M31,Table1[#All],8,FALSE) -> Cust Rep: | X31: Mabby | Y31: =VLOOKUP(M31,Table1[#All],2,FALSE) -> Task Sub Pending Claims Queue | Z31: =VLOOKUP(M31,Table1[#All],9,FALSE) -> Additional Notes: | AA31: Claim Resubmitted through fax on 05/06/2022 - SN // Rep states that clm is not on file for the dos, the patient is active, we can send send the clm through fax #8595502662, NO TFL. | AB31: 44701 | AC31: NO | AD31: V Team | AE31: DK | AF31: 44606 | AG31: Further Follow-Up
A32: =Data!K31 -> Cigna | B32: =Data!L31 -> 8002446224 | C32: =Data!D31 -> Michaelis, Benjamin | D32: =Data!F31 -> U50621274 | E32: =Data!B31 -> 8777 | F32: =Data!A31 -> Michaelis, Benjamin | G32: =Data!C31 -> 12/13/1986 | H32: =Data!H31 -> 44566 | I32: =Data!I31 -> 1/12/2022 | J32: =Data!J31 -> 186 | K32: =TODAY()-I32 -> 127 | L32: =Data!M31 -> 0 | M32: CLAIM PAID - EFT | N32: =VLOOKUP(M32,Table1[#All],3,FALSE) -> Claim Paid by EFT; | O32: =VLOOKUP(M32,Table1[#All],4,FALSE) -> Issue Date: | P32: 44575 | Q32: =VLOOKUP(M32,Table1[#All],5,FALSE) -> EFT# | R32: 9999761866 | S32: =VLOOKUP(M32,Table1[#All],6,FALSE) -> Bulk/Sep: | T32: bulk | U32: =VLOOKUP(M32,Table1[#All],7,FALSE) -> Call Ref#: | V32: 5749 | W32: =VLOOKUP(M32,Table1[#All],8,FALSE) -> Cust Rep: | X32: Joei | Y32: =VLOOKUP(M32,Table1[#All],2,FALSE) -> Task Post Pmt Queue | Z32: =VLOOKUP(M32,Table1[#All],9,FALSE) -> Additional Notes: | AA32: Rep States that Claim Paid,Paid Amt: 123.20,Claim No:E220146565650,Patient Resp:$62.80 All the lines paid on the claim. | AB32: NV pending | AC32: YES | AD32: V Team | AE32: AA | AF32: 44663 | AG32: Follow-Up Complete
A33: =Data!K32 -> Cigna | B33: =Data!L32 -> 8002446224 | C33: =Data!D32 -> Delk, Mark | D33: =Data!F32 -> U62450847 | E33: =Data!B32 -> 8713 | F33: =Data!A32 -> Delk, Mark | G33: =Data!C32 -> 7/1/1961 | H33: =Data!H32 -> 44557 | I33: =Data!I32 -> 12/30/2021 | J33: =Data!J32 -> 372.8 | K33: =TODAY()-I33 -> 140 | L33: =Data!M32 -> 0 | M33: CLAIM PAID - EFT | N33: =VLOOKUP(M33,Table1[#All],3,FALSE) -> Claim Paid by EFT; | O33: =VLOOKUP(M33,Table1[#All],4,FALSE) -> Issue Date: | P33: 44561 | Q33: =VLOOKUP(M33,Table1[#All],5,FALSE) -> EFT# | R33: 9999367367 | S33: =VLOOKUP(M33,Table1[#All],6,FALSE) -> Bulk/Sep: | T33: Sep | U33: =VLOOKUP(M33,Table1[#All],7,FALSE) -> Call Ref#: | V33: 4651 | W33: =VLOOKUP(M33,Table1[#All],8,FALSE) -> Cust Rep: | X33: natalie | Y33: =VLOOKUP(M33,Table1[#All],2,FALSE) -> Task Post Pmt Queue | Z33: =VLOOKUP(M33,Table1[#All],9,FALSE) -> Additional Notes: | AA33: Rep states that, Claim paid EFT Mode. Cashed out 01/05/2022 for $320.40. Rep name: NICs. Ref# 8666. Claim# E213656187000.//EOB Requested 24 Hr as per Rep Rep Name: Michal Call Ref: 1569//GET EOB -SN // Rep States that the Claim Paid,Claim No:E21365618700, paid amt$320.40 Patient Resp: $52.40 | AB33: NV pending | AC33: YES | AD33: V Team | AE33: SF//SN | AF33: 44655 | AG33: Follow-Up Complete
A34: =Data!K33 -> Cigna | B34: =Data!L33 -> 8002446224 | C34: =Data!D33 -> Ramsey, Jerod | D34: =Data!F33 -> U69059849 | E34: =Data!B33 -> 8165 | F34: =Data!A33 -> Ramsey, Jerod | G34: =Data!C33 -> 4/11/1992 | H34: =Data!H33 -> 44477 | I34: =Data!I33 -> 10/11/2021 | J34: =Data!J33 -> 244.8 | K34: =TODAY()-I34 -> 220 | L34: =Data!M33 -> 0 | M34: CLAIM PAID - EFT | N34: =VLOOKUP(M34,Table1[#All],3,FALSE) -> Claim Paid by EFT; | O34: =VLOOKUP(M34,Table1[#All],4,FALSE) -> Issue Date: | P34: 44482 | Q34: =VLOOKUP(M34,Table1[#All],5,FALSE) -> EFT# | R34: 9997740966 | S34: =VLOOKUP(M34,Table1[#All],6,FALSE) -> Bulk/Sep: | T34: Single | U34: =VLOOKUP(M34,Table1[#All],7,FALSE) -> Call Ref#: | V34: 5422 | W34: =VLOOKUP(M34,Table1[#All],8,FALSE) -> Cust Rep: | X34: Ey | Y34: =VLOOKUP(M34,Table1[#All],2,FALSE) -> Task Post Pmt Queue | Z34: =VLOOKUP(M34,Table1[#All],9,FALSE) -> Additional Notes: | AA34: Pd $105 Pt responsibility $'0' Clm #D212856143770. All codes are got paid. Eob requested | AB34: CLAIM CLOSED | AC34: YES | AD34: V Team | AE34: DK | AF34: 44579 | AG34: Follow-Up Complete
A35: =Data!K34 -> Cigna | B35: =Data!L34 -> 8002446224 | C35: =Data!D34 -> Kienia, Brooke | D35: =Data!F34 -> U53657370 | E35: =Data!B34 -> 7712 | F35: =Data!A34 -> Kienia, Brooke | G35: =Data!C34 -> 12/2/1990 | H35: =Data!H34 -> 44426 | I35: =Data!I34 -> 8/27/2021 | J35: =Data!J34 -> 273.2 | K35: =TODAY()-I35 -> 265 | L35: =Data!M34 -> 0 | M35: CLAIM PAID - EFT | N35: =VLOOKUP(M35,Table1[#All],3,FALSE) -> Claim Paid by EFT; | O35: =VLOOKUP(M35,Table1[#All],4,FALSE) -> Issue Date: | P35: 44438 | Q35: =VLOOKUP(M35,Table1[#All],5,FALSE) -> EFT# | R35: 128408296 | S35: =VLOOKUP(M35,Table1[#All],6,FALSE) -> Bulk/Sep: | T35: Bulk | U35: =VLOOKUP(M35,Table1[#All],7,FALSE) -> Call Ref#: | V35: 7115 | W35: =VLOOKUP(M35,Table1[#All],8,FALSE) -> Cust Rep: | X35: Roger | Y35: =VLOOKUP(M35,Table1[#All],2,FALSE) -> Task Post Pmt Queue | Z35: =VLOOKUP(M35,Table1[#All],9,FALSE) -> Additional Notes: | AA35: Rep States that Claim Paid,Claim No:E212426363940, paid amt$124 Patient Resp: NIL, All the lines paid on the claim. | AB35: CLAIM CLOSED | AC35: YES | AD35: V Team | AE35: MA | AF35: 44614 | AG35: Follow-Up Complete
A36: =Data!K35 -> Cigna | B36: =Data!L35 -> 8002446224 | C36: =Data!D35 -> Kienia, Jaxon | D36: =Data!F35 -> U53657370 | E36: =Data!B35 -> 7711 | F36: =Data!A35 -> Kienia, Jaxon | G36: =Data!C35 -> 12/2/1990 | H36: =Data!H35 -> 44426 | I36: =Data!I35 -> 8/27/2021 | J36: =Data!J35 -> 256.4 | K36: =TODAY()-I36 -> 265 | L36: =Data!M35 -> 0 | M36: CLAIM PAID - EFT | N36: =VLOOKUP(M36,Table1[#All],3,FALSE) -> Claim Paid by EFT; | O36: =VLOOKUP(M36,Table1[#All],4,FALSE) -> Issue Date: | P36: 44438 | Q36: =VLOOKUP(M36,Table1[#All],5,FALSE) -> EFT# | R36: 9996836027 | S36: =VLOOKUP(M36,Table1[#All],6,FALSE) -> Bulk/Sep: | T36: Bulk | U36: =VLOOKUP(M36,Table1[#All],7,FALSE) -> Call Ref#: | V36: 9985 | W36: =VLOOKUP(M36,Table1[#All],8,FALSE) -> Cust Rep: | X36: sara | Y36: =VLOOKUP(M36,Table1[#All],2,FALSE) -> Task Post Pmt Queue | Z36: =VLOOKUP(M36,Table1[#All],9,FALSE) -> Additional Notes: | AA36: EOB Requested//Get EOB - SN // Rep States that the Claim Paid,Claim No:D212426363980, paid amt$114 , All the lines paid on the claim. | AB36: CLAIM CLOSED | AC36: NO | AD36: V Team | AE36: AA | AF36: 2/28/2022 & 04/29/2022 | AG36: Follow-Up Complete
A37: =Data!K36 -> Cigna | B37: =Data!L36 -> 8002446224 | C37: =Data!D36 -> Al-Jehani, Afton | D37: =Data!F36 -> U50782273 | E37: =Data!B36 -> 7755 | F37: =Data!A36 -> Al-Jehani, Afton | G37: =Data!C36 -> 5/10/1992 | H37: =Data!H36 -> 44425 | I37: =Data!I36 -> 8/27/2021 | J37: =Data!J36 -> 325.2 | K37: =TODAY()-I37 -> 265 | L37: =Data!M36 -> 0 | M37: CLAIM PAID - EFT | N37: =VLOOKUP(M37,Table1[#All],3,FALSE) -> Claim Paid by EFT; | O37: =VLOOKUP(M37,Table1[#All],4,FALSE) -> Issue Date: | P37: 44439 | Q37: =VLOOKUP(M37,Table1[#All],5,FALSE) -> EFT# | R37: 6836028 | S37: =VLOOKUP(M37,Table1[#All],6,FALSE) -> Bulk/Sep: | T37: Single | U37: =VLOOKUP(M37,Table1[#All],7,FALSE) -> Call Ref#: | V37: 3545 | W37: =VLOOKUP(M37,Table1[#All],8,FALSE) -> Cust Rep: | X37: karissa | Y37: =VLOOKUP(M37,Table1[#All],2,FALSE) -> Task Post Pmt Queue | Z37: =VLOOKUP(M37,Table1[#All],9,FALSE) -> Additional Notes: | AA37: Pd $105 Pt responsibility $47.00 Clm #E2124726363920. All codes are got paid. Eob requested | AB37: CLAIM CLOSED | AC37: YES | AD37: V Team | AE37: DK | AF37: 44569 | AG37: Follow-Up Complete
A38: =Data!K37 -> DELTA DENTAL OF IOWA | B38: =Data!L37 -> 8005440718 | C38: =Data!D37 -> SHERMAN, STEPHANIE | D38: =Data!F37 -> 3199644 | E38: =Data!B37 -> 3523 | F38: =Data!A37 -> SHERMAN, STEPHANIE | G38: =Data!C37 -> 5/20/1977 | H38: =Data!H37 -> 44265 | I38: =Data!I37 -> 4/15/2021 | J38: =Data!J37 -> 230 | K38: =TODAY()-I38 -> 399 | L38: =Data!M37 -> 0 | M38: CLAIM PAID - EFT | N38: =VLOOKUP(M38,Table1[#All],3,FALSE) -> Claim Paid by EFT; | O38: =VLOOKUP(M38,Table1[#All],4,FALSE) -> Issue Date: | P38: 44321 | Q38: =VLOOKUP(M38,Table1[#All],5,FALSE) -> EFT# | R38: 921050501590 | S38: =VLOOKUP(M38,Table1[#All],6,FALSE) -> Bulk/Sep: | T38: Bulk | U38: =VLOOKUP(M38,Table1[#All],7,FALSE) -> Call Ref#: | V38: 021720211010 | W38: =VLOOKUP(M38,Table1[#All],8,FALSE) -> Cust Rep: | X38: jane | Y38: =VLOOKUP(M38,Table1[#All],2,FALSE) -> Task Post Pmt Queue | Z38: =VLOOKUP(M38,Table1[#All],9,FALSE) -> Additional Notes: | AA38: Rep states that the clm#202110611427-1 total amt$181 Pt resp paid on the Nil. | AB38: NV pending | AC38: YES | AD38: V Team | AE38: SN | AF38: 44609 | AG38: Follow-Up Complete
A39: =Data!K38 -> DELTA DENTAL OF MICHIGAN | B39: =Data!L38 -> 8005240149 | C39: =Data!D38 -> Tamsen , Robin | D39: =Data!F38 -> 394847319 | E39: =Data!B38 -> 5758 | F39: =Data!A38 -> Tamsen , Robin | G39: =Data!C38 -> 0 | H39: =Data!H38 -> 44498 | I39: =Data!I38 -> 12/11/2021 | J39: =Data!J38 -> 593.2 | K39: =TODAY()-I39 -> 159 | L39: =Data!M38 -> 0 | M39: PRTL - PAID EFT | N39: =VLOOKUP(M39,Table1[#All],3,FALSE) -> Claim Partially Paid by EFT; Add notes | O39: =VLOOKUP(M39,Table1[#All],4,FALSE) -> Issue Date: | P39: 44658 | Q39: =VLOOKUP(M39,Table1[#All],5,FALSE) -> EFT# | R39: 9907646801 | S39: =VLOOKUP(M39,Table1[#All],6,FALSE) -> Bulk/Sep: | T39: Sep | U39: =VLOOKUP(M39,Table1[#All],7,FALSE) -> Call Ref#: | V39: 2001833603 | W39: =VLOOKUP(M39,Table1[#All],8,FALSE) -> Cust Rep: | X39: Musheerah | Y39: =VLOOKUP(M39,Table1[#All],2,FALSE) -> Task Post Pmt Queue | Z39: =VLOOKUP(M39,Table1[#All],9,FALSE) -> Additional Notes: | AA39: Rep State Clm No:2111102306400,Paid Amt: 190.50,Patient Resp 292.50 Code D9230 is denied as it is not covered //Rep states that claim has been sent for reprosessing and the EOB has sent to the provideers mailing address. Rep Santo id #2001261703. ///REWORK & UPDATE - SN // Rep states that the clm #2112142747268, the claim is on hold because the ins is wondering that the member has the sec policy with him, there is a DPOW-CCHP is the sec policy for the patient, Rep says that we have to submitt with only the primay insurance policy which is Delta dental to allow the benifits of the claim. | AB39: 44698 | AC39: NO | AD39: V Team | AE39: AA | AF39: 44665 | AG39: Further Follow-Up
A40: =Data!K39 -> Delta Dental of Minnesota | B40: =Data!L39 -> 8004483815 | C40: =Data!D39 -> Tweedt, David | D40: =Data!F39 -> 916435131 | E40: =Data!B39 -> 8109 | F40: =Data!A39 -> Tweedt, David | G40: =Data!C39 -> 10/8/1961 | H40: =Data!H39 -> 44617 | I40: =Data!I39 -> 2/25/2022 | J40: =Data!J39 -> 890 | K40: =TODAY()-I40 -> 83 | L40: =Data!M39 -> 0 | M40: Select Status | N40: =VLOOKUP(M40,Table1[#All],3,FALSE) -> Note | O40: =VLOOKUP(M40,Table1[#All],4,FALSE) -> Q1 | Q40: =VLOOKUP(M40,Table1[#All],5,FALSE) -> Q2 | S40: =VLOOKUP(M40,Table1[#All],6,FALSE) -> Q3 | U40: =VLOOKUP(M40,Table1[#All],7,FALSE) -> Q4 | W40: =VLOOKUP(M40,Table1[#All],8,FALSE) -> Q5 | Y40: =VLOOKUP(M40,Table1[#All],2,FALSE) -> Action | Z40: =VLOOKUP(M40,Table1[#All],9,FALSE) -> Additional Notes: | AC40: Select | AD40: Select | AG40: Select
A41: =Data!K40 -> Delta Dental of Minnesota | B41: =Data!L40 -> 8004483815 | C41: =Data!D40 -> Penland, Teagan | D41: =Data!F40 -> 916516138 | E41: =Data!B40 -> 479 | F41: =Data!A40 -> Penland, Teagan | G41: =Data!C40 -> 11/16/1989 | H41: =Data!H40 -> 44538 | I41: =Data!I40 -> 12/14/2021 | J41: =Data!J40 -> 333.2 | K41: =TODAY()-I41 -> 156 | L41: =Data!M40 -> 0 | M41: DENIED - NOT COVERED | N41: =VLOOKUP(M41,Table1[#All],3,FALSE) -> Procedure is not a covered benefit; | O41: =VLOOKUP(M41,Table1[#All],4,FALSE) -> Why? | Q41: =VLOOKUP(M41,Table1[#All],5,FALSE) -> Call Ref#: | S41: =VLOOKUP(M41,Table1[#All],6,FALSE) -> Cust Rep: | U41: =VLOOKUP(M41,Table1[#All],7,FALSE) -> 0 | W41: =VLOOKUP(M41,Table1[#All],8,FALSE) -> 0 | Y41: =VLOOKUP(M41,Table1[#All],2,FALSE) -> Task Client - Denied Claim Queue | Z41: =VLOOKUP(M41,Table1[#All],9,FALSE) -> Additional Notes: | AA41: Clm # 2112152962231, This claim could not be processed since the submitted combination of member ID, first name and/or date of birth could not be located in our records. Please confirm the claim was submitted to the correct carrier and if so, resubmit the claim with the correct member ID (which may not be the Social Security Number), first name and date of birth. | AB41: NV pending | AC41: NO | AD41: V Team | AE41: MU | AF41: 44635 | AG41: Follow-Up Complete
A42: =Data!K41 -> Delta Dental of Minnesota | B42: =Data!L41 -> 8004483815 | C42: =Data!D41 -> Turner, Lukas | D42: =Data!F41 -> 916516138 | E42: =Data!B41 -> 5310 | F42: =Data!A41 -> Turner, Lukas | G42: =Data!C41 -> 11/16/1989 | H42: =Data!H41 -> 44482 | I42: =Data!I41 -> 12/11/2021 | J42: =Data!J41 -> 326 | K42: =TODAY()-I42 -> 159 | L42: =Data!M41 -> 0 | M42: PRTL - PAID EFT | N42: =VLOOKUP(M42,Table1[#All],3,FALSE) -> Claim Partially Paid by EFT; Add notes | O42: =VLOOKUP(M42,Table1[#All],4,FALSE) -> Issue Date: | P42: 44544 | Q42: =VLOOKUP(M42,Table1[#All],5,FALSE) -> EFT# | R42: 9100859245 | S42: =VLOOKUP(M42,Table1[#All],6,FALSE) -> Bulk/Sep: | T42: Single | U42: =VLOOKUP(M42,Table1[#All],7,FALSE) -> Call Ref#: | V42: 1538617207 | W42: =VLOOKUP(M42,Table1[#All],8,FALSE) -> Cust Rep: | X42: Siera | Y42: =VLOOKUP(M42,Table1[#All],2,FALSE) -> Task Post Pmt Queue | Z42: =VLOOKUP(M42,Table1[#All],9,FALSE) -> Additional Notes: | AA42: Rep states that clm #2112142789895, paid amt $196,Rcd on 12/14/2021 processed on the same day D0272 and D1208 is denied due to frequency and the freq for both is 1 per calender year, his dates for both the codes are 4/12/2021. ///Get the status - SN | AB42: NV pending | AC42: Mailed to Office | AD42: V Team | AE42: MU | AF42: 44656 | AG42: Follow-Up Complete
A43: =Data!K42 -> Delta Dental of Minnesota | B43: =Data!L42 -> 8004483815 | C43: =Data!D42 -> Mccarter , Markayla | D43: =Data!F42 -> 930691605 | E43: =Data!B42 -> 7084 | F43: =Data!A42 -> Mccarter , Markayla | G43: =Data!C42 -> 6/29/1992 | H43: =Data!H42 -> 44461 | I43: =Data!I42 -> 9/22/2021 | J43: =Data!J42 -> 0 | K43: =TODAY()-I43 -> 239 | L43: =Data!M42 -> 0 | M43: CNOF Active | N43: =VLOOKUP(M43,Table1[#All],3,FALSE) -> Claim not on file. Patient is active ; | O43: =VLOOKUP(M43,Table1[#All],4,FALSE) -> Payor ID & Address: | P43: 7000 | Q43: =VLOOKUP(M43,Table1[#All],5,FALSE) -> Fax # (If Fax Yes): | S43: =VLOOKUP(M43,Table1[#All],6,FALSE) -> TFL in Mnths: | T43: 12 Months from Dos | U43: =VLOOKUP(M43,Table1[#All],7,FALSE) -> Call Ref#: | V43: 1538986657 | W43: =VLOOKUP(M43,Table1[#All],8,FALSE) -> Cust Rep: | X43: ANGIE | Y43: =VLOOKUP(M43,Table1[#All],2,FALSE) -> Task Sub Pending Claims Queue | Z43: =VLOOKUP(M43,Table1[#All],9,FALSE) -> Additional Notes: | AA43: CNOF - patient Active. Address: PO Box# 9120, Farmington Hill MI -48333 | AB43: CLAIM CLOSED | AC43: NO | AD43: V Team | AE43: SF | AF43: 44693 | AG43: Follow-Up Complete
A44: =Data!K43 -> Delta Dental of Missouri | B44: =Data!L43 -> 8003358266 | C44: =Data!D43 -> Cordero, Ana | D44: =Data!F43 -> 598207509 | E44: =Data!B43 -> 821 | F44: =Data!A43 -> Cordero, Ana | G44: =Data!C43 -> 2/19/1989 | H44: =Data!H43 -> 44537 | I44: =Data!I43 -> 12/9/2021 | J44: =Data!J43 -> 61.2 | K44: =TODAY()-I44 -> 161 | L44: =Data!M43 -> 0 | M44: CNOF Not Active | N44: =VLOOKUP(M44,Table1[#All],3,FALSE) -> Patient not active/no active policy; | O44: =VLOOKUP(M44,Table1[#All],4,FALSE) -> Policy Term Dt: | P44: 44489 | Q44: =VLOOKUP(M44,Table1[#All],5,FALSE) -> Call Ref#: | R44: 9104701 | S44: =VLOOKUP(M44,Table1[#All],6,FALSE) -> Cust Rep: | T44: Siera | U44: =VLOOKUP(M44,Table1[#All],7,FALSE) -> 0 | W44: =VLOOKUP(M44,Table1[#All],8,FALSE) -> 0 | Y44: =VLOOKUP(M44,Table1[#All],2,FALSE) -> Task Denied Claims Queue | Z44: =VLOOKUP(M44,Table1[#All],9,FALSE) -> Additional Notes: | AA44: Rep states that the policy has been terminated for the patient, term date 10/20/2021. | AB44: TASK CREATED | AC44: NO | AD44: V Team | AE44: MU | AF44: 44629 | AG44: Follow-Up Complete
A45: =Data!K44 -> Delta Dental of Washington | B45: =Data!L44 -> 8005541907 | C45: =Data!D44 -> Mejia , Jason | D45: =Data!F44 -> 963587927 | E45: =Data!B44 -> 3001 | F45: =Data!A44 -> Mejia , Jason | G45: =Data!C44 -> 4/4/1993 | H45: =Data!H44 -> 44321 | I45: =Data!I44 -> 5/6/2021 | J45: =Data!J44 -> 782.8 | K45: =TODAY()-I45 -> 378 | L45: =Data!M44 -> 0 | M45: CLAIM PAID - EFT | N45: =VLOOKUP(M45,Table1[#All],3,FALSE) -> Claim Paid by EFT; | O45: =VLOOKUP(M45,Table1[#All],4,FALSE) -> Issue Date: | P45: 44329 | Q45: =VLOOKUP(M45,Table1[#All],5,FALSE) -> EFT# | R45: 11234233 | S45: =VLOOKUP(M45,Table1[#All],6,FALSE) -> Bulk/Sep: | T45: Single | U45: =VLOOKUP(M45,Table1[#All],7,FALSE) -> Call Ref#: | V45: 20220139569 | W45: =VLOOKUP(M45,Table1[#All],8,FALSE) -> Cust Rep: | X45: Morgan | Y45: =VLOOKUP(M45,Table1[#All],2,FALSE) -> Task Post Pmt Queue | Z45: =VLOOKUP(M45,Table1[#All],9,FALSE) -> Additional Notes: | AA45: Rep states that clm #202113031228400, paid amt $153.40, It is a direct deposit cased dt 5/13/2021, Pt res 153.40. | AB45: NV pending | AC45: YES | AD45: V Team | AE45: MU | AF45: 44621 | AG45: Follow-Up Complete
A46: =Data!K45 -> Delta Dental of Washington | B46: =Data!L45 -> 8005541907 | C46: =Data!D45 -> Clark, Charles | D46: =Data!F45 -> 963886263 | E46: =Data!B45 -> 1865 | F46: =Data!A45 -> Clark, Charles | G46: =Data!C45 -> 8/6/1982 | H46: =Data!H45 -> 44319 | I46: =Data!I45 -> 5/6/2021 | J46: =Data!J45 -> 610.8 | K46: =TODAY()-I46 -> 378 | L46: =Data!M45 -> 0 | M46: DENIED - NOT COVERED | N46: =VLOOKUP(M46,Table1[#All],3,FALSE) -> Procedure is not a covered benefit; | O46: =VLOOKUP(M46,Table1[#All],4,FALSE) -> Why? | P46: Not eligible at DOS | Q46: =VLOOKUP(M46,Table1[#All],5,FALSE) -> Call Ref#: | R46: 202200054335 | S46: =VLOOKUP(M46,Table1[#All],6,FALSE) -> Cust Rep: | T46: Kathleen | U46: =VLOOKUP(M46,Table1[#All],7,FALSE) -> 0 | W46: =VLOOKUP(M46,Table1[#All],8,FALSE) -> 0 | Y46: =VLOOKUP(M46,Table1[#All],2,FALSE) -> Task Client - Denied Claim Queue | Z46: =VLOOKUP(M46,Table1[#All],9,FALSE) -> Additional Notes: | AA46: Rep State that Claim Denied as patient is Inactive at the time of service,Termination Date:04/30/2021,Last Active Date:03/23/2020, Effective Date: 03/23/2020, Claim No:202113031229700, Processed & Denied Date: 05/28/2021, Patient Resp:$610.80 | AB46: NV pending | AC46: YES | AD46: V Team | AE46: AA | AF46: 44588 | AG46: Follow-Up Complete
A47: =Data!K46 -> Delta Dental of Washington | B47: =Data!L46 -> 8005541907 | C47: =Data!D46 -> Syas, Brenae | D47: =Data!F46 -> 962760622 | E47: =Data!B46 -> 5461 | F47: =Data!A46 -> Syas, Brenae | G47: =Data!C46 -> 2/8/1998 | H47: =Data!H46 -> 44301 | I47: =Data!I46 -> 4/15/2021 | J47: =Data!J46 -> 396 | K47: =TODAY()-I47 -> 399 | L47: =Data!M46 -> 0 | M47: CLAIM PAID - EFT | N47: =VLOOKUP(M47,Table1[#All],3,FALSE) -> Claim Paid by EFT; | O47: =VLOOKUP(M47,Table1[#All],4,FALSE) -> Issue Date: | P47: 44308 | Q47: =VLOOKUP(M47,Table1[#All],5,FALSE) -> EFT# | R47: 11207602 | S47: =VLOOKUP(M47,Table1[#All],6,FALSE) -> Bulk/Sep: | T47: Bulk | U47: =VLOOKUP(M47,Table1[#All],7,FALSE) -> Call Ref#: | V47: 202200054382 | W47: =VLOOKUP(M47,Table1[#All],8,FALSE) -> Cust Rep: | X47: Kathleen | Y47: =VLOOKUP(M47,Table1[#All],2,FALSE) -> Task Post Pmt Queue | Z47: =VLOOKUP(M47,Table1[#All],9,FALSE) -> Additional Notes: | AA47: Rep State that Claim Paid,Claim No: 202110631644400, Paid Amt:$239.40,Paid by Bulk(Bulk Amt: $855.90) , Patient Resp:$76.60 | AB47: NV pending | AC47: YES | AD47: V Team | AE47: AA | AF47: 44588 | AG47: Follow-Up Complete
A48: =Data!K47 -> Delta Dental of Washington | B48: =Data!L47 -> 8005541907 | C48: =Data!D47 -> Mejia, Viannie | D48: =Data!F47 -> 963587927 | E48: =Data!B47 -> 2870 | F48: =Data!A47 -> Mejia, Viannie | G48: =Data!C47 -> 4/4/1993 | H48: =Data!H47 -> 44301 | I48: =Data!I47 -> 4/15/2021 | J48: =Data!J47 -> 532 | K48: =TODAY()-I48 -> 399 | L48: =Data!M47 -> 0 | M48: OTHER | N48: =VLOOKUP(M48,Table1[#All],3,FALSE) -> Write information in Addl Notes | O48: =VLOOKUP(M48,Table1[#All],4,FALSE) -> Call Ref#: | Q48: =VLOOKUP(M48,Table1[#All],5,FALSE) -> Cust Rep: | S48: =VLOOKUP(M48,Table1[#All],6,FALSE) -> 0 | U48: =VLOOKUP(M48,Table1[#All],7,FALSE) | W48: =VLOOKUP(M48,Table1[#All],8,FALSE) | Y48: =VLOOKUP(M48,Table1[#All],2,FALSE) -> Team Lead to review & Follow-Up | Z48: =VLOOKUP(M48,Table1[#All],9,FALSE) -> Additional Notes: | AB48: CLAIM CLOSED | AC48: NO | AD48: V Team | AE48: MU | AF48: 44627 | AG48: Follow-Up Complete
A49: =Data!K48 -> Delta Dental of Washington | B49: =Data!L48 -> 8005541907 | C49: =Data!D48 -> Mejia , Jason | D49: =Data!F48 -> 963587927 | E49: =Data!B48 -> 3001 | F49: =Data!A48 -> Mejia , Jason | G49: =Data!C48 -> 4/4/1993 | H49: =Data!H48 -> 44299 | I49: =Data!I48 -> 4/15/2021 | J49: =Data!J48 -> 748 | K49: =TODAY()-I49 -> 399 | L49: =Data!M48 -> 0 | M49: CLAIM PAID - EFT | N49: =VLOOKUP(M49,Table1[#All],3,FALSE) -> Claim Paid by EFT; | O49: =VLOOKUP(M49,Table1[#All],4,FALSE) -> Issue Date: | P49: 44308 | Q49: =VLOOKUP(M49,Table1[#All],5,FALSE) -> EFT# | R49: 11207602 | S49: =VLOOKUP(M49,Table1[#All],6,FALSE) -> Bulk/Sep: | T49: Bulk | U49: =VLOOKUP(M49,Table1[#All],7,FALSE) -> Call Ref#: | V49: 20220139569 | W49: =VLOOKUP(M49,Table1[#All],8,FALSE) -> Cust Rep: | X49: Morgan | Y49: =VLOOKUP(M49,Table1[#All],2,FALSE) -> Task Post Pmt Queue | Z49: =VLOOKUP(M49,Table1[#All],9,FALSE) -> Additional Notes: | AA49: Rep states that clm #202110631649100, paid amt $411.30, It is a bulk amt $855.90, PR aamt $195.70, It’s a direct deposit, cashed dt 4/22/2021, There are 3 codes on the claim which has been paid. | AB49: NV pending | AC49: YES | AD49: V Team | AE49: MU | AF49: 44627 | AG49: Follow-Up Complete
A50: =Data!K49 -> Delta Dental of Washington | B50: =Data!L49 -> 8005541907 | C50: =Data!D49 -> Mejia , Jason | D50: =Data!F49 -> 963587927 | E50: =Data!B49 -> 3001 | F50: =Data!A49 -> Mejia , Jason | G50: =Data!C49 -> 4/4/1993 | H50: =Data!H49 -> 44273 | I50: =Data!I49 -> 3/23/2021 | J50: =Data!J49 -> 227.6 | K50: =TODAY()-I50 -> 422 | L50: =Data!M49 -> 0 | M50: CLAIM PAID - EFT | N50: =VLOOKUP(M50,Table1[#All],3,FALSE) -> Claim Paid by EFT; | O50: =VLOOKUP(M50,Table1[#All],4,FALSE) -> Issue Date: | P50: 44287 | Q50: =VLOOKUP(M50,Table1[#All],5,FALSE) -> EFT# | R50: 11181248 | S50: =VLOOKUP(M50,Table1[#All],6,FALSE) -> Bulk/Sep: | T50: Bulk | U50: =VLOOKUP(M50,Table1[#All],7,FALSE) -> Call Ref#: | V50: 20220139569 | W50: =VLOOKUP(M50,Table1[#All],8,FALSE) -> Cust Rep: | X50: Morgan | Y50: =VLOOKUP(M50,Table1[#All],2,FALSE) -> Task Post Pmt Queue | Z50: =VLOOKUP(M50,Table1[#All],9,FALSE) -> Additional Notes: | AA50: Rep states that clm #202108332109200, paid amt $178, Patient res NIL, It’s a direct deposit cashed dt 4/1/2021, there are 6 codes on the claim which is paid. | AB50: NV pending | AC50: YES | AD50: V Team | AE50: MU | AF50: 44627 | AG50: Follow-Up Complete
A51: =Data!K50 -> Delta Dental of Washington | B51: =Data!L50 -> 8005541907 | C51: =Data!D50 -> Mejia, Viannie | D51: =Data!F50 -> 963587927 | E51: =Data!B50 -> 2870 | F51: =Data!A50 -> Mejia, Viannie | G51: =Data!C50 -> 4/4/1993 | H51: =Data!H50 -> 44273 | I51: =Data!I50 -> 3/23/2021 | J51: =Data!J50 -> 227.6 | K51: =TODAY()-I51 -> 422 | L51: =Data!M50 -> 0 | M51: CLAIM PAID - EFT | N51: =VLOOKUP(M51,Table1[#All],3,FALSE) -> Claim Paid by EFT; | O51: =VLOOKUP(M51,Table1[#All],4,FALSE) -> Issue Date: | P51: 44287 | Q51: =VLOOKUP(M51,Table1[#All],5,FALSE) -> EFT# | R51: 11181248 | S51: =VLOOKUP(M51,Table1[#All],6,FALSE) -> Bulk/Sep: | T51: Bulk | U51: =VLOOKUP(M51,Table1[#All],7,FALSE) -> Call Ref#: | V51: 202200139640 | W51: =VLOOKUP(M51,Table1[#All],8,FALSE) -> Cust Rep: | X51: Morgan | Y51: =VLOOKUP(M51,Table1[#All],2,FALSE) -> Task Post Pmt Queue | Z51: =VLOOKUP(M51,Table1[#All],9,FALSE) -> Additional Notes: | AA51: Rep states that clm #202108332129600, paid amt $178, patient res NIL, it’s a bulk payment $366, there are 6lines on the claim which has been paid. | AB51: NV pending | AC51: YES | AD51: V Team | AE51: MU | AF51: 44627 | AG51: Follow-Up Complete
A52: =Data!K51 -> Delta Dental Of Wisconsin | B52: =Data!L51 -> 8002363712 | C52: =Data!D51 -> Legree, Cristie | D52: =Data!F51 -> 08068800996 | E52: =Data!B51 -> 6277 | F52: =Data!A51 -> Legree, Cristie | G52: =Data!C51 -> 2/26/1987 | H52: =Data!H51 -> 44651 | I52: =Data!I51 -> 4/1/2022 | J52: =Data!J51 -> 82.8 | K52: =TODAY()-I52 -> 48 | L52: =Data!M51 -> 0 | M52: Select Status | N52: =VLOOKUP(M52,Table1[#All],3,FALSE) -> Note | O52: =VLOOKUP(M52,Table1[#All],4,FALSE) -> Q1 | Q52: =VLOOKUP(M52,Table1[#All],5,FALSE) -> Q2 | S52: =VLOOKUP(M52,Table1[#All],6,FALSE) -> Q3 | U52: =VLOOKUP(M52,Table1[#All],7,FALSE) -> Q4 | W52: =VLOOKUP(M52,Table1[#All],8,FALSE) -> Q5 | Y52: =VLOOKUP(M52,Table1[#All],2,FALSE) -> Action | Z52: =VLOOKUP(M52,Table1[#All],9,FALSE) -> Additional Notes: | AC52: Select | AD52: Select | AG52: Select
A53: =Data!K52 -> Delta Dental Of Wisconsin | B53: =Data!L52 -> 8002363712 | C53: =Data!D52 -> Barber, Jazaria | D53: =Data!F52 -> 08046078168 | E53: =Data!B52 -> 9286 | F53: =Data!A52 -> Barber, Jazaria | G53: =Data!C52 -> 2/24/2009 | H53: =Data!H52 -> 44643 | I53: =Data!I52 -> 3/24/2022 | J53: =Data!J52 -> 1480.4 | K53: =TODAY()-I53 -> 56 | L53: =Data!M52 -> 0 | M53: Select Status | N53: =VLOOKUP(M53,Table1[#All],3,FALSE) -> Note | O53: =VLOOKUP(M53,Table1[#All],4,FALSE) -> Q1 | Q53: =VLOOKUP(M53,Table1[#All],5,FALSE) -> Q2 | S53: =VLOOKUP(M53,Table1[#All],6,FALSE) -> Q3 | U53: =VLOOKUP(M53,Table1[#All],7,FALSE) -> Q4 | W53: =VLOOKUP(M53,Table1[#All],8,FALSE) -> Q5 | Y53: =VLOOKUP(M53,Table1[#All],2,FALSE) -> Action | Z53: =VLOOKUP(M53,Table1[#All],9,FALSE) -> Additional Notes: | AC53: Select | AD53: Select | AG53: Select
A54: =Data!K53 -> Delta Dental Of Wisconsin | B54: =Data!L53 -> 8002363712 | C54: =Data!D53 -> Casarez , Romeo | D54: =Data!F53 -> 08037992525 | E54: =Data!B53 -> 8966 | F54: =Data!A53 -> Casarez , Romeo | G54: =Data!C53 -> 4/6/1985 | H54: =Data!H53 -> 44622 | I54: =Data!I53 -> 3/2/2022 | J54: =Data!J53 -> 1183.2 | K54: =TODAY()-I54 -> 78 | L54: =Data!M53 -> 0 | M54: Select Status | N54: =VLOOKUP(M54,Table1[#All],3,FALSE) -> Note | O54: =VLOOKUP(M54,Table1[#All],4,FALSE) -> Q1 | Q54: =VLOOKUP(M54,Table1[#All],5,FALSE) -> Q2 | S54: =VLOOKUP(M54,Table1[#All],6,FALSE) -> Q3 | U54: =VLOOKUP(M54,Table1[#All],7,FALSE) -> Q4 | W54: =VLOOKUP(M54,Table1[#All],8,FALSE) -> Q5 | Y54: =VLOOKUP(M54,Table1[#All],2,FALSE) -> Action | Z54: =VLOOKUP(M54,Table1[#All],9,FALSE) -> Additional Notes: | AC54: Select | AD54: Select | AG54: Select
A55: =Data!K54 -> Delta Dental Of Wisconsin | B55: =Data!L54 -> 8002363712 | C55: =Data!D54 -> Anadell, Carrie | D55: =Data!F54 -> 08092951962 | E55: =Data!B54 -> 9079 | F55: =Data!A54 -> Anadell, Carrie | G55: =Data!C54 -> 6/20/1979 | H55: =Data!H54 -> 44607 | I55: =Data!I54 -> 2/25/2022 | J55: =Data!J54 -> 220.4 | K55: =TODAY()-I55 -> 83 | L55: =Data!M54 -> 0 | M55: Select Status | N55: =VLOOKUP(M55,Table1[#All],3,FALSE) -> Note | O55: =VLOOKUP(M55,Table1[#All],4,FALSE) -> Q1 | Q55: =VLOOKUP(M55,Table1[#All],5,FALSE) -> Q2 | S55: =VLOOKUP(M55,Table1[#All],6,FALSE) -> Q3 | U55: =VLOOKUP(M55,Table1[#All],7,FALSE) -> Q4 | W55: =VLOOKUP(M55,Table1[#All],8,FALSE) -> Q5 | Y55: =VLOOKUP(M55,Table1[#All],2,FALSE) -> Action | Z55: =VLOOKUP(M55,Table1[#All],9,FALSE) -> Additional Notes: | AC55: Select | AD55: Select | AG55: Select
A56: =Data!K55 -> Delta Dental Of Wisconsin | B56: =Data!L55 -> 8002363712 | C56: =Data!D55 -> Wooden, Jasmine | D56: =Data!F55 -> 08081760881 | E56: =Data!B55 -> 4735 | F56: =Data!A55 -> Wooden, Jasmine | G56: =Data!C55 -> 7/27/1990 | H56: =Data!H55 -> 44587 | I56: =Data!I55 -> 2/1/2022 | J56: =Data!J55 -> 432 | K56: =TODAY()-I56 -> 107 | L56: =Data!M55 -> 0 | M56: CLAIM PAID - EFT | N56: =VLOOKUP(M56,Table1[#All],3,FALSE) -> Claim Paid by EFT; | O56: =VLOOKUP(M56,Table1[#All],4,FALSE) -> Issue Date: | P56: 44685 | Q56: =VLOOKUP(M56,Table1[#All],5,FALSE) -> EFT# | R56: "1088874 | S56: =VLOOKUP(M56,Table1[#All],6,FALSE) -> Bulk/Sep: | T56: Bulk | U56: =VLOOKUP(M56,Table1[#All],7,FALSE) -> Call Ref#: | V56: Char05062022 | W56: =VLOOKUP(M56,Table1[#All],8,FALSE) -> Cust Rep: | X56: Char | Y56: =VLOOKUP(M56,Table1[#All],2,FALSE) -> Task Post Pmt Queue | Z56: =VLOOKUP(M56,Table1[#All],9,FALSE) -> Additional Notes: | AA56: Rep State that Claim Paid,Paid Amt: $232,Patient Resp: $106,Paid by Direct Deposit,Rep Also State that Elisha from Dental office Called on 04/25/2022 and said to Changed the Date to 01/25/2022 for Tretment and Insurance Denied for 01/26/2022 as Duplicate and Paid for 01/25/2022 | AB56: CLAIM CLOSED | AC56: YES | AD56: V Team | AE56: AA | AF56: 44687 | AG56: Follow-Up Complete
A57: =Data!K56 -> Delta Dental Of Wisconsin | B57: =Data!L56 -> 8002363712 | C57: =Data!D56 -> Malone , Kalahni | D57: =Data!F56 -> 08013357739 | E57: =Data!B56 -> 6339 | F57: =Data!A56 -> Malone , Kalahni | G57: =Data!C56 -> 4/11/1991 | H57: =Data!H56 -> 44457 | I57: =Data!I56 -> 12/11/2021 | J57: =Data!J56 -> 227.6 | K57: =TODAY()-I57 -> 159 | L57: =Data!M56 -> 0 | M57: DENIED - NOT COVERED | N57: =VLOOKUP(M57,Table1[#All],3,FALSE) -> Procedure is not a covered benefit; | O57: =VLOOKUP(M57,Table1[#All],4,FALSE) -> Why? | P57: Not covered under pt plan | Q57: =VLOOKUP(M57,Table1[#All],5,FALSE) -> Call Ref#: | R57: Can | S57: =VLOOKUP(M57,Table1[#All],6,FALSE) -> Cust Rep: | T57: can 3/18/2022 | U57: =VLOOKUP(M57,Table1[#All],7,FALSE) -> 0 | W57: =VLOOKUP(M57,Table1[#All],8,FALSE) -> 0 | Y57: =VLOOKUP(M57,Table1[#All],2,FALSE) -> Task Client - Denied Claim Queue | Z57: =VLOOKUP(M57,Table1[#All],9,FALSE) -> Additional Notes: | AA57: Rep states that clm #2129240113, clm has been denied due to not covered under patient plan & COB. | AB57: NV pending | AC57: YES | AD57: V Team | AE57: MU | AF57: 44627 | AG57: Follow-Up Complete
A58: =Data!K57 -> Delta Dental Of Wisconsin | B58: =Data!L57 -> 8002363712 | C58: =Data!D57 -> Sesham Haribabu, Saigopal | D58: =Data!F57 -> 08005831007 | E58: =Data!B57 -> 8250 | F58: =Data!A57 -> Sesham Haribabu, Saigopal | G58: =Data!C57 -> 6/2/1980 | H58: =Data!H57 -> 44495 | I58: =Data!I57 -> 12/11/2021 | J58: =Data!J57 -> 332.4 | K58: =TODAY()-I58 -> 159 | L58: =Data!M57 -> 0 | M58: CNOF Active | N58: =VLOOKUP(M58,Table1[#All],3,FALSE) -> Claim not on file. Patient is active ; | O58: =VLOOKUP(M58,Table1[#All],4,FALSE) -> Payor ID & Address: | P58: 39069 | Q58: =VLOOKUP(M58,Table1[#All],5,FALSE) -> Fax # (If Fax Yes): | S58: =VLOOKUP(M58,Table1[#All],6,FALSE) -> TFL in Mnths: | T58: 15 month from dos | U58: =VLOOKUP(M58,Table1[#All],7,FALSE) -> Call Ref#: | V58: can 3/18/2022 | W58: =VLOOKUP(M58,Table1[#All],8,FALSE) -> Cust Rep: | X58: Can | Y58: =VLOOKUP(M58,Table1[#All],2,FALSE) -> Task Sub Pending Claims Queue | Z58: =VLOOKUP(M58,Table1[#All],9,FALSE) -> Additional Notes: | AA58: Claim Resubmitted electronically on 05/06/2022 - SN // Rep states that the clm is not on file for the Dos, pat is active from 8/1/2021, we can submitt claim trough electronically or by mailing add P.O box 828, Stevens Point, WI 54481. | AB58: 44701 | AC58: NO | AD58: V Team | AE58: MU | AF58: 44628 | AG58: Further Follow-Up
A59: =Data!K58 -> Delta Dental Of Wisconsin | B59: =Data!L58 -> 8002363712 | C59: =Data!D58 -> Malone , Kalahni | D59: =Data!F58 -> 08013357739 | E59: =Data!B58 -> 6339 | F59: =Data!A58 -> Malone , Kalahni | G59: =Data!C58 -> 4/11/1991 | H59: =Data!H58 -> 44536 | I59: =Data!I58 -> 2/15/2022 | J59: =Data!J58 -> 712 | K59: =TODAY()-I59 -> 93 | L59: =Data!M58 -> 0 | M59: Select Status | N59: =VLOOKUP(M59,Table1[#All],3,FALSE) -> Note | O59: =VLOOKUP(M59,Table1[#All],4,FALSE) -> Q1 | Q59: =VLOOKUP(M59,Table1[#All],5,FALSE) -> Q2 | S59: =VLOOKUP(M59,Table1[#All],6,FALSE) -> Q3 | U59: =VLOOKUP(M59,Table1[#All],7,FALSE) -> Q4 | W59: =VLOOKUP(M59,Table1[#All],8,FALSE) -> Q5 | Y59: =VLOOKUP(M59,Table1[#All],2,FALSE) -> Action | Z59: =VLOOKUP(M59,Table1[#All],9,FALSE) -> Additional Notes: | AC59: Select | AD59: Select | AG59: Select
A60: =Data!K59 -> Delta Dental Of Wisconsin | B60: =Data!L59 -> 8002363712 | C60: =Data!D59 -> Gordon, Jamie | D60: =Data!F59 -> 08007200266 | E60: =Data!B59 -> 8537 | F60: =Data!A59 -> Gordon, Jamie | G60: =Data!C59 -> 2/15/1972 | H60: =Data!H59 -> 44524 | I60: =Data!I59 -> 12/1/2021 | J60: =Data!J59 -> 199.2 | K60: =TODAY()-I60 -> 169 | L60: =Data!M59 -> 0 | M60: CLAIM PAID - EFT | N60: =VLOOKUP(M60,Table1[#All],3,FALSE) -> Claim Paid by EFT; | O60: =VLOOKUP(M60,Table1[#All],4,FALSE) -> Issue Date: | P60: 44538 | Q60: =VLOOKUP(M60,Table1[#All],5,FALSE) -> EFT# | R60: 1050566 | S60: =VLOOKUP(M60,Table1[#All],6,FALSE) -> Bulk/Sep: | T60: Bulk | U60: =VLOOKUP(M60,Table1[#All],7,FALSE) -> Call Ref#: | V60: Lisa 3/8/2022 | W60: =VLOOKUP(M60,Table1[#All],8,FALSE) -> Cust Rep: | X60: Lisa | Y60: =VLOOKUP(M60,Table1[#All],2,FALSE) -> Task Post Pmt Queue | Z60: =VLOOKUP(M60,Table1[#All],9,FALSE) -> Additional Notes: | AA60: Rep states that clm #2-1336-398-73, paid amt $145.20, It’s a direct deposit, 2codes on the claim has been paid, Bulk amt $1,883.50. | AB60: NV pending | AC60: YES | AD60: V Team | AE60: MU | AF60: 44628 | AG60: Follow-Up Complete
A61: =Data!K60 -> Delta Dental Of Wisconsin | B61: =Data!L60 -> 8002363712 | C61: =Data!D60 -> Rubach , Gretchen | D61: =Data!F60 -> 08082233537 | E61: =Data!B60 -> 7397 | F61: =Data!A60 -> Rubach , Gretchen | G61: =Data!C60 -> 3/21/1972 | H61: =Data!H60 -> 44519 | I61: =Data!I60 -> 12/1/2021 | J61: =Data!J60 -> 133.2 | K61: =TODAY()-I61 -> 169 | L61: =Data!M60 -> 0 | M61: CLAIM PAID - EFT | N61: =VLOOKUP(M61,Table1[#All],3,FALSE) -> Claim Paid by EFT; | O61: =VLOOKUP(M61,Table1[#All],4,FALSE) -> Issue Date: | P61: 44538 | Q61: =VLOOKUP(M61,Table1[#All],5,FALSE) -> EFT# | R61: 1050566 | S61: =VLOOKUP(M61,Table1[#All],6,FALSE) -> Bulk/Sep: | T61: Bulk | U61: =VLOOKUP(M61,Table1[#All],7,FALSE) -> Call Ref#: | V61: Lisa 3/8/2022 | W61: =VLOOKUP(M61,Table1[#All],8,FALSE) -> Cust Rep: | X61: Lisa | Y61: =VLOOKUP(M61,Table1[#All],2,FALSE) -> Task Post Pmt Queue | Z61: =VLOOKUP(M61,Table1[#All],9,FALSE) -> Additional Notes: | AA61: Rep states that clm #2-1336-399-64, paid amt $86.40, It’s a direct deposit, Patient res $21.60, There is one code on the claim which is paid. | AB61: NV pending | AC61: YES | AD61: V Team | AE61: MU | AF61: 44628 | AG61: Follow-Up Complete
A62: =Data!K61 -> Delta Dental Of Wisconsin | B62: =Data!L61 -> 8002363712 | C62: =Data!D61 -> Ramirez , Jazmin | D62: =Data!F61 -> 011405227 | E62: =Data!B61 -> 8419 | F62: =Data!A61 -> Ramirez , Jazmin | G62: =Data!C61 -> 1/9/1992 | H62: =Data!H61 -> 44511 | I62: =Data!I61 -> 12/9/2021 | J62: =Data!J61 -> 61.2 | K62: =TODAY()-I62 -> 161 | L62: =Data!M61 -> 0 | M62: DENIED - PRM PAID MAX | N62: =VLOOKUP(M62,Table1[#All],3,FALSE) -> Primary Ins paid Max allowable; | O62: =VLOOKUP(M62,Table1[#All],4,FALSE) -> Call Ref#: | P62: Cat 3/9/2022 | Q62: =VLOOKUP(M62,Table1[#All],5,FALSE) -> Cust Rep: | R62: Cat | S62: =VLOOKUP(M62,Table1[#All],6,FALSE) -> 0 | U62: =VLOOKUP(M62,Table1[#All],7,FALSE) -> 0 | W62: =VLOOKUP(M62,Table1[#All],8,FALSE) -> 0 | Y62: =VLOOKUP(M62,Table1[#All],2,FALSE) -> Task Post Pmt Queue | Z62: =VLOOKUP(M62,Table1[#All],9,FALSE) -> Additional Notes: | AA62: Coordination of Benefits | AB62: CLAIM CLOSED | AC62: YES | AD62: V Team | AE62: MU | AF62: 44629 | AG62: Follow-Up Complete
A63: =Data!K62 -> Delta Dental Of Wisconsin | B63: =Data!L62 -> 8002363712 | C63: =Data!D62 -> Pedersen, Arianna | D63: =Data!F62 -> 08041397221 | E63: =Data!B62 -> 7216 | F63: =Data!A62 -> Pedersen, Arianna | G63: =Data!C62 -> 10/28/1974 | H63: =Data!H62 -> 44455 | I63: =Data!I62 -> 10/15/2021 | J63: =Data!J62 -> 342 | K63: =TODAY()-I63 -> 216 | L63: =Data!M62 -> 0 | M63: CLAIM PAID - CHK | N63: =VLOOKUP(M63,Table1[#All],3,FALSE) -> Claim Paid by Check; | O63: =VLOOKUP(M63,Table1[#All],4,FALSE) -> Issue Date: | P63: 44636 | Q63: =VLOOKUP(M63,Table1[#All],5,FALSE) -> CHK# | R63: 1656809 | S63: =VLOOKUP(M63,Table1[#All],6,FALSE) -> Bulk/Sep: | T63: Sep | U63: =VLOOKUP(M63,Table1[#All],7,FALSE) -> Call Ref#: | W63: =VLOOKUP(M63,Table1[#All],8,FALSE) -> Cust Rep: | Y63: =VLOOKUP(M63,Table1[#All],2,FALSE) -> Task Cashed Chk Queue | Z63: =VLOOKUP(M63,Table1[#All],9,FALSE) -> Additional Notes: | AA63: Rep states confirm that the doctor is not an in-network so the payment made to subscriber, we need to call to the subscriber for the cashed date. Rep Crista, id #crista 4/5/2022.///CHECK WHY IT WAS SENT TO SUBSCRIBER AND CASHED DATE ? // CLM # 2206930006; Pd Amt $227; Paid to Subscriber. | AB63: TASK CREATED | AC63: YES | AD63: V Team | AE63: MU | AF63: 44656 | AG63: Follow-Up Complete
A64: =Data!K63 -> Delta Dental Of Wisconsin | B64: =Data!L63 -> 8002363712 | C64: =Data!D63 -> Malone , Kaleyah | D64: =Data!F63 -> 08094978110 | E64: =Data!B63 -> 6340 | F64: =Data!A63 -> Malone , Kaleyah | G64: =Data!C63 -> 4/11/1991 | H64: =Data!H63 -> 44457 | I64: =Data!I63 -> 9/21/2021 | J64: =Data!J63 -> 138 | K64: =TODAY()-I64 -> 240 | L64: =Data!M63 -> 0 | M64: CLAIM PAID - CHK | N64: =VLOOKUP(M64,Table1[#All],3,FALSE) -> Claim Paid by Check; | O64: =VLOOKUP(M64,Table1[#All],4,FALSE) -> Issue Date: | P64: 44468 | Q64: =VLOOKUP(M64,Table1[#All],5,FALSE) -> CHK# | R64: 1008274 | S64: =VLOOKUP(M64,Table1[#All],6,FALSE) -> Bulk/Sep: | T64: Single | U64: =VLOOKUP(M64,Table1[#All],7,FALSE) -> Call Ref#: | V64: Lisa 3/8/2022 | W64: =VLOOKUP(M64,Table1[#All],8,FALSE) -> Cust Rep: | X64: Lisa | Y64: =VLOOKUP(M64,Table1[#All],2,FALSE) -> Task Cashed Chk Queue | Z64: =VLOOKUP(M64,Table1[#All],9,FALSE) -> Additional Notes: | AA64: Rep states that clm #2126547242, paid amt $80, it’s a direct deposit, D1208 - Denied due to Age Limitataion. | AB64: NV pending | AC64: YES | AD64: V Team | AE64: MU | AF64: 44628 | AG64: Follow-Up Complete
A65: =Data!K64 -> Delta Dental Of Wisconsin | B65: =Data!L64 -> 8002363712 | C65: =Data!D64 -> Vanderwielen, Brenda | D65: =Data!F64 -> 08025116974 | E65: =Data!B64 -> 7729 | F65: =Data!A64 -> Vanderwielen, Brenda | G65: =Data!C64 -> 9/3/1975 | H65: =Data!H64 -> 44419 | I65: =Data!I64 -> 8/16/2021 | J65: =Data!J64 -> 61.2 | K65: =TODAY()-I65 -> 276 | L65: =Data!M64 -> 0 | M65: CLAIM PAID - EFT | N65: =VLOOKUP(M65,Table1[#All],3,FALSE) -> Claim Paid by EFT; | O65: =VLOOKUP(M65,Table1[#All],4,FALSE) -> Issue Date: | P65: 44433 | Q65: =VLOOKUP(M65,Table1[#All],5,FALSE) -> EFT# | R65: 988435 | S65: =VLOOKUP(M65,Table1[#All],6,FALSE) -> Bulk/Sep: | T65: Bulk | U65: =VLOOKUP(M65,Table1[#All],7,FALSE) -> Call Ref#: | V65: Ami01272022 | W65: =VLOOKUP(M65,Table1[#All],8,FALSE) -> Cust Rep: | X65: Ami | Y65: =VLOOKUP(M65,Table1[#All],2,FALSE) -> Task Post Pmt Queue | Z65: =VLOOKUP(M65,Table1[#All],9,FALSE) -> Additional Notes: | AA65: Rep State that Claim Paid,Paid Amt:$23, Claim No: 2-1229-385-28, Paid by Bulk(Bulk Amt:$2446.60), Patient Resp:$25 | AB65: NV pending | AC65: YES | AD65: V Team | AE65: AA | AF65: 44588 | AG65: Follow-Up Complete
A66: =Data!K65 -> Delta Dental Of Wisconsin | B66: =Data!L65 -> 8002363712 | C66: =Data!D65 -> Sanchez Esquive , Israel | D66: =Data!F65 -> 08066254638 | E66: =Data!B65 -> 4691 | F66: =Data!A65 -> Sanchez Esquive , Israel | G66: =Data!C65 -> 9/29/1984 | H66: =Data!H65 -> 44408 | I66: =Data!I65 -> 7/31/2021 | J66: =Data!J65 -> 2750.4 | K66: =TODAY()-I66 -> 292 | L66: =Data!M65 -> 0 | M66: CNOF Not Active | N66: =VLOOKUP(M66,Table1[#All],3,FALSE) -> Patient not active/no active policy; | O66: =VLOOKUP(M66,Table1[#All],4,FALSE) -> Policy Term Dt: | P66: 44316 | Q66: =VLOOKUP(M66,Table1[#All],5,FALSE) -> Call Ref#: | R66: Amalia01272022 | S66: =VLOOKUP(M66,Table1[#All],6,FALSE) -> Cust Rep: | T66: Amalia | U66: =VLOOKUP(M66,Table1[#All],7,FALSE) -> 0 | W66: =VLOOKUP(M66,Table1[#All],8,FALSE) -> 0 | Y66: =VLOOKUP(M66,Table1[#All],2,FALSE) -> Task Denied Claims Queue | Z66: =VLOOKUP(M66,Table1[#All],9,FALSE) -> Additional Notes: | AA66: Rep State that CNOF Patient Inactive, Effective Date:03/01/2018, Last Active Date:04/30/2021 | AB66: TASK CREATED | AC66: NO | AD66: V Team | AE66: AA | AF66: 44588 | AG66: Follow-Up Complete
A67: =Data!K66 -> Delta Dental Of Wisconsin | B67: =Data!L66 -> 8002363712 | C67: =Data!D66 -> Kyles , Amari | D67: =Data!F66 -> 08058488409 | E67: =Data!B66 -> 5011 | F67: =Data!A66 -> Kyles , Amari | G67: =Data!C66 -> 3/11/1995 | H67: =Data!H66 -> 44277 | I67: =Data!I66 -> 5/11/2021 | J67: =Data!J66 -> 869.2 | K67: =TODAY()-I67 -> 373 | L67: =Data!M66 -> 0 | M67: CLAIM PAID - EFT | N67: =VLOOKUP(M67,Table1[#All],3,FALSE) -> Claim Paid by EFT; | O67: =VLOOKUP(M67,Table1[#All],4,FALSE) -> Issue Date: | P67: 44293 | Q67: =VLOOKUP(M67,Table1[#All],5,FALSE) -> EFT# | R67: 907363 | S67: =VLOOKUP(M67,Table1[#All],6,FALSE) -> Bulk/Sep: | T67: Bulk | U67: =VLOOKUP(M67,Table1[#All],7,FALSE) -> Call Ref#: | V67: Lisa 3/8/2022 | W67: =VLOOKUP(M67,Table1[#All],8,FALSE) -> Cust Rep: | X67: LISA | Y67: =VLOOKUP(M67,Table1[#All],2,FALSE) -> Task Post Pmt Queue | Z67: =VLOOKUP(M67,Table1[#All],9,FALSE) -> Additional Notes: | AA67: Rep states that clm #2-1090-396-68, paid amt $479.80, PR amt $232.20, cashed dt 4/7/2021, it’s a bulk amt $1,640.80, there are 13 codes on the claim in which 2 codes D1208 and the reason for the age limitation. D9230 is denied for not covered benefits for the dental plan. | AB67: NV pending | AC67: YES | AD67: V Team | AE67: MU | AF67: 44628 | AG67: Follow-Up Complete
A68: =Data!K67 -> Delta Dental Of Wisconsin | B68: =Data!L67 -> 8002363712 | C68: =Data!D67 -> Franke , Ryan | D68: =Data!F67 -> 08068258853 | E68: =Data!B67 -> 5311 | F68: =Data!A67 -> Franke , Ryan | G68: =Data!C67 -> 6/9/1986 | H68: =Data!H67 -> 44127 | I68: =Data!I67 -> 2/1/2021 | J68: =Data!J67 -> 4439.6 | K68: =TODAY()-I68 -> 472 | L68: =Data!M67 -> 0 | M68: CLAIM PAID - EFT | N68: =VLOOKUP(M68,Table1[#All],3,FALSE) -> Claim Paid by EFT; | O68: =VLOOKUP(M68,Table1[#All],4,FALSE) -> Issue Date: | P68: 44131 | Q68: =VLOOKUP(M68,Table1[#All],5,FALSE) -> EFT# | R68: 825000 | S68: =VLOOKUP(M68,Table1[#All],6,FALSE) -> Bulk/Sep: | T68: Sep | U68: =VLOOKUP(M68,Table1[#All],7,FALSE) -> Call Ref#: | V68: Amalia01272022 | W68: =VLOOKUP(M68,Table1[#All],8,FALSE) -> Cust Rep: | X68: Amalia | Y68: =VLOOKUP(M68,Table1[#All],2,FALSE) -> Task Post Pmt Queue | Z68: =VLOOKUP(M68,Table1[#All],9,FALSE) -> Additional Notes: | AA68: Rep State that Claim Paid,Paid Amt:$1147, Claim No: 2030139640, Patient Resp:$25($25 Deductable). DOS:12/14/2020 - D3310 & D2954 are denied Maxed out. DOS: 12/19/2020 - D4341 - LR - Paid AMT $23 & D4341 - UR - Maxed out. DOS: 12/22/2022 - D2750, D4341 (UL & LL) - Denied Maxed out. | AB68: NV pending | AC68: YES | AD68: V Team | AE68: SN | AF68: 44649 | AG68: Follow-Up Complete
A69: =Data!K68 -> Delta Dental Wisconsin Individual plan | B69: =Data!L68 -> 8888993734 | C69: =Data!D68 -> BLANTON, LOUISE | D69: =Data!F68 -> 07730973539 | E69: =Data!B68 -> 1695 | F69: =Data!A68 -> BLANTON, LOUISE | G69: =Data!C68 -> 9/17/1979 | H69: =Data!H68 -> 44274 | I69: =Data!I68 -> 4/21/2021 | J69: =Data!J68 -> 1495.2 | K69: =TODAY()-I69 -> 393 | L69: =Data!M68 -> 0 | M69: CNOF Not Active | N69: =VLOOKUP(M69,Table1[#All],3,FALSE) -> Patient not active/no active policy; | O69: =VLOOKUP(M69,Table1[#All],4,FALSE) -> Policy Term Dt: | P69: 44620 | Q69: =VLOOKUP(M69,Table1[#All],5,FALSE) -> Call Ref#: | R69: Jerrone 3/8/2022 | S69: =VLOOKUP(M69,Table1[#All],6,FALSE) -> Cust Rep: | T69: Jerrone | U69: =VLOOKUP(M69,Table1[#All],7,FALSE) -> 0 | W69: =VLOOKUP(M69,Table1[#All],8,FALSE) -> 0 | Y69: =VLOOKUP(M69,Table1[#All],2,FALSE) -> Task Denied Claims Queue | Z69: =VLOOKUP(M69,Table1[#All],9,FALSE) -> Additional Notes: | AA69: Patient not active for DOS. Patient has Molina Ins as Sec Ins, need to submit claim to Molina for processing. | AB69: NV pending | AC69: NO | AD69: V Team | AE69: MU | AF69: 44628 | AG69: Follow-Up Complete
A70: =Data!K69 -> Denta Trust | B70: =Data!L69 -> 8004365294 | C70: =Data!D69 -> Liggett, Carrie | D70: =Data!F69 -> 0002426991 | E70: =Data!B69 -> 6130 | F70: =Data!A69 -> Liggett, Carrie | G70: =Data!C69 -> 8/17/1972 | H70: =Data!H69 -> 44428 | I70: =Data!I69 -> 3/5/2022 | J70: =Data!J69 -> 339.6 | K70: =TODAY()-I70 -> 75 | L70: =Data!M69 -> 0 | M70: Select Status | N70: =VLOOKUP(M70,Table1[#All],3,FALSE) -> Note | O70: =VLOOKUP(M70,Table1[#All],4,FALSE) -> Q1 | Q70: =VLOOKUP(M70,Table1[#All],5,FALSE) -> Q2 | S70: =VLOOKUP(M70,Table1[#All],6,FALSE) -> Q3 | U70: =VLOOKUP(M70,Table1[#All],7,FALSE) -> Q4 | W70: =VLOOKUP(M70,Table1[#All],8,FALSE) -> Q5 | Y70: =VLOOKUP(M70,Table1[#All],2,FALSE) -> Action | Z70: =VLOOKUP(M70,Table1[#All],9,FALSE) -> Additional Notes: | AC70: Select | AD70: Select | AG70: Select
A71: =Data!K70 -> Denta Trust | B71: =Data!L70 -> 8004365294 | C71: =Data!D70 -> Rivera , Reyes | D71: =Data!F70 -> 000248499 | E71: =Data!B70 -> 8678 | F71: =Data!A70 -> Rivera , Reyes | G71: =Data!C70 -> 4/7/1981 | H71: =Data!H70 -> 44546 | I71: =Data!I70 -> 12/22/2021 | J71: =Data!J70 -> 372.8 | K71: =TODAY()-I71 -> 148 | L71: =Data!M70 -> 0 | M71: OTHER | N71: =VLOOKUP(M71,Table1[#All],3,FALSE) -> Write information in Addl Notes | O71: =VLOOKUP(M71,Table1[#All],4,FALSE) -> Call Ref#: | P71: 202201772935 | Q71: =VLOOKUP(M71,Table1[#All],5,FALSE) -> Cust Rep: | R71: Williams | S71: =VLOOKUP(M71,Table1[#All],6,FALSE) -> 0 | U71: =VLOOKUP(M71,Table1[#All],7,FALSE) | W71: =VLOOKUP(M71,Table1[#All],8,FALSE) | Y71: =VLOOKUP(M71,Table1[#All],2,FALSE) -> Team Lead to review & Follow-Up | Z71: =VLOOKUP(M71,Table1[#All],9,FALSE) -> Additional Notes: | AA71: Rep states that they unable to pull the pat information with the mem id need to call to the subscriber or the patient to get the correct id.// Unable to get the details form the portal. Need to call and get the status. - SN | AB71: NV pending | AC71: NO | AD71: V Team | AE71: MU | AF71: 44658 | AG71: Follow-Up Complete
A72: =Data!K71 -> Denta Trust | B72: =Data!L71 -> 8004365294 | C72: =Data!D71 -> Washington , Valencia | D72: =Data!F71 -> 0003474082 | E72: =Data!B71 -> 8437 | F72: =Data!A71 -> Washington , Valencia | G72: =Data!C71 -> 2/21/1984 | H72: =Data!H71 -> 44512 | I72: =Data!I71 -> 11/18/2021 | J72: =Data!J71 -> 525.6 | K72: =TODAY()-I72 -> 182 | L72: =Data!M71 -> 0 | M72: CLAIM PAID - EFT | N72: =VLOOKUP(M72,Table1[#All],3,FALSE) -> Claim Paid by EFT; | O72: =VLOOKUP(M72,Table1[#All],4,FALSE) -> Issue Date: | P72: 44526 | Q72: =VLOOKUP(M72,Table1[#All],5,FALSE) -> EFT# | R72: 5877982047 | S72: =VLOOKUP(M72,Table1[#All],6,FALSE) -> Bulk/Sep: | T72: Sep | U72: =VLOOKUP(M72,Table1[#All],7,FALSE) -> Call Ref#: | V72: 20220101760 | W72: =VLOOKUP(M72,Table1[#All],8,FALSE) -> Cust Rep: | X72: Casey | Y72: =VLOOKUP(M72,Table1[#All],2,FALSE) -> Task Post Pmt Queue | Z72: =VLOOKUP(M72,Table1[#All],9,FALSE) -> Additional Notes: | AA72: D7210 - Dnd for waiting period (1 yr) and waiting period was going to be end on 12/31/2021. Now patient is Inactive and $420 is patient's resp for this claim. Code D0220 was bundled with D0274. - 02/28/2022 - SN. // Need Waiting Period for D7210 and bundled Code for D0220 as this procedure is dnd stating bundled as FMX but there is no FMX code paid clm# 202132338791800, Paid $ 80.73. D0220 dnd as Service has been bundled with other procedure lines to a more cost effective full mouth series - Need to check for which is this code bundled with and D7210 is dnd due to waiting period for this benefit has not been met - Need to check what is the waiting period for this procedure. | AB72: NV pending | AC72: YES | AD72: V Team | AE72: MA | AF72: 44608 | AG72: Follow-Up Complete
A73: =Data!K72 -> Denta Trust | B73: =Data!L72 -> 8004365294 | C73: =Data!D72 -> Arries, Daniel | D73: =Data!F72 -> 0002458747 | E73: =Data!B72 -> 7808 | F73: =Data!A72 -> Arries, Daniel | G73: =Data!C72 -> 5/13/1986 | H73: =Data!H72 -> 44432 | I73: =Data!I72 -> 9/21/2021 | J73: =Data!J72 -> 216 | K73: =TODAY()-I73 -> 240 | L73: =Data!M72 -> 0 | M73: CLAIM PAID - EFT | N73: =VLOOKUP(M73,Table1[#All],3,FALSE) -> Claim Paid by EFT; | O73: =VLOOKUP(M73,Table1[#All],4,FALSE) -> Issue Date: | P73: 44442 | Q73: =VLOOKUP(M73,Table1[#All],5,FALSE) -> EFT# | R73: 5877908417 | S73: =VLOOKUP(M73,Table1[#All],6,FALSE) -> Bulk/Sep: | T73: SEP | U73: =VLOOKUP(M73,Table1[#All],7,FALSE) -> Call Ref#: | V73: 202200318022 | W73: =VLOOKUP(M73,Table1[#All],8,FALSE) -> Cust Rep: | X73: Ander | Y73: =VLOOKUP(M73,Table1[#All],2,FALSE) -> Task Post Pmt Queue | Z73: =VLOOKUP(M73,Table1[#All],9,FALSE) -> Additional Notes: | AA73: Rep States that Claim Paid,Claim NO: 202124238888600, Paid AMT:$80.73,Patient Resp: $135.27 | AB73: NV pending | AC73: YES | AD73: V Team | AE73: AA | AF73: 44581 | AG73: Follow-Up Complete
A74: =Data!K73 -> Denta Trust | B74: =Data!L73 -> 8004365294 | C74: =Data!D73 -> Luttrell, Melanie | D74: =Data!F73 -> 0002988406 | E74: =Data!B73 -> 7899 | F74: =Data!A73 -> Luttrell, Melanie | G74: =Data!C73 -> 5/20/1993 | H74: =Data!H73 -> 44449 | I74: =Data!I73 -> 9/15/2021 | J74: =Data!J73 -> 178.4 | K74: =TODAY()-I74 -> 246 | L74: =Data!M73 -> 0 | M74: CLAIM PAID - EFT | N74: =VLOOKUP(M74,Table1[#All],3,FALSE) -> Claim Paid by EFT; | O74: =VLOOKUP(M74,Table1[#All],4,FALSE) -> Issue Date: | P74: 44463 | Q74: =VLOOKUP(M74,Table1[#All],5,FALSE) -> EFT# | R74: 5877926593 | S74: =VLOOKUP(M74,Table1[#All],6,FALSE) -> Bulk/Sep: | T74: SEP | U74: =VLOOKUP(M74,Table1[#All],7,FALSE) -> Call Ref#: | V74: 202200318169 | W74: =VLOOKUP(M74,Table1[#All],8,FALSE) -> Cust Rep: | X74: Ander | Y74: =VLOOKUP(M74,Table1[#All],2,FALSE) -> Task Post Pmt Queue | Z74: =VLOOKUP(M74,Table1[#All],9,FALSE) -> Additional Notes: | AA74: Rep States that Claim Paid,Claim NO: 202125839780100, Paid AMT:$53.65. | AB74: NV pending | AC74: YES | AD74: V Team | AE74: AA | AF74: 44581 | AG74: Follow-Up Complete
A75: =Data!K74 -> Denta Trust | B75: =Data!L74 -> 8004365294 | C75: =Data!D74 -> Goffe, Dennis | D75: =Data!F74 -> 0003096716 | E75: =Data!B74 -> 7782 | F75: =Data!A74 -> Goffe, Dennis | G75: =Data!C74 -> 2/8/1957 | H75: =Data!H74 -> 44433 | I75: =Data!I74 -> 8/30/2021 | J75: =Data!J74 -> 505.2 | K75: =TODAY()-I75 -> 262 | L75: =Data!M74 -> 0 | M75: CLAIM PAID - EFT | N75: =VLOOKUP(M75,Table1[#All],3,FALSE) -> Claim Paid by EFT; | O75: =VLOOKUP(M75,Table1[#All],4,FALSE) -> Issue Date: | P75: 44447 | Q75: =VLOOKUP(M75,Table1[#All],5,FALSE) -> EFT# | R75: 5877908417 | S75: =VLOOKUP(M75,Table1[#All],6,FALSE) -> Bulk/Sep: | T75: SEP | U75: =VLOOKUP(M75,Table1[#All],7,FALSE) -> Call Ref#: | V75: 202200318449 | W75: =VLOOKUP(M75,Table1[#All],8,FALSE) -> Cust Rep: | X75: Emily | Y75: =VLOOKUP(M75,Table1[#All],2,FALSE) -> Task Post Pmt Queue | Z75: =VLOOKUP(M75,Table1[#All],9,FALSE) -> Additional Notes: | AA75: Rep States that Claim Paid,Claim NO: 202124238867800, Paid AMT:$105.04 | AB75: NV pending | AC75: YES | AD75: V Team | AE75: AA | AF75: 44581 | AG75: Follow-Up Complete
A76: =Data!K75 -> Denta Trust | B76: =Data!L75 -> 8004365294 | C76: =Data!D75 -> Prasser , Stephanie | D76: =Data!F75 -> 0003388416 | E76: =Data!B75 -> 7024 | F76: =Data!A75 -> Prasser , Stephanie | G76: =Data!C75 -> 5/10/1995 | H76: =Data!H75 -> 44322 | I76: =Data!I75 -> 5/6/2021 | J76: =Data!J75 -> 583.2 | K76: =TODAY()-I76 -> 378 | L76: =Data!M75 -> 0 | M76: DENIED - NOT COVERED | N76: =VLOOKUP(M76,Table1[#All],3,FALSE) -> Procedure is not a covered benefit; | O76: =VLOOKUP(M76,Table1[#All],4,FALSE) -> Why? | P76: Not covered under pt plan | Q76: =VLOOKUP(M76,Table1[#All],5,FALSE) -> Call Ref#: | R76: 202200318509 | S76: =VLOOKUP(M76,Table1[#All],6,FALSE) -> Cust Rep: | T76: Emily | U76: =VLOOKUP(M76,Table1[#All],7,FALSE) -> 0 | W76: =VLOOKUP(M76,Table1[#All],8,FALSE) -> 0 | Y76: =VLOOKUP(M76,Table1[#All],2,FALSE) -> Task Client - Denied Claim Queue | Z76: =VLOOKUP(M76,Table1[#All],9,FALSE) -> Additional Notes: | AA76: D2393 - Denied waiting period Issue & D1208 - Denied benefit not covered under pt plan. Payment posting already done. Need to close the claim. | AB76: NV pending | AC76: YES | AD76: V Team | AE76: SN | AF76: 44581 | AG76: Follow-Up Complete
A77: =Data!K76 -> Dental Health and Wellness WI | B77: =Data!L76 -> 8444645635 | C77: =Data!D76 -> Rice, Matthew | D77: =Data!F76 -> 8453528381 | E77: =Data!B76 -> 2431 | F77: =Data!A76 -> Rice, Matthew | G77: =Data!C76 -> 8/29/2003 | H77: =Data!H76 -> 44652 | I77: =Data!I76 -> 4/4/2022 | J77: =Data!J76 -> 501.6 | K77: =TODAY()-I77 -> 45 | L77: =Data!M76 -> 0 | M77: Select Status | N77: =VLOOKUP(M77,Table1[#All],3,FALSE) -> Note | O77: =VLOOKUP(M77,Table1[#All],4,FALSE) -> Q1 | Q77: =VLOOKUP(M77,Table1[#All],5,FALSE) -> Q2 | S77: =VLOOKUP(M77,Table1[#All],6,FALSE) -> Q3 | U77: =VLOOKUP(M77,Table1[#All],7,FALSE) -> Q4 | W77: =VLOOKUP(M77,Table1[#All],8,FALSE) -> Q5 | Y77: =VLOOKUP(M77,Table1[#All],2,FALSE) -> Action | Z77: =VLOOKUP(M77,Table1[#All],9,FALSE) -> Additional Notes: | AC77: Select | AD77: Select | AG77: Select
A78: =Data!K77 -> Dental Health and Wellness WI | B78: =Data!L77 -> 8444645635 | C78: =Data!D77 -> Rice, Quiana | D78: =Data!F77 -> 9453528391 | E78: =Data!B77 -> 2432 | F78: =Data!A77 -> Rice, Quiana | G78: =Data!C77 -> 4/15/2005 | H78: =Data!H77 -> 44652 | I78: =Data!I77 -> 4/4/2022 | J78: =Data!J77 -> 669.6 | K78: =TODAY()-I78 -> 45 | L78: =Data!M77 -> 0 | M78: Select Status | N78: =VLOOKUP(M78,Table1[#All],3,FALSE) -> Note | O78: =VLOOKUP(M78,Table1[#All],4,FALSE) -> Q1 | Q78: =VLOOKUP(M78,Table1[#All],5,FALSE) -> Q2 | S78: =VLOOKUP(M78,Table1[#All],6,FALSE) -> Q3 | U78: =VLOOKUP(M78,Table1[#All],7,FALSE) -> Q4 | W78: =VLOOKUP(M78,Table1[#All],8,FALSE) -> Q5 | Y78: =VLOOKUP(M78,Table1[#All],2,FALSE) -> Action | Z78: =VLOOKUP(M78,Table1[#All],9,FALSE) -> Additional Notes: | AC78: Select | AD78: Select | AG78: Select
A79: =Data!K78 -> Dental Health and Wellness WI | B79: =Data!L78 -> 8444645635 | C79: =Data!D78 -> Mcneal, Gabrielle | D79: =Data!F78 -> 4405491747 | E79: =Data!B78 -> 3084 | F79: =Data!A78 -> Mcneal, Gabrielle | G79: =Data!C78 -> 4/13/1995 | H79: =Data!H78 -> 44652 | I79: =Data!I78 -> 4/4/2022 | J79: =Data!J78 -> 149.6 | K79: =TODAY()-I79 -> 45 | L79: =Data!M78 -> 0 | M79: Select Status | N79: =VLOOKUP(M79,Table1[#All],3,FALSE) -> Note | O79: =VLOOKUP(M79,Table1[#All],4,FALSE) -> Q1 | Q79: =VLOOKUP(M79,Table1[#All],5,FALSE) -> Q2 | S79: =VLOOKUP(M79,Table1[#All],6,FALSE) -> Q3 | U79: =VLOOKUP(M79,Table1[#All],7,FALSE) -> Q4 | W79: =VLOOKUP(M79,Table1[#All],8,FALSE) -> Q5 | Y79: =VLOOKUP(M79,Table1[#All],2,FALSE) -> Action | Z79: =VLOOKUP(M79,Table1[#All],9,FALSE) -> Additional Notes: | AC79: Select | AD79: Select | AG79: Select
A80: =Data!K79 -> Dental Health and Wellness WI | B80: =Data!L79 -> 8444645635 | C80: =Data!D79 -> Veasey, Zayden | D80: =Data!F79 -> 2446058621 | E80: =Data!B79 -> 9219 | F80: =Data!A79 -> Veasey, Zayden | G80: =Data!C79 -> 4/2/2014 | H80: =Data!H79 -> 44649 | I80: =Data!I79 -> 3/30/2022 | J80: =Data!J79 -> 470 | K80: =TODAY()-I80 -> 50 | L80: =Data!M79 -> 0 | M80: Select Status | N80: =VLOOKUP(M80,Table1[#All],3,FALSE) -> Note | O80: =VLOOKUP(M80,Table1[#All],4,FALSE) -> Q1 | Q80: =VLOOKUP(M80,Table1[#All],5,FALSE) -> Q2 | S80: =VLOOKUP(M80,Table1[#All],6,FALSE) -> Q3 | U80: =VLOOKUP(M80,Table1[#All],7,FALSE) -> Q4 | W80: =VLOOKUP(M80,Table1[#All],8,FALSE) -> Q5 | Y80: =VLOOKUP(M80,Table1[#All],2,FALSE) -> Action | Z80: =VLOOKUP(M80,Table1[#All],9,FALSE) -> Additional Notes: | AC80: Select | AD80: Select | AG80: Select
A81: =Data!K80 -> Dental Health and Wellness WI | B81: =Data!L80 -> 8444645635 | C81: =Data!D80 -> Bell , Muhammed | D81: =Data!F80 -> 7440164377 | E81: =Data!B80 -> 2943 | F81: =Data!A80 -> Bell , Muhammed | G81: =Data!C80 -> 2/27/1998 | H81: =Data!H80 -> 44645 | I81: =Data!I80 -> 3/28/2022 | J81: =Data!J80 -> 61.2 | K81: =TODAY()-I81 -> 52 | L81: =Data!M80 -> 0 | M81: Select Status | N81: =VLOOKUP(M81,Table1[#All],3,FALSE) -> Note | O81: =VLOOKUP(M81,Table1[#All],4,FALSE) -> Q1 | Q81: =VLOOKUP(M81,Table1[#All],5,FALSE) -> Q2 | S81: =VLOOKUP(M81,Table1[#All],6,FALSE) -> Q3 | U81: =VLOOKUP(M81,Table1[#All],7,FALSE) -> Q4 | W81: =VLOOKUP(M81,Table1[#All],8,FALSE) -> Q5 | Y81: =VLOOKUP(M81,Table1[#All],2,FALSE) -> Action | Z81: =VLOOKUP(M81,Table1[#All],9,FALSE) -> Additional Notes: | AC81: Select | AD81: Select | AG81: Select
A82: =Data!K81 -> Dental Health and Wellness WI | B82: =Data!L81 -> 8444645635 | C82: =Data!D81 -> Conner, Aaron | D82: =Data!F81 -> 7436049879 | E82: =Data!B81 -> 9077 | F82: =Data!A81 -> Conner, Aaron | G82: =Data!C81 -> 5/26/1993 | H82: =Data!H81 -> 44645 | I82: =Data!I81 -> 3/28/2022 | J82: =Data!J81 -> 506.4 | K82: =TODAY()-I82 -> 52 | L82: =Data!M81 -> 0 | M82: Select Status | N82: =VLOOKUP(M82,Table1[#All],3,FALSE) -> Note | O82: =VLOOKUP(M82,Table1[#All],4,FALSE) -> Q1 | Q82: =VLOOKUP(M82,Table1[#All],5,FALSE) -> Q2 | S82: =VLOOKUP(M82,Table1[#All],6,FALSE) -> Q3 | U82: =VLOOKUP(M82,Table1[#All],7,FALSE) -> Q4 | W82: =VLOOKUP(M82,Table1[#All],8,FALSE) -> Q5 | Y82: =VLOOKUP(M82,Table1[#All],2,FALSE) -> Action | Z82: =VLOOKUP(M82,Table1[#All],9,FALSE) -> Additional Notes: | AC82: Select | AD82: Select | AG82: Select
A83: =Data!K82 -> Dental Health and Wellness WI | B83: =Data!L82 -> 8444645635 | C83: =Data!D82 -> Brown, Jayce | D83: =Data!F82 -> 4442014043 | E83: =Data!B82 -> 9302 | F83: =Data!A82 -> Brown, Jayce | G83: =Data!C82 -> 3/15/2012 | H83: =Data!H82 -> 44639 | I83: =Data!I82 -> 3/28/2022 | J83: =Data!J82 -> 432 | K83: =TODAY()-I83 -> 52 | L83: =Data!M82 -> 0 | M83: Select Status | N83: =VLOOKUP(M83,Table1[#All],3,FALSE) -> Note | O83: =VLOOKUP(M83,Table1[#All],4,FALSE) -> Q1 | Q83: =VLOOKUP(M83,Table1[#All],5,FALSE) -> Q2 | S83: =VLOOKUP(M83,Table1[#All],6,FALSE) -> Q3 | U83: =VLOOKUP(M83,Table1[#All],7,FALSE) -> Q4 | W83: =VLOOKUP(M83,Table1[#All],8,FALSE) -> Q5 | Y83: =VLOOKUP(M83,Table1[#All],2,FALSE) -> Action | Z83: =VLOOKUP(M83,Table1[#All],9,FALSE) -> Additional Notes: | AC83: Select | AD83: Select | AG83: Select
A84: =Data!K83 -> Dental Health and Wellness WI | B84: =Data!L83 -> 8444645635 | C84: =Data!D83 -> Beqiri, Malik | D84: =Data!F83 -> 0456692509 | E84: =Data!B83 -> 7851 | F84: =Data!A83 -> Beqiri, Malik | G84: =Data!C83 -> 9/14/2019 | H84: =Data!H83 -> 44643 | I84: =Data!I83 -> 3/24/2022 | J84: =Data!J83 -> 138 | K84: =TODAY()-I84 -> 56 | L84: =Data!M83 -> 0 | M84: Select Status | N84: =VLOOKUP(M84,Table1[#All],3,FALSE) -> Note | O84: =VLOOKUP(M84,Table1[#All],4,FALSE) -> Q1 | Q84: =VLOOKUP(M84,Table1[#All],5,FALSE) -> Q2 | S84: =VLOOKUP(M84,Table1[#All],6,FALSE) -> Q3 | U84: =VLOOKUP(M84,Table1[#All],7,FALSE) -> Q4 | W84: =VLOOKUP(M84,Table1[#All],8,FALSE) -> Q5 | Y84: =VLOOKUP(M84,Table1[#All],2,FALSE) -> Action | Z84: =VLOOKUP(M84,Table1[#All],9,FALSE) -> Additional Notes: | AC84: Select | AD84: Select | AG84: Select
A85: =Data!K84 -> Dental Health and Wellness WI | B85: =Data!L84 -> 8444645635 | C85: =Data!D84 -> Edmonds, Kelly | D85: =Data!F84 -> 5432809656 | E85: =Data!B84 -> 9278 | F85: =Data!A84 -> Edmonds, Kelly | G85: =Data!C84 -> 10/7/1964 | H85: =Data!H84 -> 44643 | I85: =Data!I84 -> 3/24/2022 | J85: =Data!J84 -> 178.4 | K85: =TODAY()-I85 -> 56 | L85: =Data!M84 -> 0 | M85: Select Status | N85: =VLOOKUP(M85,Table1[#All],3,FALSE) -> Note | O85: =VLOOKUP(M85,Table1[#All],4,FALSE) -> Q1 | Q85: =VLOOKUP(M85,Table1[#All],5,FALSE) -> Q2 | S85: =VLOOKUP(M85,Table1[#All],6,FALSE) -> Q3 | U85: =VLOOKUP(M85,Table1[#All],7,FALSE) -> Q4 | W85: =VLOOKUP(M85,Table1[#All],8,FALSE) -> Q5 | Y85: =VLOOKUP(M85,Table1[#All],2,FALSE) -> Action | Z85: =VLOOKUP(M85,Table1[#All],9,FALSE) -> Additional Notes: | AC85: Select | AD85: Select | AG85: Select
A86: =Data!K85 -> Dental Health and Wellness WI | B86: =Data!L85 -> 8444645635 | C86: =Data!D85 -> Howard , Jace | D86: =Data!F85 -> 3454824532 | E86: =Data!B85 -> 9285 | F86: =Data!A85 -> Howard , Jace | G86: =Data!C85 -> 6/21/2019 | H86: =Data!H85 -> 44643 | I86: =Data!I85 -> 3/24/2022 | J86: =Data!J85 -> 166.8 | K86: =TODAY()-I86 -> 56 | L86: =Data!M85 -> 0 | M86: Select Status | N86: =VLOOKUP(M86,Table1[#All],3,FALSE) -> Note | O86: =VLOOKUP(M86,Table1[#All],4,FALSE) -> Q1 | Q86: =VLOOKUP(M86,Table1[#All],5,FALSE) -> Q2 | S86: =VLOOKUP(M86,Table1[#All],6,FALSE) -> Q3 | U86: =VLOOKUP(M86,Table1[#All],7,FALSE) -> Q4 | W86: =VLOOKUP(M86,Table1[#All],8,FALSE) -> Q5 | Y86: =VLOOKUP(M86,Table1[#All],2,FALSE) -> Action | Z86: =VLOOKUP(M86,Table1[#All],9,FALSE) -> Additional Notes: | AC86: Select | AD86: Select | AG86: Select
A87: =Data!K86 -> Dental Health and Wellness WI | B87: =Data!L86 -> 8444645635 | C87: =Data!D86 -> Hayes , Shequita | D87: =Data!F86 -> 9450379491 | E87: =Data!B86 -> 8696 | F87: =Data!A86 -> Hayes , Shequita | G87: =Data!C86 -> 8/1/1992 | H87: =Data!H86 -> 44642 | I87: =Data!I86 -> 3/23/2022 | J87: =Data!J86 -> 506.4 | K87: =TODAY()-I87 -> 57 | L87: =Data!M86 -> 0 | M87: Select Status | N87: =VLOOKUP(M87,Table1[#All],3,FALSE) -> Note | O87: =VLOOKUP(M87,Table1[#All],4,FALSE) -> Q1 | Q87: =VLOOKUP(M87,Table1[#All],5,FALSE) -> Q2 | S87: =VLOOKUP(M87,Table1[#All],6,FALSE) -> Q3 | U87: =VLOOKUP(M87,Table1[#All],7,FALSE) -> Q4 | W87: =VLOOKUP(M87,Table1[#All],8,FALSE) -> Q5 | Y87: =VLOOKUP(M87,Table1[#All],2,FALSE) -> Action | Z87: =VLOOKUP(M87,Table1[#All],9,FALSE) -> Additional Notes: | AC87: Select | AD87: Select | AG87: Select
A88: =Data!K87 -> Dental Health and Wellness WI | B88: =Data!L87 -> 8444645635 | C88: =Data!D87 -> Baker, Marquis | D88: =Data!F87 -> 9416757993 | E88: =Data!B87 -> 9053 | F88: =Data!A87 -> Baker, Marquis | G88: =Data!C87 -> 6/10/1991 | H88: =Data!H87 -> 44642 | I88: =Data!I87 -> 3/23/2022 | J88: =Data!J87 -> 466.8 | K88: =TODAY()-I88 -> 57 | L88: =Data!M87 -> 0 | M88: Select Status | N88: =VLOOKUP(M88,Table1[#All],3,FALSE) -> Note | O88: =VLOOKUP(M88,Table1[#All],4,FALSE) -> Q1 | Q88: =VLOOKUP(M88,Table1[#All],5,FALSE) -> Q2 | S88: =VLOOKUP(M88,Table1[#All],6,FALSE) -> Q3 | U88: =VLOOKUP(M88,Table1[#All],7,FALSE) -> Q4 | W88: =VLOOKUP(M88,Table1[#All],8,FALSE) -> Q5 | Y88: =VLOOKUP(M88,Table1[#All],2,FALSE) -> Action | Z88: =VLOOKUP(M88,Table1[#All],9,FALSE) -> Additional Notes: | AC88: Select | AD88: Select | AG88: Select
... A113: =Data!K112 -> Dental Health and Wellness WI | B113: =Data!L112 -> 8444645635 | C113: =Data!D112 -> Baker, Mariah | D113: =Data!F112 -> 4442744742 | E113: =Data!B112 -> 9055 | F113: =Data!A112 -> Baker, Mariah | G113: =Data!C112 -> 9/8/2012 | H113: =Data!H112 -> 44603 | I113: =Data!I112 -> 2/15/2022 | J113: =Data!J112 -> 273.2 | K113: =TODAY()-I113 -> 93 | L113: =Data!M112 -> 0 | M113: Select Status | N113: =VLOOKUP(M113,Table1[#All],3,FALSE) -> Note | O113: =VLOOKUP(M113,Table1[#All],4,FALSE) -> Q1 | Q113: =VLOOKUP(M113,Table1[#All],5,FALSE) -> Q2 | S113: =VLOOKUP(M113,Table1[#All],6,FALSE) -> Q3 | U113: =VLOOKUP(M113,Table1[#All],7,FALSE) -> Q4 | W113: =VLOOKUP(M113,Table1[#All],8,FALSE) -> Q5 | Y113: =VLOOKUP(M113,Table1[#All],2,FALSE) -> Action | Z113: =VLOOKUP(M113,Table1[#All],9,FALSE) -> Additional Notes: | AC113: Select | AD113: Select | AG113: Select
A114: =Data!K113 -> Dental Health and Wellness WI | B114: =Data!L113 -> 8444645635 | C114: =Data!D113 -> Cervantes, Giselle | D114: =Data!F113 -> 6454600963 | E114: =Data!B113 -> 6261 | F114: =Data!A113 -> Cervantes, Giselle | G114: =Data!C113 -> 5/6/2016 | H114: =Data!H113 -> 44600 | I114: =Data!I113 -> 2/9/2022 | J114: =Data!J113 -> 227.6 | K114: =TODAY()-I114 -> 99 | L114: =Data!M113 -> 0 | M114: DENIED - MORE INFO | N114: =VLOOKUP(M114,Table1[#All],3,FALSE) -> Ins needs more info, need to submit; | O114: =VLOOKUP(M114,Table1[#All],4,FALSE) -> Attachments/Info needed? | P114: Primary EOB Required | Q114: =VLOOKUP(M114,Table1[#All],5,FALSE) -> Fax # (If Fax Yes): | S114: =VLOOKUP(M114,Table1[#All],6,FALSE) -> Call Ref#: | T114: 607713 | U114: =VLOOKUP(M114,Table1[#All],7,FALSE) -> Cust Rep: | V114: GLADYS | W114: =VLOOKUP(M114,Table1[#All],8,FALSE) -> 0 | Y114: =VLOOKUP(M114,Table1[#All],2,FALSE) -> Task Sub Pending Claims Queue | Z114: =VLOOKUP(M114,Table1[#All],9,FALSE) -> Additional Notes: | AA114: Claim was denied due to No primary Insure EOB. Patient has primary Insurance . The Provider need to include EOB with the claim or term letter indicating the primary Insurance was terminated. | AB114: NV pending | AC114: YES | AD114: V Team | AE114: SF | AF114: 44693 | AG114: Follow-Up Complete
A115: =Data!K114 -> Dental Health and Wellness WI | B115: =Data!L114 -> 8444645635 | C115: =Data!D114 -> Reed, Christine | D115: =Data!F114 -> 5430626457 | E115: =Data!B114 -> 9013 | F115: =Data!A114 -> Reed, Christine | G115: =Data!C114 -> 5/11/1999 | H115: =Data!H114 -> 44600 | I115: =Data!I114 -> 2/22/2022 | J115: =Data!J114 -> 408.8 | K115: =TODAY()-I115 -> 86 | L115: =Data!M114 -> 0 | M115: Select Status | N115: =VLOOKUP(M115,Table1[#All],3,FALSE) -> Note | O115: =VLOOKUP(M115,Table1[#All],4,FALSE) -> Q1 | Q115: =VLOOKUP(M115,Table1[#All],5,FALSE) -> Q2 | S115: =VLOOKUP(M115,Table1[#All],6,FALSE) -> Q3 | U115: =VLOOKUP(M115,Table1[#All],7,FALSE) -> Q4 | W115: =VLOOKUP(M115,Table1[#All],8,FALSE) -> Q5 | Y115: =VLOOKUP(M115,Table1[#All],2,FALSE) -> Action | Z115: =VLOOKUP(M115,Table1[#All],9,FALSE) -> Additional Notes: | AC115: Select | AD115: Select | AG115: Select
A116: =Data!K115 -> Dental Health and Wellness WI | B116: =Data!L115 -> 8444645635 | C116: =Data!D115 -> Sloat , Breanna | D116: =Data!F115 -> 2422230121 | E116: =Data!B115 -> 8958 | F116: =Data!A115 -> Sloat , Breanna | G116: =Data!C115 -> 5/23/1998 | H116: =Data!H115 -> 44600 | I116: =Data!I115 -> 2/9/2022 | J116: =Data!J115 -> 607.2 | K116: =TODAY()-I116 -> 99 | L116: =Data!M115 -> 0 | M116: DENIED - MORE INFO | N116: =VLOOKUP(M116,Table1[#All],3,FALSE) -> Ins needs more info, need to submit; | O116: =VLOOKUP(M116,Table1[#All],4,FALSE) -> Attachments/Info needed? | P116: Primary EOB Required | Q116: =VLOOKUP(M116,Table1[#All],5,FALSE) -> Fax # (If Fax Yes): | S116: =VLOOKUP(M116,Table1[#All],6,FALSE) -> Call Ref#: | T116: 607713 | U116: =VLOOKUP(M116,Table1[#All],7,FALSE) -> Cust Rep: | V116: GLADYS | W116: =VLOOKUP(M116,Table1[#All],8,FALSE) -> 0 | Y116: =VLOOKUP(M116,Table1[#All],2,FALSE) -> Task Sub Pending Claims Queue | Z116: =VLOOKUP(M116,Table1[#All],9,FALSE) -> Additional Notes: | AA116: Claim was denied due to No primary Insure EOB. Patient has primary Insurance . The Provider need to include EOB with the claim or term letter indicating the primary Insurance was terminated. | AB116: NV pending | AC116: YES | AD116: V Team | AE116: SF | AF116: 44693 | AG116: Follow-Up Complete
A117: =Data!K116 -> Dental Health and Wellness WI | B117: =Data!L116 -> 8444645635 | C117: =Data!D116 -> Groves, Nolan | D117: =Data!F116 -> 4451849241 | E117: =Data!B116 -> 2956 | F117: =Data!A116 -> Groves, Nolan | G117: =Data!C116 -> 7/17/2017 | H117: =Data!H116 -> 44588 | I117: =Data!I116 -> 1/27/2022 | J117: =Data!J116 -> 20 | K117: =TODAY()-I117 -> 112 | L117: =Data!M116 -> 0 | M117: DENIED - DUP SUBMIT | N117: =VLOOKUP(M117,Table1[#All],3,FALSE) -> Duplicate Submission; | O117: =VLOOKUP(M117,Table1[#All],4,FALSE) -> Dt orig. claim submitted: | Q117: =VLOOKUP(M117,Table1[#All],5,FALSE) -> Status of original Claim: | S117: =VLOOKUP(M117,Table1[#All],6,FALSE) -> Call Ref#: | T117: 575324 | U117: =VLOOKUP(M117,Table1[#All],7,FALSE) -> Cust Rep: | V117: JAZZ | W117: =VLOOKUP(M117,Table1[#All],8,FALSE) -> 0 | Y117: =VLOOKUP(M117,Table1[#All],2,FALSE) -> No Action | Z117: =VLOOKUP(M117,Table1[#All],9,FALSE) -> Additional Notes: | AA117: Incorrectly denied as duplicate, Check with Stanley for clarification - SN. | AB117: 44698 | AC117: YES | AD117: V Team | AE117: SF | AF117: 44679 | AG117: Further Follow-Up
A118: =Data!K117 -> Dental Health and Wellness WI | B118: =Data!L117 -> 8444645635 | C118: =Data!D117 -> Lees, Vannessa | D118: =Data!F117 -> 8417361189 | E118: =Data!B117 -> 8714 | F118: =Data!A117 -> Lees, Vannessa | G118: =Data!C117 -> 10/2/1996 | H118: =Data!H117 -> 44553 | I118: =Data!I117 -> 2/15/2022 | J118: =Data!J117 -> 813.6 | K118: =TODAY()-I118 -> 93 | L118: =Data!M117 -> 0 | M118: Select Status | N118: =VLOOKUP(M118,Table1[#All],3,FALSE) -> Note | O118: =VLOOKUP(M118,Table1[#All],4,FALSE) -> Q1 | Q118: =VLOOKUP(M118,Table1[#All],5,FALSE) -> Q2 | S118: =VLOOKUP(M118,Table1[#All],6,FALSE) -> Q3 | U118: =VLOOKUP(M118,Table1[#All],7,FALSE) -> Q4 | W118: =VLOOKUP(M118,Table1[#All],8,FALSE) -> Q5 | Y118: =VLOOKUP(M118,Table1[#All],2,FALSE) -> Action | Z118: =VLOOKUP(M118,Table1[#All],9,FALSE) -> Additional Notes: | AC118: Select | AD118: Select | AG118: Select
A119: =Data!K118 -> Dental Health and Wellness WI | B119: =Data!L118 -> 8444645635 | C119: =Data!D118 -> Johnson , Elliott | D119: =Data!F118 -> 5438989150 | E119: =Data!B118 -> 8863 | F119: =Data!A118 -> Johnson , Elliott | G119: =Data!C118 -> 11/16/1985 | H119: =Data!H118 -> 44575 | I119: =Data!I118 -> 2/16/2022 | J119: =Data!J118 -> 408.8 | K119: =TODAY()-I119 -> 92 | L119: =Data!M118 -> 0 | M119: Select Status | N119: =VLOOKUP(M119,Table1[#All],3,FALSE) -> Note | O119: =VLOOKUP(M119,Table1[#All],4,FALSE) -> Q1 | Q119: =VLOOKUP(M119,Table1[#All],5,FALSE) -> Q2 | S119: =VLOOKUP(M119,Table1[#All],6,FALSE) -> Q3 | U119: =VLOOKUP(M119,Table1[#All],7,FALSE) -> Q4 | W119: =VLOOKUP(M119,Table1[#All],8,FALSE) -> Q5 | Y119: =VLOOKUP(M119,Table1[#All],2,FALSE) -> Action | Z119: =VLOOKUP(M119,Table1[#All],9,FALSE) -> Additional Notes: | AC119: Select | AD119: Select | AG119: Select
A120: =Data!K119 -> Dental Health and Wellness WI | B120: =Data!L119 -> 8444645635 | C120: =Data!D119 -> Jaimes, Gener | D120: =Data!F119 -> 7421220771 | E120: =Data!B119 -> 629 | F120: =Data!A119 -> Jaimes, Gener | G120: =Data!C119 -> 6/6/1970 | H120: =Data!H119 -> 44575 | I120: =Data!I119 -> 1/14/2022 | J120: =Data!J119 -> 132.8 | K120: =TODAY()-I120 -> 125 | L120: =Data!M119 -> 0 | M120: CLAIM PAID - CHK | N120: =VLOOKUP(M120,Table1[#All],3,FALSE) -> Claim Paid by Check; | O120: =VLOOKUP(M120,Table1[#All],4,FALSE) -> Issue Date: | P120: 44581 | Q120: =VLOOKUP(M120,Table1[#All],5,FALSE) -> CHK# | R120: 904375 | S120: =VLOOKUP(M120,Table1[#All],6,FALSE) -> Bulk/Sep: | T120: Bulk | U120: =VLOOKUP(M120,Table1[#All],7,FALSE) -> Call Ref#: | W120: =VLOOKUP(M120,Table1[#All],8,FALSE) -> Cust Rep: | Y120: =VLOOKUP(M120,Table1[#All],2,FALSE) -> Task Cashed Chk Queue | Z120: =VLOOKUP(M120,Table1[#All],9,FALSE) -> Additional Notes: | AA120: Cashed date 01/31/2022 CLM # 20220117144845; Pd Amt : $56.57; Pt Resp: 0; Bulk Amt : $1566.24; Check is outstanding. D0220, D0230 & D0274 are bundled to D0210 and paid | AB120: TASK CREATED | AC120: YES | AD120: V Team | AE120: SF | AF120: 44676 | AG120: Follow-Up Complete
A121: =Data!K120 -> Dental Health and Wellness WI | B121: =Data!L120 -> 8444645635 | C121: =Data!D120 -> Guzman, Daniel | D121: =Data!F120 -> 7450197171 | E121: =Data!B120 -> 8765 | F121: =Data!A120 -> Guzman, Daniel | G121: =Data!C120 -> 12/9/1994 | H121: =Data!H120 -> 44575 | I121: =Data!I120 -> 1/14/2022 | J121: =Data!J120 -> 332.4 | K121: =TODAY()-I121 -> 125 | L121: =Data!M120 -> 0 | M121: CLAIM PAID - CHK | N121: =VLOOKUP(M121,Table1[#All],3,FALSE) -> Claim Paid by Check; | O121: =VLOOKUP(M121,Table1[#All],4,FALSE) -> Issue Date: | P121: 44581 | Q121: =VLOOKUP(M121,Table1[#All],5,FALSE) -> CHK# | R121: 904375 | S121: =VLOOKUP(M121,Table1[#All],6,FALSE) -> Bulk/Sep: | T121: Bulk | U121: =VLOOKUP(M121,Table1[#All],7,FALSE) -> Call Ref#: | W121: =VLOOKUP(M121,Table1[#All],8,FALSE) -> Cust Rep: | Y121: =VLOOKUP(M121,Table1[#All],2,FALSE) -> Task Cashed Chk Queue | Z121: =VLOOKUP(M121,Table1[#All],9,FALSE) -> Additional Notes: | AA121: Cashed date 01/31/2022; CLM # 20220117144846; Pd Amt : $103.19; Pt Resp : $0; Bulk Amt $1566.24. Check is outstanding | AB121: TASK CREATED | AC121: YES | AD121: V Team | AE121: SF | AF121: 44679 | AG121: Follow-Up Complete
A122: =Data!K121 -> Dental Health and Wellness WI | B122: =Data!L121 -> 8444645635 | C122: =Data!D121 -> Allen, Andre | D122: =Data!F121 -> 0411704605 | E122: =Data!B121 -> 8807 | F122: =Data!A121 -> Allen, Andre | G122: =Data!C121 -> 4/19/1982 | H122: =Data!H121 -> 44575 | I122: =Data!I121 -> 1/14/2022 | J122: =Data!J121 -> 294.8 | K122: =TODAY()-I122 -> 125 | L122: =Data!M121 -> 0 | M122: CLAIM PAID - CHK | N122: =VLOOKUP(M122,Table1[#All],3,FALSE) -> Claim Paid by Check; | O122: =VLOOKUP(M122,Table1[#All],4,FALSE) -> Issue Date: | P122: 44581 | Q122: =VLOOKUP(M122,Table1[#All],5,FALSE) -> CHK# | R122: 904375 | S122: =VLOOKUP(M122,Table1[#All],6,FALSE) -> Bulk/Sep: | T122: Bulk | U122: =VLOOKUP(M122,Table1[#All],7,FALSE) -> Call Ref#: | W122: =VLOOKUP(M122,Table1[#All],8,FALSE) -> Cust Rep: | Y122: =VLOOKUP(M122,Table1[#All],2,FALSE) -> Task Cashed Chk Queue | Z122: =VLOOKUP(M122,Table1[#All],9,FALSE) -> Additional Notes: | AA122: Cashed date 01/31/2022 //GET CASED DATE -MU ( Instead of 1/14/2022 for the DOS 1/06/2022 get the cashed date. ) ////CLM # 20220117142317; Pd Amt : $103.19; Pt Resp $0; Bulk Amt : $1566.24 | AB122: TASK CREATED | AC122: YES | AD122: V Team | AE122: SF | AF122: 44679 | AG122: Follow-Up Complete
A123: =Data!K122 -> Dental Health and Wellness WI | B123: =Data!L122 -> 8444645635 | C123: =Data!D122 -> Williams, James | D123: =Data!F122 -> 3455093931 | E123: =Data!B122 -> 8849 | F123: =Data!A122 -> Williams, James | G123: =Data!C122 -> 2/10/1998 | H123: =Data!H122 -> 44573 | I123: =Data!I122 -> 1/13/2022 | J123: =Data!J122 -> 612 | K123: =TODAY()-I123 -> 126 | L123: =Data!M122 -> 0 | M123: CLAIM PAID - CHK | N123: =VLOOKUP(M123,Table1[#All],3,FALSE) -> Claim Paid by Check; | O123: =VLOOKUP(M123,Table1[#All],4,FALSE) -> Issue Date: | P123: 44616 | Q123: =VLOOKUP(M123,Table1[#All],5,FALSE) -> CHK# | R123: 932617 | S123: =VLOOKUP(M123,Table1[#All],6,FALSE) -> Bulk/Sep: | T123: Bulk | U123: =VLOOKUP(M123,Table1[#All],7,FALSE) -> Call Ref#: | W123: =VLOOKUP(M123,Table1[#All],8,FALSE) -> Cust Rep: | Y123: =VLOOKUP(M123,Table1[#All],2,FALSE) -> Task Cashed Chk Queue | Z123: =VLOOKUP(M123,Table1[#All],9,FALSE) -> Additional Notes: | AA123: Rep State that Cashed on 03/23/2022 Rep Name: Jahni, Call Ref: 541267,CLM # 20220114130481; Pd Amt $157.86; Pt Resp $0; Bulk Amt $1566.24 | AB123: TASK CREATED | AC123: YES | AD123: V Team | AE123: AA | AF123: 44664 | AG123: Follow-Up Complete
A124: =Data!K123 -> Dental Health and Wellness WI | B124: =Data!L123 -> 8444645635 | C124: =Data!D123 -> Guzman, Nydia | D124: =Data!F123 -> 5424267955 | E124: =Data!B123 -> 8755 | F124: =Data!A123 -> Guzman, Nydia | G124: =Data!C123 -> 3/7/1980 | H124: =Data!H123 -> 44572 | I124: =Data!I123 -> 1/13/2022 | J124: =Data!J123 -> 332.4 | K124: =TODAY()-I124 -> 126 | L124: =Data!M123 -> 0 | M124: CLAIM PAID - CHK | N124: =VLOOKUP(M124,Table1[#All],3,FALSE) -> Claim Paid by Check; | O124: =VLOOKUP(M124,Table1[#All],4,FALSE) -> Issue Date: | P124: 44616 | Q124: =VLOOKUP(M124,Table1[#All],5,FALSE) -> CHK# | R124: 932617 | S124: =VLOOKUP(M124,Table1[#All],6,FALSE) -> Bulk/Sep: | T124: Bulk | U124: =VLOOKUP(M124,Table1[#All],7,FALSE) -> Call Ref#: | W124: =VLOOKUP(M124,Table1[#All],8,FALSE) -> Cust Rep: | Y124: =VLOOKUP(M124,Table1[#All],2,FALSE) -> Task Cashed Chk Queue | Z124: =VLOOKUP(M124,Table1[#All],9,FALSE) -> Additional Notes: | AA124: Rep State that Cashed on 03/23/2022 Rep Name: Jahni, Call Ref: 541267,CLM # 20220114130481; Pd Amt $157.86; Pt Resp $0; Bulk Amt $1566.24 | AB124: TASK CREATED | AC124: YES | AD124: V Team | AE124: AA | AF124: 44664 | AG124: Follow-Up Complete
...

Sheet Level 2
D1: Total No of Claims ===================================> | E1: ='Summary '!C27 -> 1065 | F1: =COUNTIF(E5:E1200,"Task Created") -> 16 | G1: <==========================Task Created
A2: TASK TEMPLATE | D2: INSB NV Team Pending Tasks ===========> | E2: =COUNTIF(E5:E1200,"INSB NV Team Task ") -> 216 | F2: =COUNTIF(E5:E1200,"Further Follow-Up") -> 0 | G2: <==========================Further Followup
D3: Closed (Task Created + Resolved =======================> | E3: =COUNTIF(E5:E1200,"Claim Resolved ")+COUNTIF(E5:E1200,"Task Created") -> 32
A4: Task Subject | B4: Task Detail | C4: Action | D4: What We Need/Reason (Tasking to Client) | E4: Claim Status | F4: Completed By | G4: Level 2 Comment
A5: =CONCATENATE("Pt Id:",'Level 1'!E5," ","Pt Name: ",'Level 1'!F5," ","DOS: ", TEXT('Level 1'!H5,"mm-dd-yyyy")," "," Amnt: ","$",'Level 1'!J5," ", 'Level 1'!N5) -> Pt Id:9200 Pt Name: Passehl , Kayla DOS: 03-15-2022 Amnt: $292.4 Note | B5: =CONCATENATE("Detail: ",'Level 1'!N5," ",'Level 1'!O5,TEXT('Level 1'!P5," mm-dd-yyyy"),";"," ",'Level 1'!Q5,'Level 1'!R5," ",'Level 1'!T5," ","Payment "," ",'Level 1'!U5," ",'Level 1'!V5," ",'Level 1'!W5," ",'Level 1'!X5," ",'Level 1'!Z5, " ",'Level 1'!AA5, " ","Insurance: ",'Level 1'!A5) -> Detail: Note Q1 01-00-1900; Q2 Payment Q4 Q5 Additional Notes: Insurance: Aetna | C5: ='Level 1'!Y5 -> Action | D5: =VLOOKUP(C5,Table2[#All],3,FALSE) -> What we need from you/Reason | E5: Claim Status
A6: =CONCATENATE("Pt Id:",'Level 1'!E6," ","Pt Name: ",'Level 1'!F6," ","DOS: ", TEXT('Level 1'!H6,"mm-dd-yyyy")," "," Amnt: ","$",'Level 1'!J6," ", 'Level 1'!N6) -> Pt Id:7412 Pt Name: Brown, Isabella DOS: 10-01-2021 Amnt: $1036.8 Claim Paid by Check; | B6: =CONCATENATE("Detail: ",'Level 1'!N6," ",'Level 1'!O6,TEXT('Level 1'!P6," mm-dd-yyyy"),";"," ",'Level 1'!Q6,'Level 1'!R6," ",'Level 1'!T6," ","Payment "," ",'Level 1'!U6," ",'Level 1'!V6," ",'Level 1'!W6," ",'Level 1'!X6," ",'Level 1'!Z6, " ",'Level 1'!AA6, " ","Insurance: ",'Level 1'!A6) -> Detail: Claim Paid by Check; Issue Date: 10-15-2021; CHK#237237308 Single Payment Call Ref#: 2070 Cust Rep: Poni Additional Notes: Rep states that clm #043444672190, paid amt $702.40, Its is a V.C.C payment and the draft number #237237308, patient responsibility is 303.60. cashed dt 10/26/2021. Insurance: Ameritas | C6: ='Level 1'!Y6 -> Task Cashed Chk Queue | D6: =VLOOKUP(C6,Table2[#All],3,FALSE) -> What We Need From You: Please confirm Check was received. Reason: To close claim. | E6: Task Created | F6: MU
A7: =CONCATENATE("Pt Id:",'Level 1'!E7," ","Pt Name: ",'Level 1'!F7," ","DOS: ", TEXT('Level 1'!H7,"mm-dd-yyyy")," "," Amnt: ","$",'Level 1'!J7," ", 'Level 1'!N7) -> Pt Id:9330 Pt Name: Thom, Keri DOS: 03-22-2022 Amnt: $294.8 Note | B7: =CONCATENATE("Detail: ",'Level 1'!N7," ",'Level 1'!O7,TEXT('Level 1'!P7," mm-dd-yyyy"),";"," ",'Level 1'!Q7,'Level 1'!R7," ",'Level 1'!T7," ","Payment "," ",'Level 1'!U7," ",'Level 1'!V7," ",'Level 1'!W7," ",'Level 1'!X7," ",'Level 1'!Z7, " ",'Level 1'!AA7, " ","Insurance: ",'Level 1'!A7) -> Detail: Note Q1 01-00-1900; Q2 Payment Q4 Q5 Additional Notes: Insurance: Anthem | C7: ='Level 1'!Y7 -> Action | D7: =VLOOKUP(C7,Table2[#All],3,FALSE) -> What we need from you/Reason | E7: Claim Status
A8: =CONCATENATE("Pt Id:",'Level 1'!E8," ","Pt Name: ",'Level 1'!F8," ","DOS: ", TEXT('Level 1'!H8,"mm-dd-yyyy")," "," Amnt: ","$",'Level 1'!J8," ", 'Level 1'!N8) -> Pt Id:4527 Pt Name: Wricks, Derrishia DOS: 12-15-2021 Amnt: $266 Claim not on file. Patient is active ; | B8: =CONCATENATE("Detail: ",'Level 1'!N8," ",'Level 1'!O8,TEXT('Level 1'!P8," mm-dd-yyyy"),";"," ",'Level 1'!Q8,'Level 1'!R8," ",'Level 1'!T8," ","Payment "," ",'Level 1'!U8," ",'Level 1'!V8," ",'Level 1'!W8," ",'Level 1'!X8," ",'Level 1'!Z8, " ",'Level 1'!AA8, " ","Insurance: ",'Level 1'!A8) -> Detail: Claim not on file. Patient is active ; Payor ID & Address:CB950; Fax # (If Fax Yes): 12Months from Dos Payment Call Ref#: LEANDRO Cust Rep: 8719609 Additional Notes: CNOF - Active Insurance: Anthem | C8: ='Level 1'!Y8 -> Task Sub Pending Claims Queue | D8: =VLOOKUP(C8,Table2[#All],3,FALSE) -> N/A | E8: INSB NV Team Task | F8: SN
A9: =CONCATENATE("Pt Id:",'Level 1'!E9," ","Pt Name: ",'Level 1'!F9," ","DOS: ", TEXT('Level 1'!H9,"mm-dd-yyyy")," "," Amnt: ","$",'Level 1'!J9," ", 'Level 1'!N9) -> Pt Id:8543 Pt Name: Allen, Janiyah DOS: 12-15-2021 Amnt: $307.2 Claim not on file. Patient is active ; | B9: =CONCATENATE("Detail: ",'Level 1'!N9," ",'Level 1'!O9,TEXT('Level 1'!P9," mm-dd-yyyy"),";"," ",'Level 1'!Q9,'Level 1'!R9," ",'Level 1'!T9," ","Payment "," ",'Level 1'!U9," ",'Level 1'!V9," ",'Level 1'!W9," ",'Level 1'!X9," ",'Level 1'!Z9, " ",'Level 1'!AA9, " ","Insurance: ",'Level 1'!A9) -> Detail: Claim not on file. Patient is active ; Payor ID & Address:CB950; Fax # (If Fax Yes): 12 Months from Dos Payment Call Ref#: 87214304 Cust Rep: CELLE Additional Notes: CNOF - Active. Insurance: Anthem | C9: ='Level 1'!Y9 -> Task Sub Pending Claims Queue | D9: =VLOOKUP(C9,Table2[#All],3,FALSE) -> N/A | E9: INSB NV Team Task | F9: SN
A10: =CONCATENATE("Pt Id:",'Level 1'!E10," ","Pt Name: ",'Level 1'!F10," ","DOS: ", TEXT('Level 1'!H10,"mm-dd-yyyy")," "," Amnt: ","$",'Level 1'!J10," ", 'Level 1'!N10) -> Pt Id:9345 Pt Name: Sullivan, Jessica DOS: 03-24-2022 Amnt: $302.4 Note | B10: =CONCATENATE("Detail: ",'Level 1'!N10," ",'Level 1'!O10,TEXT('Level 1'!P10," mm-dd-yyyy"),";"," ",'Level 1'!Q10,'Level 1'!R10," ",'Level 1'!T10," ","Payment "," ",'Level 1'!U10," ",'Level 1'!V10," ",'Level 1'!W10," ",'Level 1'!X10," ",'Level 1'!Z10, " ",'Level 1'!AA10, " ","Insurance: ",'Level 1'!A10) -> Detail: Note Q1 01-00-1900; Q2 Payment Q4 Q5 Additional Notes: Insurance: Cigna | C10: ='Level 1'!Y10 -> Action | D10: =VLOOKUP(C10,Table2[#All],3,FALSE) -> What we need from you/Reason | E10: Claim Status
A11: =CONCATENATE("Pt Id:",'Level 1'!E11," ","Pt Name: ",'Level 1'!F11," ","DOS: ", TEXT('Level 1'!H11,"mm-dd-yyyy")," "," Amnt: ","$",'Level 1'!J11," ", 'Level 1'!N11) -> Pt Id:2668 Pt Name: Sullivan, Carter DOS: 03-23-2022 Amnt: $102 Note | B11: =CONCATENATE("Detail: ",'Level 1'!N11," ",'Level 1'!O11,TEXT('Level 1'!P11," mm-dd-yyyy"),";"," ",'Level 1'!Q11,'Level 1'!R11," ",'Level 1'!T11," ","Payment "," ",'Level 1'!U11," ",'Level 1'!V11," ",'Level 1'!W11," ",'Level 1'!X11," ",'Level 1'!Z11, " ",'Level 1'!AA11, " ","Insurance: ",'Level 1'!A11) -> Detail: Note Q1 01-00-1900; Q2 Payment Q4 Q5 Additional Notes: Insurance: Cigna | C11: ='Level 1'!Y11 -> Action | D11: =VLOOKUP(C11,Table2[#All],3,FALSE) -> What we need from you/Reason | E11: Claim Status
A12: =CONCATENATE("Pt Id:",'Level 1'!E12," ","Pt Name: ",'Level 1'!F12," ","DOS: ", TEXT('Level 1'!H12,"mm-dd-yyyy")," "," Amnt: ","$",'Level 1'!J12," ", 'Level 1'!N12) -> Pt Id:3727 Pt Name: Arthur, Bernika DOS: 03-19-2022 Amnt: $123.6 Note | B12: =CONCATENATE("Detail: ",'Level 1'!N12," ",'Level 1'!O12,TEXT('Level 1'!P12," mm-dd-yyyy"),";"," ",'Level 1'!Q12,'Level 1'!R12," ",'Level 1'!T12," ","Payment "," ",'Level 1'!U12," ",'Level 1'!V12," ",'Level 1'!W12," ",'Level 1'!X12," ",'Level 1'!Z12, " ",'Level 1'!AA12, " ","Insurance: ",'Level 1'!A12) -> Detail: Note Q1 01-00-1900; Q2 Payment Q4 Q5 Additional Notes: Insurance: Cigna | C12: ='Level 1'!Y12 -> Action | D12: =VLOOKUP(C12,Table2[#All],3,FALSE) -> What we need from you/Reason | E12: Claim Status
A13: =CONCATENATE("Pt Id:",'Level 1'!E13," ","Pt Name: ",'Level 1'!F13," ","DOS: ", TEXT('Level 1'!H13,"mm-dd-yyyy")," "," Amnt: ","$",'Level 1'!J13," ", 'Level 1'!N13) -> Pt Id:3729 Pt Name: Arthur, Lilyana DOS: 03-19-2022 Amnt: $58.8 Note | B13: =CONCATENATE("Detail: ",'Level 1'!N13," ",'Level 1'!O13,TEXT('Level 1'!P13," mm-dd-yyyy"),";"," ",'Level 1'!Q13,'Level 1'!R13," ",'Level 1'!T13," ","Payment "," ",'Level 1'!U13," ",'Level 1'!V13," ",'Level 1'!W13," ",'Level 1'!X13," ",'Level 1'!Z13, " ",'Level 1'!AA13, " ","Insurance: ",'Level 1'!A13) -> Detail: Note Q1 01-00-1900; Q2 Payment Q4 Q5 Additional Notes: Insurance: Cigna | C13: ='Level 1'!Y13 -> Action | D13: =VLOOKUP(C13,Table2[#All],3,FALSE) -> What we need from you/Reason | E13: Claim Status
A14: =CONCATENATE("Pt Id:",'Level 1'!E14," ","Pt Name: ",'Level 1'!F14," ","DOS: ", TEXT('Level 1'!H14,"mm-dd-yyyy")," "," Amnt: ","$",'Level 1'!J14," ", 'Level 1'!N14) -> Pt Id:3729 Pt Name: Arthur, Lilyana DOS: 03-19-2022 Amnt: $79.2 Note | B14: =CONCATENATE("Detail: ",'Level 1'!N14," ",'Level 1'!O14,TEXT('Level 1'!P14," mm-dd-yyyy"),";"," ",'Level 1'!Q14,'Level 1'!R14," ",'Level 1'!T14," ","Payment "," ",'Level 1'!U14," ",'Level 1'!V14," ",'Level 1'!W14," ",'Level 1'!X14," ",'Level 1'!Z14, " ",'Level 1'!AA14, " ","Insurance: ",'Level 1'!A14) -> Detail: Note Q1 01-00-1900; Q2 Payment Q4 Q5 Additional Notes: Insurance: Cigna | C14: ='Level 1'!Y14 -> Action | D14: =VLOOKUP(C14,Table2[#All],3,FALSE) -> What we need from you/Reason | E14: Claim Status
A15: =CONCATENATE("Pt Id:",'Level 1'!E15," ","Pt Name: ",'Level 1'!F15," ","DOS: ", TEXT('Level 1'!H15,"mm-dd-yyyy")," "," Amnt: ","$",'Level 1'!J15," ", 'Level 1'!N15) -> Pt Id:4246 Pt Name: Belle , Byron DOS: 01-12-2022 Amnt: $266 Claim Paid by EFT; | B15: =CONCATENATE("Detail: ",'Level 1'!N15," ",'Level 1'!O15,TEXT('Level 1'!P15," mm-dd-yyyy"),";"," ",'Level 1'!Q15,'Level 1'!R15," ",'Level 1'!T15," ","Payment "," ",'Level 1'!U15," ",'Level 1'!V15," ",'Level 1'!W15," ",'Level 1'!X15," ",'Level 1'!Z15, " ",'Level 1'!AA15, " ","Insurance: ",'Level 1'!A15) -> Detail: Claim Paid by EFT; Issue Date: 01-19-2022; EFT#9999761864 single Payment Call Ref#: 2763 Cust Rep: MJ Additional Notes: Rep State that Code D0120, D0220, D0230 & (Partially) D0274 are applied towards the deductable. D1208 - denied due to Age limit (Age limit under 19) Rep Name: Moises, Call Ref: 4641//Rep States that the Claim Paid,Claim No:D220146565680, paid amt$130 Patient Resp: $136. Insurance: Cigna | C15: ='Level 1'!Y15 -> Task Post Pmt Queue | D15: =VLOOKUP(C15,Table2[#All],3,FALSE) -> N/A | E15: Claim Resolved | F15: SN/MA | G15: Payment Posted on 05.01.2022
A16: =CONCATENATE("Pt Id:",'Level 1'!E16," ","Pt Name: ",'Level 1'!F16," ","DOS: ", TEXT('Level 1'!H16,"mm-dd-yyyy")," "," Amnt: ","$",'Level 1'!J16," ", 'Level 1'!N16) -> Pt Id:3728 Pt Name: Arthur, Devin DOS: 10-09-2021 Amnt: $230 Claim Paid by EFT; | B16: =CONCATENATE("Detail: ",'Level 1'!N16," ",'Level 1'!O16,TEXT('Level 1'!P16," mm-dd-yyyy"),";"," ",'Level 1'!Q16,'Level 1'!R16," ",'Level 1'!T16," ","Payment "," ",'Level 1'!U16," ",'Level 1'!V16," ",'Level 1'!W16," ",'Level 1'!X16," ",'Level 1'!Z16, " ",'Level 1'!AA16, " ","Insurance: ",'Level 1'!A16) -> Detail: Claim Paid by EFT; Issue Date: 10-12-2021; EFT#9997740967 Bulk Payment Call Ref#: 9764 Cust Rep: sara Additional Notes: Rep States that Claim Paid,Claim No:D212856143800, paid amt$113 Patient Resp: NIL, All the lines paid on the claim. Insurance: Cigna | C16: ='Level 1'!Y16 -> Task Post Pmt Queue | D16: =VLOOKUP(C16,Table2[#All],3,FALSE) -> N/A | E16: INSB NV Team Task | F16: SN
A17: =CONCATENATE("Pt Id:",'Level 1'!E17," ","Pt Name: ",'Level 1'!F17," ","DOS: ", TEXT('Level 1'!H17,"mm-dd-yyyy")," "," Amnt: ","$",'Level 1'!J17," ", 'Level 1'!N17) -> Pt Id:3727 Pt Name: Arthur, Bernika DOS: 10-09-2021 Amnt: $216 Claim Paid by EFT; | B17: =CONCATENATE("Detail: ",'Level 1'!N17," ",'Level 1'!O17,TEXT('Level 1'!P17," mm-dd-yyyy"),";"," ",'Level 1'!Q17,'Level 1'!R17," ",'Level 1'!T17," ","Payment "," ",'Level 1'!U17," ",'Level 1'!V17," ",'Level 1'!W17," ",'Level 1'!X17," ",'Level 1'!Z17, " ",'Level 1'!AA17, " ","Insurance: ",'Level 1'!A17) -> Detail: Claim Paid by EFT; Issue Date: 10-13-2021; EFT#9997740967 Single Payment Call Ref#: 5334 Cust Rep: Nel Additional Notes: Pd $4.00 Pt res $76.00 Clm #D212856144410 was cashed on 10/18/2021 Insurance: Cigna | C17: ='Level 1'!Y17 -> Task Post Pmt Queue | D17: =VLOOKUP(C17,Table2[#All],3,FALSE) -> N/A | E17: INSB NV Team Task | F17: SN
A18: =CONCATENATE("Pt Id:",'Level 1'!E18," ","Pt Name: ",'Level 1'!F18," ","DOS: ", TEXT('Level 1'!H18,"mm-dd-yyyy")," "," Amnt: ","$",'Level 1'!J18," ", 'Level 1'!N18) -> Pt Id:6734 Pt Name: Rasmussen , John DOS: 10-05-2021 Amnt: $88.8 Claim Paid by EFT; | B18: =CONCATENATE("Detail: ",'Level 1'!N18," ",'Level 1'!O18,TEXT('Level 1'!P18," mm-dd-yyyy"),";"," ",'Level 1'!Q18,'Level 1'!R18," ",'Level 1'!T18," ","Payment "," ",'Level 1'!U18," ",'Level 1'!V18," ",'Level 1'!W18," ",'Level 1'!X18," ",'Level 1'!Z18, " ",'Level 1'!AA18, " ","Insurance: ",'Level 1'!A18) -> Detail: Claim Paid by EFT; Issue Date: 10-08-2021; EFT#9997740965 SEP Payment Call Ref#: 7209 Cust Rep: Erick Additional Notes: Rep States that Claim Paid,Claim No:R212816304340,Pd Amt $53; Patient Resp: Nil, Insurance: Cigna | C18: ='Level 1'!Y18 -> Task Post Pmt Queue | D18: =VLOOKUP(C18,Table2[#All],3,FALSE) -> N/A | E18: INSB NV Team Task | F18: SN
A19: =CONCATENATE("Pt Id:",'Level 1'!E19," ","Pt Name: ",'Level 1'!F19," ","DOS: ", TEXT('Level 1'!H19,"mm-dd-yyyy")," "," Amnt: ","$",'Level 1'!J19," ", 'Level 1'!N19) -> Pt Id:5453 Pt Name: Knight, Richard DOS: 05-06-2021 Amnt: $890 Ins needs more info, need to submit; | B19: =CONCATENATE("Detail: ",'Level 1'!N19," ",'Level 1'!O19,TEXT('Level 1'!P19," mm-dd-yyyy"),";"," ",'Level 1'!Q19,'Level 1'!R19," ",'Level 1'!T19," ","Payment "," ",'Level 1'!U19," ",'Level 1'!V19," ",'Level 1'!W19," ",'Level 1'!X19," ",'Level 1'!Z19, " ",'Level 1'!AA19, " ","Insurance: ",'Level 1'!A19) -> Detail: Ins needs more info, need to submit; Attachments/Info needed?Prep Date,Seat Date & Initial or Replacement Prior Placement Date; Fax # (If Fax Yes):8595502662 7991 Payment Cust Rep: Michal 0 Additional Notes: Rep State Clm Denied,Claim No: S211306181710,Mailing Address: PO Box 188037. Chattanooga, TN 37422,TFL: 365 Days for Out of Nework Patient,Processed & Denied Date: 07/19/2021 Insurance: Cigna | C19: ='Level 1'!Y19 -> Task Sub Pending Claims Queue | D19: =VLOOKUP(C19,Table2[#All],3,FALSE) -> N/A | E19: INSB NV Team Task | F19: SN
A20: =CONCATENATE("Pt Id:",'Level 1'!E20," ","Pt Name: ",'Level 1'!F20," ","DOS: ", TEXT('Level 1'!H20,"mm-dd-yyyy")," "," Amnt: ","$",'Level 1'!J20," ", 'Level 1'!N20) -> Pt Id:7171 Pt Name: Mokry, Lila DOS: 05-27-2021 Amnt: $256.4 Claim not on file. Patient is active ; | B20: =CONCATENATE("Detail: ",'Level 1'!N20," ",'Level 1'!O20,TEXT('Level 1'!P20," mm-dd-yyyy"),";"," ",'Level 1'!Q20,'Level 1'!R20," ",'Level 1'!T20," ","Payment "," ",'Level 1'!U20," ",'Level 1'!V20," ",'Level 1'!W20," ",'Level 1'!X20," ",'Level 1'!Z20, " ",'Level 1'!AA20, " ","Insurance: ",'Level 1'!A20) -> Detail: Claim not on file. Patient is active ; Payor ID & Address: 08-03-2070; Fax # (If Fax Yes):8595502662 No Limit Payment Call Ref#: 1606 Cust Rep: Irvin Additional Notes: Claim Resubmitted electronically on 05/06/2022 - SN // Rep State that CNOF,Effective Date:01/01/2021, Mailing Adrss: P.O.BOX 188037,Chattanooga,TN 37422 Rep Name: Michal Call Ref: 1569 Insurance: Cigna Out Of Network | C20: ='Level 1'!Y20 -> Task Sub Pending Claims Queue | D20: =VLOOKUP(C20,Table2[#All],3,FALSE) -> N/A | E20: Review in next report | F20: SN/NE | G20: Claim Resubmitted electronically on 05/06/2022
A21: =CONCATENATE("Pt Id:",'Level 1'!E21," ","Pt Name: ",'Level 1'!F21," ","DOS: ", TEXT('Level 1'!H21,"mm-dd-yyyy")," "," Amnt: ","$",'Level 1'!J21," ", 'Level 1'!N21) -> Pt Id:5823 Pt Name: Johnson , Alina DOS: 03-23-2022 Amnt: $496 Note | B21: =CONCATENATE("Detail: ",'Level 1'!N21," ",'Level 1'!O21,TEXT('Level 1'!P21," mm-dd-yyyy"),";"," ",'Level 1'!Q21,'Level 1'!R21," ",'Level 1'!T21," ","Payment "," ",'Level 1'!U21," ",'Level 1'!V21," ",'Level 1'!W21," ",'Level 1'!X21," ",'Level 1'!Z21, " ",'Level 1'!AA21, " ","Insurance: ",'Level 1'!A21) -> Detail: Note Q1 01-00-1900; Q2 Payment Q4 Q5 Additional Notes: Insurance: Cigna | C21: ='Level 1'!Y21 -> Action | D21: =VLOOKUP(C21,Table2[#All],3,FALSE) -> What we need from you/Reason | E21: Claim Status
A22: =CONCATENATE("Pt Id:",'Level 1'!E22," ","Pt Name: ",'Level 1'!F22," ","DOS: ", TEXT('Level 1'!H22,"mm-dd-yyyy")," "," Amnt: ","$",'Level 1'!J22," ", 'Level 1'!N22) -> Pt Id:9036 Pt Name: Johnson, Aila DOS: 03-23-2022 Amnt: $396 Note | B22: =CONCATENATE("Detail: ",'Level 1'!N22," ",'Level 1'!O22,TEXT('Level 1'!P22," mm-dd-yyyy"),";"," ",'Level 1'!Q22,'Level 1'!R22," ",'Level 1'!T22," ","Payment "," ",'Level 1'!U22," ",'Level 1'!V22," ",'Level 1'!W22," ",'Level 1'!X22," ",'Level 1'!Z22, " ",'Level 1'!AA22, " ","Insurance: ",'Level 1'!A22) -> Detail: Note Q1 01-00-1900; Q2 Payment Q4 Q5 Additional Notes: Insurance: Cigna | C22: ='Level 1'!Y22 -> Action | D22: =VLOOKUP(C22,Table2[#All],3,FALSE) -> What we need from you/Reason | E22: Claim Status
A23: =CONCATENATE("Pt Id:",'Level 1'!E23," ","Pt Name: ",'Level 1'!F23," ","DOS: ", TEXT('Level 1'!H23,"mm-dd-yyyy")," "," Amnt: ","$",'Level 1'!J23," ", 'Level 1'!N23) -> Pt Id:7711 Pt Name: Kienia, Jaxon DOS: 03-16-2022 Amnt: $940 Note | B23: =CONCATENATE("Detail: ",'Level 1'!N23," ",'Level 1'!O23,TEXT('Level 1'!P23," mm-dd-yyyy"),";"," ",'Level 1'!Q23,'Level 1'!R23," ",'Level 1'!T23," ","Payment "," ",'Level 1'!U23," ",'Level 1'!V23," ",'Level 1'!W23," ",'Level 1'!X23," ",'Level 1'!Z23, " ",'Level 1'!AA23, " ","Insurance: ",'Level 1'!A23) -> Detail: Note Q1 01-00-1900; Q2 Payment Q4 Q5 Additional Notes: Insurance: Cigna | C23: ='Level 1'!Y23 -> Action | D23: =VLOOKUP(C23,Table2[#All],3,FALSE) -> What we need from you/Reason | E23: Claim Status
A24: =CONCATENATE("Pt Id:",'Level 1'!E24," ","Pt Name: ",'Level 1'!F24," ","DOS: ", TEXT('Level 1'!H24,"mm-dd-yyyy")," "," Amnt: ","$",'Level 1'!J24," ", 'Level 1'!N24) -> Pt Id:8777 Pt Name: Michaelis, Benjamin DOS: 03-10-2022 Amnt: $1062 Note | B24: =CONCATENATE("Detail: ",'Level 1'!N24," ",'Level 1'!O24,TEXT('Level 1'!P24," mm-dd-yyyy"),";"," ",'Level 1'!Q24,'Level 1'!R24," ",'Level 1'!T24," ","Payment "," ",'Level 1'!U24," ",'Level 1'!V24," ",'Level 1'!W24," ",'Level 1'!X24," ",'Level 1'!Z24, " ",'Level 1'!AA24, " ","Insurance: ",'Level 1'!A24) -> Detail: Note Q1 01-00-1900; Q2 Payment Q4 Q5 Additional Notes: Insurance: Cigna | C24: ='Level 1'!Y24 -> Action | D24: =VLOOKUP(C24,Table2[#All],3,FALSE) -> What we need from you/Reason | E24: Claim Status
A25: =CONCATENATE("Pt Id:",'Level 1'!E25," ","Pt Name: ",'Level 1'!F25," ","DOS: ", TEXT('Level 1'!H25,"mm-dd-yyyy")," "," Amnt: ","$",'Level 1'!J25," ", 'Level 1'!N25) -> Pt Id:9237 Pt Name: Salgado, Manuel DOS: 03-10-2022 Amnt: $256.4 Note | B25: =CONCATENATE("Detail: ",'Level 1'!N25," ",'Level 1'!O25,TEXT('Level 1'!P25," mm-dd-yyyy"),";"," ",'Level 1'!Q25,'Level 1'!R25," ",'Level 1'!T25," ","Payment "," ",'Level 1'!U25," ",'Level 1'!V25," ",'Level 1'!W25," ",'Level 1'!X25," ",'Level 1'!Z25, " ",'Level 1'!AA25, " ","Insurance: ",'Level 1'!A25) -> Detail: Note Q1 01-00-1900; Q2 Payment Q4 Q5 Additional Notes: Insurance: Cigna | C25: ='Level 1'!Y25 -> Action | D25: =VLOOKUP(C25,Table2[#All],3,FALSE) -> What we need from you/Reason | E25: Claim Status
A26: =CONCATENATE("Pt Id:",'Level 1'!E26," ","Pt Name: ",'Level 1'!F26," ","DOS: ", TEXT('Level 1'!H26,"mm-dd-yyyy")," "," Amnt: ","$",'Level 1'!J26," ", 'Level 1'!N26) -> Pt Id:7471 Pt Name: Cox, Racheal DOS: 07-07-2021 Amnt: $820.8 Note | B26: =CONCATENATE("Detail: ",'Level 1'!N26," ",'Level 1'!O26,TEXT('Level 1'!P26," mm-dd-yyyy"),";"," ",'Level 1'!Q26,'Level 1'!R26," ",'Level 1'!T26," ","Payment "," ",'Level 1'!U26," ",'Level 1'!V26," ",'Level 1'!W26," ",'Level 1'!X26," ",'Level 1'!Z26, " ",'Level 1'!AA26, " ","Insurance: ",'Level 1'!A26) -> Detail: Note Q1 01-00-1900; Q2 Payment Q4 Q5 Additional Notes: Insurance: Cigna | C26: ='Level 1'!Y26 -> Action | D26: =VLOOKUP(C26,Table2[#All],3,FALSE) -> What we need from you/Reason | E26: Claim Status
A27: =CONCATENATE("Pt Id:",'Level 1'!E27," ","Pt Name: ",'Level 1'!F27," ","DOS: ", TEXT('Level 1'!H27,"mm-dd-yyyy")," "," Amnt: ","$",'Level 1'!J27," ", 'Level 1'!N27) -> Pt Id:5759 Pt Name: Sexton Free , Brittney DOS: 03-04-2022 Amnt: $1315.2 Note | B27: =CONCATENATE("Detail: ",'Level 1'!N27," ",'Level 1'!O27,TEXT('Level 1'!P27," mm-dd-yyyy"),";"," ",'Level 1'!Q27,'Level 1'!R27," ",'Level 1'!T27," ","Payment "," ",'Level 1'!U27," ",'Level 1'!V27," ",'Level 1'!W27," ",'Level 1'!X27," ",'Level 1'!Z27, " ",'Level 1'!AA27, " ","Insurance: ",'Level 1'!A27) -> Detail: Note Q1 01-00-1900; Q2 Payment Q4 Q5 Additional Notes: Insurance: Cigna | C27: ='Level 1'!Y27 -> Action | D27: =VLOOKUP(C27,Table2[#All],3,FALSE) -> What we need from you/Reason | E27: Claim Status
A28: =CONCATENATE("Pt Id:",'Level 1'!E28," ","Pt Name: ",'Level 1'!F28," ","DOS: ", TEXT('Level 1'!H28,"mm-dd-yyyy")," "," Amnt: ","$",'Level 1'!J28," ", 'Level 1'!N28) -> Pt Id:5759 Pt Name: Sexton Free , Brittney DOS: 02-09-2022 Amnt: $253.2 Procedure is not a covered benefit; | B28: =CONCATENATE("Detail: ",'Level 1'!N28," ",'Level 1'!O28,TEXT('Level 1'!P28," mm-dd-yyyy"),";"," ",'Level 1'!Q28,'Level 1'!R28," ",'Level 1'!T28," ","Payment "," ",'Level 1'!U28," ",'Level 1'!V28," ",'Level 1'!W28," ",'Level 1'!X28," ",'Level 1'!Z28, " ",'Level 1'!AA28, " ","Insurance: ",'Level 1'!A28) -> Detail: Procedure is not a covered benefit; Why? Not covered under pt plan; Call Ref#:1142 RHEA Payment 0 0 Additional Notes: CLM#D22042654574,Processed Date: 02/11/2022,Your plan does not provide benefits for this service,Patient Resp: $253.20 Insurance: Cigna | C28: ='Level 1'!Y28 -> Task Client - Denied Claim Queue | D28: =VLOOKUP(C28,Table2[#All],3,FALSE) -> What We Need From You: Pls confirm if we can close the claims Reason: To close claim | E28: Claim Status
A29: =CONCATENATE("Pt Id:",'Level 1'!E29," ","Pt Name: ",'Level 1'!F29," ","DOS: ", TEXT('Level 1'!H29,"mm-dd-yyyy")," "," Amnt: ","$",'Level 1'!J29," ", 'Level 1'!N29) -> Pt Id:5759 Pt Name: Sexton Free , Brittney DOS: 01-12-2022 Amnt: $210 Claim Paid by EFT; | B29: =CONCATENATE("Detail: ",'Level 1'!N29," ",'Level 1'!O29,TEXT('Level 1'!P29," mm-dd-yyyy"),";"," ",'Level 1'!Q29,'Level 1'!R29," ",'Level 1'!T29," ","Payment "," ",'Level 1'!U29," ",'Level 1'!V29," ",'Level 1'!W29," ",'Level 1'!X29," ",'Level 1'!Z29, " ",'Level 1'!AA29, " ","Insurance: ",'Level 1'!A29) -> Detail: Claim Paid by EFT; Issue Date: 01-19-2022; EFT#9999730907 Bulk Payment Call Ref#: 83827 Cust Rep: Mabby Additional Notes: Rep States that Claim Paid,Claim No:E220186079630,Patient Resp: NIL. Insurance: Cigna | C29: ='Level 1'!Y29 -> Task Post Pmt Queue | D29: =VLOOKUP(C29,Table2[#All],3,FALSE) -> N/A | E29: Claim Resolved | F29: MU/MA | G29: Payment Posted on 05.01.2022
A30: =CONCATENATE("Pt Id:",'Level 1'!E30," ","Pt Name: ",'Level 1'!F30," ","DOS: ", TEXT('Level 1'!H30,"mm-dd-yyyy")," "," Amnt: ","$",'Level 1'!J30," ", 'Level 1'!N30) -> Pt Id:8803 Pt Name: Gibson, Karl DOS: 01-14-2022 Amnt: $294.8 Claim Paid by EFT; | B30: =CONCATENATE("Detail: ",'Level 1'!N30," ",'Level 1'!O30,TEXT('Level 1'!P30," mm-dd-yyyy"),";"," ",'Level 1'!Q30,'Level 1'!R30," ",'Level 1'!T30," ","Payment "," ",'Level 1'!U30," ",'Level 1'!V30," ",'Level 1'!W30," ",'Level 1'!X30," ",'Level 1'!Z30, " ",'Level 1'!AA30, " ","Insurance: ",'Level 1'!A30) -> Detail: Claim Paid by EFT; Issue Date: 01-19-2022; EFT#9999761865 Bulk Payment Call Ref#: 7994 Cust Rep: Mabby Additional Notes: Rep States that Claim Paid,Claim No:S220186079630,Patient Resp: NIL All the lines paid on the claim. Insurance: Cigna | C30: ='Level 1'!Y30 -> Task Post Pmt Queue | D30: =VLOOKUP(C30,Table2[#All],3,FALSE) -> N/A | E30: Claim Resolved | F30: MU/MA | G30: Payment Posted on 05.01.2022
A31: =CONCATENATE("Pt Id:",'Level 1'!E31," ","Pt Name: ",'Level 1'!F31," ","DOS: ", TEXT('Level 1'!H31,"mm-dd-yyyy")," "," Amnt: ","$",'Level 1'!J31," ", 'Level 1'!N31) -> Pt Id:8802 Pt Name: Huston, Olivia DOS: 01-14-2022 Amnt: $256.4 Claim not on file. Patient is active ; | B31: =CONCATENATE("Detail: ",'Level 1'!N31," ",'Level 1'!O31,TEXT('Level 1'!P31," mm-dd-yyyy"),";"," ",'Level 1'!Q31,'Level 1'!R31," ",'Level 1'!T31," ","Payment "," ",'Level 1'!U31," ",'Level 1'!V31," ",'Level 1'!W31," ",'Level 1'!X31," ",'Level 1'!Z31, " ",'Level 1'!AA31, " ","Insurance: ",'Level 1'!A31) -> Detail: Claim not on file. Patient is active ; Payor ID & Address: 08-03-2070; Fax # (If Fax Yes):8595502662 No Limit Payment Call Ref#: 6550 Cust Rep: Mabby Additional Notes: Claim Resubmitted through fax on 05/06/2022 - SN // Rep states that clm is not on file for the dos, the patient is active, we can send send the clm through fax #8595502662, NO TFL. Insurance: Cigna | C31: ='Level 1'!Y31 -> Task Sub Pending Claims Queue | D31: =VLOOKUP(C31,Table2[#All],3,FALSE) -> N/A | E31: Review in next report | F31: SN/NE | G31: Claim Resubmitted through fax on 05/06/2022
A32: =CONCATENATE("Pt Id:",'Level 1'!E32," ","Pt Name: ",'Level 1'!F32," ","DOS: ", TEXT('Level 1'!H32,"mm-dd-yyyy")," "," Amnt: ","$",'Level 1'!J32," ", 'Level 1'!N32) -> Pt Id:8777 Pt Name: Michaelis, Benjamin DOS: 01-05-2022 Amnt: $186 Claim Paid by EFT; | B32: =CONCATENATE("Detail: ",'Level 1'!N32," ",'Level 1'!O32,TEXT('Level 1'!P32," mm-dd-yyyy"),";"," ",'Level 1'!Q32,'Level 1'!R32," ",'Level 1'!T32," ","Payment "," ",'Level 1'!U32," ",'Level 1'!V32," ",'Level 1'!W32," ",'Level 1'!X32," ",'Level 1'!Z32, " ",'Level 1'!AA32, " ","Insurance: ",'Level 1'!A32) -> Detail: Claim Paid by EFT; Issue Date: 01-14-2022; EFT#9999761866 bulk Payment Call Ref#: 5749 Cust Rep: Joei Additional Notes: Rep States that Claim Paid,Paid Amt: 123.20,Claim No:E220146565650,Patient Resp:$62.80 All the lines paid on the claim. Insurance: Cigna | C32: ='Level 1'!Y32 -> Task Post Pmt Queue | D32: =VLOOKUP(C32,Table2[#All],3,FALSE) -> N/A | E32: INSB NV Team Task | F32: SN
A33: =CONCATENATE("Pt Id:",'Level 1'!E33," ","Pt Name: ",'Level 1'!F33," ","DOS: ", TEXT('Level 1'!H33,"mm-dd-yyyy")," "," Amnt: ","$",'Level 1'!J33," ", 'Level 1'!N33) -> Pt Id:8713 Pt Name: Delk, Mark DOS: 12-27-2021 Amnt: $372.8 Claim Paid by EFT; | B33: =CONCATENATE("Detail: ",'Level 1'!N33," ",'Level 1'!O33,TEXT('Level 1'!P33," mm-dd-yyyy"),";"," ",'Level 1'!Q33,'Level 1'!R33," ",'Level 1'!T33," ","Payment "," ",'Level 1'!U33," ",'Level 1'!V33," ",'Level 1'!W33," ",'Level 1'!X33," ",'Level 1'!Z33, " ",'Level 1'!AA33, " ","Insurance: ",'Level 1'!A33) -> Detail: Claim Paid by EFT; Issue Date: 12-31-2021; EFT#9999367367 Sep Payment Call Ref#: 4651 Cust Rep: natalie Additional Notes: Rep states that, Claim paid EFT Mode. Cashed out 01/05/2022 for $320.40. Rep name: NICs. Ref# 8666. Claim# E213656187000.//EOB Requested 24 Hr as per Rep Rep Name: Michal Call Ref: 1569//GET EOB -SN // Rep States that the Claim Paid,Claim No:E21365618700, paid amt$320.40 Patient Resp: $52.40 Insurance: Cigna | C33: ='Level 1'!Y33 -> Task Post Pmt Queue | D33: =VLOOKUP(C33,Table2[#All],3,FALSE) -> N/A | E33: INSB NV Team Task | F33: SN
A34: =CONCATENATE("Pt Id:",'Level 1'!E34," ","Pt Name: ",'Level 1'!F34," ","DOS: ", TEXT('Level 1'!H34,"mm-dd-yyyy")," "," Amnt: ","$",'Level 1'!J34," ", 'Level 1'!N34) -> Pt Id:8165 Pt Name: Ramsey, Jerod DOS: 10-08-2021 Amnt: $244.8 Claim Paid by EFT; | B34: =CONCATENATE("Detail: ",'Level 1'!N34," ",'Level 1'!O34,TEXT('Level 1'!P34," mm-dd-yyyy"),";"," ",'Level 1'!Q34,'Level 1'!R34," ",'Level 1'!T34," ","Payment "," ",'Level 1'!U34," ",'Level 1'!V34," ",'Level 1'!W34," ",'Level 1'!X34," ",'Level 1'!Z34, " ",'Level 1'!AA34, " ","Insurance: ",'Level 1'!A34) -> Detail: Claim Paid by EFT; Issue Date: 10-13-2021; EFT#9997740966 Single Payment Call Ref#: 5422 Cust Rep: Ey Additional Notes: Pd $105 Pt responsibility $'0' Clm #D212856143770. All codes are got paid. Eob requested Insurance: Cigna | C34: ='Level 1'!Y34 -> Task Post Pmt Queue | D34: =VLOOKUP(C34,Table2[#All],3,FALSE) -> N/A | E34: Claim Resolved | F34: MU/MA | G34: Payment Posted on 05.01.2022
A35: =CONCATENATE("Pt Id:",'Level 1'!E35," ","Pt Name: ",'Level 1'!F35," ","DOS: ", TEXT('Level 1'!H35,"mm-dd-yyyy")," "," Amnt: ","$",'Level 1'!J35," ", 'Level 1'!N35) -> Pt Id:7712 Pt Name: Kienia, Brooke DOS: 08-18-2021 Amnt: $273.2 Claim Paid by EFT; | B35: =CONCATENATE("Detail: ",'Level 1'!N35," ",'Level 1'!O35,TEXT('Level 1'!P35," mm-dd-yyyy"),";"," ",'Level 1'!Q35,'Level 1'!R35," ",'Level 1'!T35," ","Payment "," ",'Level 1'!U35," ",'Level 1'!V35," ",'Level 1'!W35," ",'Level 1'!X35," ",'Level 1'!Z35, " ",'Level 1'!AA35, " ","Insurance: ",'Level 1'!A35) -> Detail: Claim Paid by EFT; Issue Date: 08-30-2021; EFT#128408296 Bulk Payment Call Ref#: 7115 Cust Rep: Roger Additional Notes: Rep States that Claim Paid,Claim No:E212426363940, paid amt$124 Patient Resp: NIL, All the lines paid on the claim. Insurance: Cigna | C35: ='Level 1'!Y35 -> Task Post Pmt Queue | D35: =VLOOKUP(C35,Table2[#All],3,FALSE) -> N/A | E35: Claim Resolved | F35: MU/MA | G35: Payment Posted on 05.01.2022
A36: =CONCATENATE("Pt Id:",'Level 1'!E36," ","Pt Name: ",'Level 1'!F36," ","DOS: ", TEXT('Level 1'!H36,"mm-dd-yyyy")," "," Amnt: ","$",'Level 1'!J36," ", 'Level 1'!N36) -> Pt Id:7711 Pt Name: Kienia, Jaxon DOS: 08-18-2021 Amnt: $256.4 Claim Paid by EFT; | B36: =CONCATENATE("Detail: ",'Level 1'!N36," ",'Level 1'!O36,TEXT('Level 1'!P36," mm-dd-yyyy"),";"," ",'Level 1'!Q36,'Level 1'!R36," ",'Level 1'!T36," ","Payment "," ",'Level 1'!U36," ",'Level 1'!V36," ",'Level 1'!W36," ",'Level 1'!X36," ",'Level 1'!Z36, " ",'Level 1'!AA36, " ","Insurance: ",'Level 1'!A36) -> Detail: Claim Paid by EFT; Issue Date: 08-30-2021; EFT#9996836027 Bulk Payment Call Ref#: 9985 Cust Rep: sara Additional Notes: EOB Requested//Get EOB - SN // Rep States that the Claim Paid,Claim No:D212426363980, paid amt$114 , All the lines paid on the claim. Insurance: Cigna | C36: ='Level 1'!Y36 -> Task Post Pmt Queue | D36: =VLOOKUP(C36,Table2[#All],3,FALSE) -> N/A | E36: Claim Resolved | F36: MU/MA | G36: Payment Posted on 05.01.2022
A37: =CONCATENATE("Pt Id:",'Level 1'!E37," ","Pt Name: ",'Level 1'!F37," ","DOS: ", TEXT('Level 1'!H37,"mm-dd-yyyy")," "," Amnt: ","$",'Level 1'!J37," ", 'Level 1'!N37) -> Pt Id:7755 Pt Name: Al-Jehani, Afton DOS: 08-17-2021 Amnt: $325.2 Claim Paid by EFT; | B37: =CONCATENATE("Detail: ",'Level 1'!N37," ",'Level 1'!O37,TEXT('Level 1'!P37," mm-dd-yyyy"),";"," ",'Level 1'!Q37,'Level 1'!R37," ",'Level 1'!T37," ","Payment "," ",'Level 1'!U37," ",'Level 1'!V37," ",'Level 1'!W37," ",'Level 1'!X37," ",'Level 1'!Z37, " ",'Level 1'!AA37, " ","Insurance: ",'Level 1'!A37) -> Detail: Claim Paid by EFT; Issue Date: 08-31-2021; EFT#6836028 Single Payment Call Ref#: 3545 Cust Rep: karissa Additional Notes: Pd $105 Pt responsibility $47.00 Clm #E2124726363920. All codes are got paid. Eob requested Insurance: Cigna | C37: ='Level 1'!Y37 -> Task Post Pmt Queue | D37: =VLOOKUP(C37,Table2[#All],3,FALSE) -> N/A | E37: Claim Resolved | F37: MU/MA | G37: Payment Posted on 05.01.2022
A38: =CONCATENATE("Pt Id:",'Level 1'!E38," ","Pt Name: ",'Level 1'!F38," ","DOS: ", TEXT('Level 1'!H38,"mm-dd-yyyy")," "," Amnt: ","$",'Level 1'!J38," ", 'Level 1'!N38) -> Pt Id:3523 Pt Name: SHERMAN, STEPHANIE DOS: 03-10-2021 Amnt: $230 Claim Paid by EFT; | B38: =CONCATENATE("Detail: ",'Level 1'!N38," ",'Level 1'!O38,TEXT('Level 1'!P38," mm-dd-yyyy"),";"," ",'Level 1'!Q38,'Level 1'!R38," ",'Level 1'!T38," ","Payment "," ",'Level 1'!U38," ",'Level 1'!V38," ",'Level 1'!W38," ",'Level 1'!X38," ",'Level 1'!Z38, " ",'Level 1'!AA38, " ","Insurance: ",'Level 1'!A38) -> Detail: Claim Paid by EFT; Issue Date: 05-05-2021; EFT#921050501590 Bulk Payment Call Ref#: 021720211010 Cust Rep: jane Additional Notes: Rep states that the clm#202110611427-1 total amt$181 Pt resp paid on the Nil. Insurance: DELTA DENTAL OF IOWA | C38: ='Level 1'!Y38 -> Task Post Pmt Queue | D38: =VLOOKUP(C38,Table2[#All],3,FALSE) -> N/A | E38: INSB NV Team Task | F38: SN
A39: =CONCATENATE("Pt Id:",'Level 1'!E39," ","Pt Name: ",'Level 1'!F39," ","DOS: ", TEXT('Level 1'!H39,"mm-dd-yyyy")," "," Amnt: ","$",'Level 1'!J39," ", 'Level 1'!N39) -> Pt Id:5758 Pt Name: Tamsen , Robin DOS: 10-29-2021 Amnt: $593.2 Claim Partially Paid by EFT; Add notes | B39: =CONCATENATE("Detail: ",'Level 1'!N39," ",'Level 1'!O39,TEXT('Level 1'!P39," mm-dd-yyyy"),";"," ",'Level 1'!Q39,'Level 1'!R39," ",'Level 1'!T39," ","Payment "," ",'Level 1'!U39," ",'Level 1'!V39," ",'Level 1'!W39," ",'Level 1'!X39," ",'Level 1'!Z39, " ",'Level 1'!AA39, " ","Insurance: ",'Level 1'!A39) -> Detail: Claim Partially Paid by EFT; Add notes Issue Date: 04-07-2022; EFT#9907646801 Sep Payment Call Ref#: 2001833603 Cust Rep: Musheerah Additional Notes: Rep State Clm No:2111102306400,Paid Amt: 190.50,Patient Resp 292.50 Code D9230 is denied as it is not covered //Rep states that claim has been sent for reprosessing and the EOB has sent to the provideers mailing address. Rep Santo id #2001261703. ///REWORK & UPDATE - SN // Rep states that the clm #2112142747268, the claim is on hold because the ins is wondering that the member has the sec policy with him, there is a DPOW-CCHP is the sec policy for the patient, Rep says that we have to submitt with only the primay insurance policy which is Delta dental to allow the benifits of the claim. Insurance: DELTA DENTAL OF MICHIGAN | C39: ='Level 1'!Y39 -> Task Post Pmt Queue | D39: =VLOOKUP(C39,Table2[#All],3,FALSE) -> N/A | E39: Claim Status
A40: =CONCATENATE("Pt Id:",'Level 1'!E40," ","Pt Name: ",'Level 1'!F40," ","DOS: ", TEXT('Level 1'!H40,"mm-dd-yyyy")," "," Amnt: ","$",'Level 1'!J40," ", 'Level 1'!N40) -> Pt Id:8109 Pt Name: Tweedt, David DOS: 02-25-2022 Amnt: $890 Note | B40: =CONCATENATE("Detail: ",'Level 1'!N40," ",'Level 1'!O40,TEXT('Level 1'!P40," mm-dd-yyyy"),";"," ",'Level 1'!Q40,'Level 1'!R40," ",'Level 1'!T40," ","Payment "," ",'Level 1'!U40," ",'Level 1'!V40," ",'Level 1'!W40," ",'Level 1'!X40," ",'Level 1'!Z40, " ",'Level 1'!AA40, " ","Insurance: ",'Level 1'!A40) -> Detail: Note Q1 01-00-1900; Q2 Payment Q4 Q5 Additional Notes: Insurance: Delta Dental of Minnesota | C40: ='Level 1'!Y40 -> Action | D40: =VLOOKUP(C40,Table2[#All],3,FALSE) -> What we need from you/Reason | E40: Claim Status
A41: =CONCATENATE("Pt Id:",'Level 1'!E41," ","Pt Name: ",'Level 1'!F41," ","DOS: ", TEXT('Level 1'!H41,"mm-dd-yyyy")," "," Amnt: ","$",'Level 1'!J41," ", 'Level 1'!N41) -> Pt Id:479 Pt Name: Penland, Teagan DOS: 12-08-2021 Amnt: $333.2 Procedure is not a covered benefit; | B41: =CONCATENATE("Detail: ",'Level 1'!N41," ",'Level 1'!O41,TEXT('Level 1'!P41," mm-dd-yyyy"),";"," ",'Level 1'!Q41,'Level 1'!R41," ",'Level 1'!T41," ","Payment "," ",'Level 1'!U41," ",'Level 1'!V41," ",'Level 1'!W41," ",'Level 1'!X41," ",'Level 1'!Z41, " ",'Level 1'!AA41, " ","Insurance: ",'Level 1'!A41) -> Detail: Procedure is not a covered benefit; Why? 01-00-1900; Call Ref#: Payment 0 0 Additional Notes: Clm # 2112152962231, This claim could not be processed since the submitted combination of member ID, first name and/or date of birth could not be located in our records. Please confirm the claim was submitted to the correct carrier and if so, resubmit the claim with the correct member ID (which may not be the Social Security Number), first name and date of birth. Insurance: Delta Dental of Minnesota | C41: ='Level 1'!Y41 -> Task Client - Denied Claim Queue | D41: =VLOOKUP(C41,Table2[#All],3,FALSE) -> What We Need From You: Pls confirm if we can close the claims Reason: To close claim | E41: INSB NV Team Task | F41: SN
A42: =CONCATENATE("Pt Id:",'Level 1'!E42," ","Pt Name: ",'Level 1'!F42," ","DOS: ", TEXT('Level 1'!H42,"mm-dd-yyyy")," "," Amnt: ","$",'Level 1'!J42," ", 'Level 1'!N42) -> Pt Id:5310 Pt Name: Turner, Lukas DOS: 10-13-2021 Amnt: $326 Claim Partially Paid by EFT; Add notes | B42: =CONCATENATE("Detail: ",'Level 1'!N42," ",'Level 1'!O42,TEXT('Level 1'!P42," mm-dd-yyyy"),";"," ",'Level 1'!Q42,'Level 1'!R42," ",'Level 1'!T42," ","Payment "," ",'Level 1'!U42," ",'Level 1'!V42," ",'Level 1'!W42," ",'Level 1'!X42," ",'Level 1'!Z42, " ",'Level 1'!AA42, " ","Insurance: ",'Level 1'!A42) -> Detail: Claim Partially Paid by EFT; Add notes Issue Date: 12-14-2021; EFT#9100859245 Single Payment Call Ref#: 1538617207 Cust Rep: Siera Additional Notes: Rep states that clm #2112142789895, paid amt $196,Rcd on 12/14/2021 processed on the same day D0272 and D1208 is denied due to frequency and the freq for both is 1 per calender year, his dates for both the codes are 4/12/2021. ///Get the status - SN Insurance: Delta Dental of Minnesota | C42: ='Level 1'!Y42 -> Task Post Pmt Queue | D42: =VLOOKUP(C42,Table2[#All],3,FALSE) -> N/A | E42: INSB NV Team Task | F42: SN
A43: =CONCATENATE("Pt Id:",'Level 1'!E43," ","Pt Name: ",'Level 1'!F43," ","DOS: ", TEXT('Level 1'!H43,"mm-dd-yyyy")," "," Amnt: ","$",'Level 1'!J43," ", 'Level 1'!N43) -> Pt Id:7084 Pt Name: Mccarter , Markayla DOS: 09-22-2021 Amnt: $0 Claim not on file. Patient is active ; | B43: =CONCATENATE("Detail: ",'Level 1'!N43," ",'Level 1'!O43,TEXT('Level 1'!P43," mm-dd-yyyy"),";"," ",'Level 1'!Q43,'Level 1'!R43," ",'Level 1'!T43," ","Payment "," ",'Level 1'!U43," ",'Level 1'!V43," ",'Level 1'!W43," ",'Level 1'!X43," ",'Level 1'!Z43, " ",'Level 1'!AA43, " ","Insurance: ",'Level 1'!A43) -> Detail: Claim not on file. Patient is active ; Payor ID & Address: 03-01-1919; Fax # (If Fax Yes): 12 Months from Dos Payment Call Ref#: 1538986657 Cust Rep: ANGIE Additional Notes: CNOF - patient Active. Address: PO Box# 9120, Farmington Hill MI -48333 Insurance: Delta Dental of Minnesota | C43: ='Level 1'!Y43 -> Task Sub Pending Claims Queue | D43: =VLOOKUP(C43,Table2[#All],3,FALSE) -> N/A | E43: Claim Resolved | F43: SN/NE | G43: Claim resolved on 05/06/2022
A44: =CONCATENATE("Pt Id:",'Level 1'!E44," ","Pt Name: ",'Level 1'!F44," ","DOS: ", TEXT('Level 1'!H44,"mm-dd-yyyy")," "," Amnt: ","$",'Level 1'!J44," ", 'Level 1'!N44) -> Pt Id:821 Pt Name: Cordero, Ana DOS: 12-07-2021 Amnt: $61.2 Patient not active/no active policy; | B44: =CONCATENATE("Detail: ",'Level 1'!N44," ",'Level 1'!O44,TEXT('Level 1'!P44," mm-dd-yyyy"),";"," ",'Level 1'!Q44,'Level 1'!R44," ",'Level 1'!T44," ","Payment "," ",'Level 1'!U44," ",'Level 1'!V44," ",'Level 1'!W44," ",'Level 1'!X44," ",'Level 1'!Z44, " ",'Level 1'!AA44, " ","Insurance: ",'Level 1'!A44) -> Detail: Patient not active/no active policy; Policy Term Dt: 10-20-2021; Call Ref#:9104701 Siera Payment 0 0 Additional Notes: Rep states that the policy has been terminated for the patient, term date 10/20/2021. Insurance: Delta Dental of Missouri | C44: ='Level 1'!Y44 -> Task Denied Claims Queue | D44: =VLOOKUP(C44,Table2[#All],3,FALSE) -> What We Need From You: Reason: | E44: Claim Status
A45: =CONCATENATE("Pt Id:",'Level 1'!E45," ","Pt Name: ",'Level 1'!F45," ","DOS: ", TEXT('Level 1'!H45,"mm-dd-yyyy")," "," Amnt: ","$",'Level 1'!J45," ", 'Level 1'!N45) -> Pt Id:3001 Pt Name: Mejia , Jason DOS: 05-05-2021 Amnt: $782.8 Claim Paid by EFT; | B45: =CONCATENATE("Detail: ",'Level 1'!N45," ",'Level 1'!O45,TEXT('Level 1'!P45," mm-dd-yyyy"),";"," ",'Level 1'!Q45,'Level 1'!R45," ",'Level 1'!T45," ","Payment "," ",'Level 1'!U45," ",'Level 1'!V45," ",'Level 1'!W45," ",'Level 1'!X45," ",'Level 1'!Z45, " ",'Level 1'!AA45, " ","Insurance: ",'Level 1'!A45) -> Detail: Claim Paid by EFT; Issue Date: 05-13-2021; EFT#11234233 Single Payment Call Ref#: 20220139569 Cust Rep: Morgan Additional Notes: Rep states that clm #202113031228400, paid amt $153.40, It is a direct deposit cased dt 5/13/2021, Pt res 153.40. Insurance: Delta Dental of Washington | C45: ='Level 1'!Y45 -> Task Post Pmt Queue | D45: =VLOOKUP(C45,Table2[#All],3,FALSE) -> N/A | E45: INSB NV Team Task | F45: SN
A46: =CONCATENATE("Pt Id:",'Level 1'!E46," ","Pt Name: ",'Level 1'!F46," ","DOS: ", TEXT('Level 1'!H46,"mm-dd-yyyy")," "," Amnt: ","$",'Level 1'!J46," ", 'Level 1'!N46) -> Pt Id:1865 Pt Name: Clark, Charles DOS: 05-03-2021 Amnt: $610.8 Procedure is not a covered benefit; | B46: =CONCATENATE("Detail: ",'Level 1'!N46," ",'Level 1'!O46,TEXT('Level 1'!P46," mm-dd-yyyy"),";"," ",'Level 1'!Q46,'Level 1'!R46," ",'Level 1'!T46," ","Payment "," ",'Level 1'!U46," ",'Level 1'!V46," ",'Level 1'!W46," ",'Level 1'!X46," ",'Level 1'!Z46, " ",'Level 1'!AA46, " ","Insurance: ",'Level 1'!A46) -> Detail: Procedure is not a covered benefit; Why? Not eligible at DOS; Call Ref#:202200054335 Kathleen Payment 0 0 Additional Notes: Rep State that Claim Denied as patient is Inactive at the time of service,Termination Date:04/30/2021,Last Active Date:03/23/2020, Effective Date: 03/23/2020, Claim No:202113031229700, Processed & Denied Date: 05/28/2021, Patient Resp:$610.80 Insurance: Delta Dental of Washington | C46: ='Level 1'!Y46 -> Task Client - Denied Claim Queue | D46: =VLOOKUP(C46,Table2[#All],3,FALSE) -> What We Need From You: Pls confirm if we can close the claims Reason: To close claim | E46: INSB NV Team Task | F46: SN
A47: =CONCATENATE("Pt Id:",'Level 1'!E47," ","Pt Name: ",'Level 1'!F47," ","DOS: ", TEXT('Level 1'!H47,"mm-dd-yyyy")," "," Amnt: ","$",'Level 1'!J47," ", 'Level 1'!N47) -> Pt Id:5461 Pt Name: Syas, Brenae DOS: 04-15-2021 Amnt: $396 Claim Paid by EFT; | B47: =CONCATENATE("Detail: ",'Level 1'!N47," ",'Level 1'!O47,TEXT('Level 1'!P47," mm-dd-yyyy"),";"," ",'Level 1'!Q47,'Level 1'!R47," ",'Level 1'!T47," ","Payment "," ",'Level 1'!U47," ",'Level 1'!V47," ",'Level 1'!W47," ",'Level 1'!X47," ",'Level 1'!Z47, " ",'Level 1'!AA47, " ","Insurance: ",'Level 1'!A47) -> Detail: Claim Paid by EFT; Issue Date: 04-22-2021; EFT#11207602 Bulk Payment Call Ref#: 202200054382 Cust Rep: Kathleen Additional Notes: Rep State that Claim Paid,Claim No: 202110631644400, Paid Amt:$239.40,Paid by Bulk(Bulk Amt: $855.90) , Patient Resp:$76.60 Insurance: Delta Dental of Washington | C47: ='Level 1'!Y47 -> Task Post Pmt Queue | D47: =VLOOKUP(C47,Table2[#All],3,FALSE) -> N/A | E47: INSB NV Team Task | F47: SN
A48: =CONCATENATE("Pt Id:",'Level 1'!E48," ","Pt Name: ",'Level 1'!F48," ","DOS: ", TEXT('Level 1'!H48,"mm-dd-yyyy")," "," Amnt: ","$",'Level 1'!J48," ", 'Level 1'!N48) -> Pt Id:2870 Pt Name: Mejia, Viannie DOS: 04-15-2021 Amnt: $532 Write information in Addl Notes | B48: =CONCATENATE("Detail: ",'Level 1'!N48," ",'Level 1'!O48,TEXT('Level 1'!P48," mm-dd-yyyy"),";"," ",'Level 1'!Q48,'Level 1'!R48," ",'Level 1'!T48," ","Payment "," ",'Level 1'!U48," ",'Level 1'!V48," ",'Level 1'!W48," ",'Level 1'!X48," ",'Level 1'!Z48, " ",'Level 1'!AA48, " ","Insurance: ",'Level 1'!A48) -> Detail: Write information in Addl Notes Call Ref#: 01-00-1900; Cust Rep: Payment Additional Notes: Insurance: Delta Dental of Washington | C48: ='Level 1'!Y48 -> Team Lead to review & Follow-Up | D48: =VLOOKUP(C48,Table2[#All],3,FALSE) -> #N/A | E48: INSB NV Team Task | F48: SN
A49: =CONCATENATE("Pt Id:",'Level 1'!E49," ","Pt Name: ",'Level 1'!F49," ","DOS: ", TEXT('Level 1'!H49,"mm-dd-yyyy")," "," Amnt: ","$",'Level 1'!J49," ", 'Level 1'!N49) -> Pt Id:3001 Pt Name: Mejia , Jason DOS: 04-13-2021 Amnt: $748 Claim Paid by EFT; | B49: =CONCATENATE("Detail: ",'Level 1'!N49," ",'Level 1'!O49,TEXT('Level 1'!P49," mm-dd-yyyy"),";"," ",'Level 1'!Q49,'Level 1'!R49," ",'Level 1'!T49," ","Payment "," ",'Level 1'!U49," ",'Level 1'!V49," ",'Level 1'!W49," ",'Level 1'!X49," ",'Level 1'!Z49, " ",'Level 1'!AA49, " ","Insurance: ",'Level 1'!A49) -> Detail: Claim Paid by EFT; Issue Date: 04-22-2021; EFT#11207602 Bulk Payment Call Ref#: 20220139569 Cust Rep: Morgan Additional Notes: Rep states that clm #202110631649100, paid amt $411.30, It is a bulk amt $855.90, PR aamt $195.70, It’s a direct deposit, cashed dt 4/22/2021, There are 3 codes on the claim which has been paid. Insurance: Delta Dental of Washington | C49: ='Level 1'!Y49 -> Task Post Pmt Queue | D49: =VLOOKUP(C49,Table2[#All],3,FALSE) -> N/A | E49: INSB NV Team Task | F49: SN
A50: =CONCATENATE("Pt Id:",'Level 1'!E50," ","Pt Name: ",'Level 1'!F50," ","DOS: ", TEXT('Level 1'!H50,"mm-dd-yyyy")," "," Amnt: ","$",'Level 1'!J50," ", 'Level 1'!N50) -> Pt Id:3001 Pt Name: Mejia , Jason DOS: 03-18-2021 Amnt: $227.6 Claim Paid by EFT; | B50: =CONCATENATE("Detail: ",'Level 1'!N50," ",'Level 1'!O50,TEXT('Level 1'!P50," mm-dd-yyyy"),";"," ",'Level 1'!Q50,'Level 1'!R50," ",'Level 1'!T50," ","Payment "," ",'Level 1'!U50," ",'Level 1'!V50," ",'Level 1'!W50," ",'Level 1'!X50," ",'Level 1'!Z50, " ",'Level 1'!AA50, " ","Insurance: ",'Level 1'!A50) -> Detail: Claim Paid by EFT; Issue Date: 04-01-2021; EFT#11181248 Bulk Payment Call Ref#: 20220139569 Cust Rep: Morgan Additional Notes: Rep states that clm #202108332109200, paid amt $178, Patient res NIL, It’s a direct deposit cashed dt 4/1/2021, there are 6 codes on the claim which is paid. Insurance: Delta Dental of Washington | C50: ='Level 1'!Y50 -> Task Post Pmt Queue | D50: =VLOOKUP(C50,Table2[#All],3,FALSE) -> N/A | E50: INSB NV Team Task | F50: SN
A51: =CONCATENATE("Pt Id:",'Level 1'!E51," ","Pt Name: ",'Level 1'!F51," ","DOS: ", TEXT('Level 1'!H51,"mm-dd-yyyy")," "," Amnt: ","$",'Level 1'!J51," ", 'Level 1'!N51) -> Pt Id:2870 Pt Name: Mejia, Viannie DOS: 03-18-2021 Amnt: $227.6 Claim Paid by EFT; | B51: =CONCATENATE("Detail: ",'Level 1'!N51," ",'Level 1'!O51,TEXT('Level 1'!P51," mm-dd-yyyy"),";"," ",'Level 1'!Q51,'Level 1'!R51," ",'Level 1'!T51," ","Payment "," ",'Level 1'!U51," ",'Level 1'!V51," ",'Level 1'!W51," ",'Level 1'!X51," ",'Level 1'!Z51, " ",'Level 1'!AA51, " ","Insurance: ",'Level 1'!A51) -> Detail: Claim Paid by EFT; Issue Date: 04-01-2021; EFT#11181248 Bulk Payment Call Ref#: 202200139640 Cust Rep: Morgan Additional Notes: Rep states that clm #202108332129600, paid amt $178, patient res NIL, it’s a bulk payment $366, there are 6lines on the claim which has been paid. Insurance: Delta Dental of Washington | C51: ='Level 1'!Y51 -> Task Post Pmt Queue | D51: =VLOOKUP(C51,Table2[#All],3,FALSE) -> N/A | E51: INSB NV Team Task | F51: SN
A52: =CONCATENATE("Pt Id:",'Level 1'!E52," ","Pt Name: ",'Level 1'!F52," ","DOS: ", TEXT('Level 1'!H52,"mm-dd-yyyy")," "," Amnt: ","$",'Level 1'!J52," ", 'Level 1'!N52) -> Pt Id:6277 Pt Name: Legree, Cristie DOS: 03-31-2022 Amnt: $82.8 Note | B52: =CONCATENATE("Detail: ",'Level 1'!N52," ",'Level 1'!O52,TEXT('Level 1'!P52," mm-dd-yyyy"),";"," ",'Level 1'!Q52,'Level 1'!R52," ",'Level 1'!T52," ","Payment "," ",'Level 1'!U52," ",'Level 1'!V52," ",'Level 1'!W52," ",'Level 1'!X52," ",'Level 1'!Z52, " ",'Level 1'!AA52, " ","Insurance: ",'Level 1'!A52) -> Detail: Note Q1 01-00-1900; Q2 Payment Q4 Q5 Additional Notes: Insurance: Delta Dental Of Wisconsin | C52: ='Level 1'!Y52 -> Action | D52: =VLOOKUP(C52,Table2[#All],3,FALSE) -> What we need from you/Reason | E52: Claim Status
A53: =CONCATENATE("Pt Id:",'Level 1'!E53," ","Pt Name: ",'Level 1'!F53," ","DOS: ", TEXT('Level 1'!H53,"mm-dd-yyyy")," "," Amnt: ","$",'Level 1'!J53," ", 'Level 1'!N53) -> Pt Id:9286 Pt Name: Barber, Jazaria DOS: 03-23-2022 Amnt: $1480.4 Note | B53: =CONCATENATE("Detail: ",'Level 1'!N53," ",'Level 1'!O53,TEXT('Level 1'!P53," mm-dd-yyyy"),";"," ",'Level 1'!Q53,'Level 1'!R53," ",'Level 1'!T53," ","Payment "," ",'Level 1'!U53," ",'Level 1'!V53," ",'Level 1'!W53," ",'Level 1'!X53," ",'Level 1'!Z53, " ",'Level 1'!AA53, " ","Insurance: ",'Level 1'!A53) -> Detail: Note Q1 01-00-1900; Q2 Payment Q4 Q5 Additional Notes: Insurance: Delta Dental Of Wisconsin | C53: ='Level 1'!Y53 -> Action | D53: =VLOOKUP(C53,Table2[#All],3,FALSE) -> What we need from you/Reason | E53: Claim Status
A54: =CONCATENATE("Pt Id:",'Level 1'!E54," ","Pt Name: ",'Level 1'!F54," ","DOS: ", TEXT('Level 1'!H54,"mm-dd-yyyy")," "," Amnt: ","$",'Level 1'!J54," ", 'Level 1'!N54) -> Pt Id:8966 Pt Name: Casarez , Romeo DOS: 03-02-2022 Amnt: $1183.2 Note | B54: =CONCATENATE("Detail: ",'Level 1'!N54," ",'Level 1'!O54,TEXT('Level 1'!P54," mm-dd-yyyy"),";"," ",'Level 1'!Q54,'Level 1'!R54," ",'Level 1'!T54," ","Payment "," ",'Level 1'!U54," ",'Level 1'!V54," ",'Level 1'!W54," ",'Level 1'!X54," ",'Level 1'!Z54, " ",'Level 1'!AA54, " ","Insurance: ",'Level 1'!A54) -> Detail: Note Q1 01-00-1900; Q2 Payment Q4 Q5 Additional Notes: Insurance: Delta Dental Of Wisconsin | C54: ='Level 1'!Y54 -> Action | D54: =VLOOKUP(C54,Table2[#All],3,FALSE) -> What we need from you/Reason | E54: Claim Status
A55: =CONCATENATE("Pt Id:",'Level 1'!E55," ","Pt Name: ",'Level 1'!F55," ","DOS: ", TEXT('Level 1'!H55,"mm-dd-yyyy")," "," Amnt: ","$",'Level 1'!J55," ", 'Level 1'!N55) -> Pt Id:9079 Pt Name: Anadell, Carrie DOS: 02-15-2022 Amnt: $220.4 Note | B55: =CONCATENATE("Detail: ",'Level 1'!N55," ",'Level 1'!O55,TEXT('Level 1'!P55," mm-dd-yyyy"),";"," ",'Level 1'!Q55,'Level 1'!R55," ",'Level 1'!T55," ","Payment "," ",'Level 1'!U55," ",'Level 1'!V55," ",'Level 1'!W55," ",'Level 1'!X55," ",'Level 1'!Z55, " ",'Level 1'!AA55, " ","Insurance: ",'Level 1'!A55) -> Detail: Note Q1 01-00-1900; Q2 Payment Q4 Q5 Additional Notes: Insurance: Delta Dental Of Wisconsin | C55: ='Level 1'!Y55 -> Action | D55: =VLOOKUP(C55,Table2[#All],3,FALSE) -> What we need from you/Reason | E55: Claim Status
A56: =CONCATENATE("Pt Id:",'Level 1'!E56," ","Pt Name: ",'Level 1'!F56," ","DOS: ", TEXT('Level 1'!H56,"mm-dd-yyyy")," "," Amnt: ","$",'Level 1'!J56," ", 'Level 1'!N56) -> Pt Id:4735 Pt Name: Wooden, Jasmine DOS: 01-26-2022 Amnt: $432 Claim Paid by EFT; | B56: =CONCATENATE("Detail: ",'Level 1'!N56," ",'Level 1'!O56,TEXT('Level 1'!P56," mm-dd-yyyy"),";"," ",'Level 1'!Q56,'Level 1'!R56," ",'Level 1'!T56," ","Payment "," ",'Level 1'!U56," ",'Level 1'!V56," ",'Level 1'!W56," ",'Level 1'!X56," ",'Level 1'!Z56, " ",'Level 1'!AA56, " ","Insurance: ",'Level 1'!A56) -> Detail: Claim Paid by EFT; Issue Date: 05-04-2022; EFT#"1088874 Bulk Payment Call Ref#: Char05062022 Cust Rep: Char Additional Notes: Rep State that Claim Paid,Paid Amt: $232,Patient Resp: $106,Paid by Direct Deposit,Rep Also State that Elisha from Dental office Called on 04/25/2022 and said to Changed the Date to 01/25/2022 for Tretment and Insurance Denied for 01/26/2022 as Duplicate and Paid for 01/25/2022 Insurance: Delta Dental Of Wisconsin | C56: ='Level 1'!Y56 -> Task Post Pmt Queue | D56: =VLOOKUP(C56,Table2[#All],3,FALSE) -> N/A | E56: Claim Resolved | F56: SN
A57: =CONCATENATE("Pt Id:",'Level 1'!E57," ","Pt Name: ",'Level 1'!F57," ","DOS: ", TEXT('Level 1'!H57,"mm-dd-yyyy")," "," Amnt: ","$",'Level 1'!J57," ", 'Level 1'!N57) -> Pt Id:6339 Pt Name: Malone , Kalahni DOS: 09-18-2021 Amnt: $227.6 Procedure is not a covered benefit; | B57: =CONCATENATE("Detail: ",'Level 1'!N57," ",'Level 1'!O57,TEXT('Level 1'!P57," mm-dd-yyyy"),";"," ",'Level 1'!Q57,'Level 1'!R57," ",'Level 1'!T57," ","Payment "," ",'Level 1'!U57," ",'Level 1'!V57," ",'Level 1'!W57," ",'Level 1'!X57," ",'Level 1'!Z57, " ",'Level 1'!AA57, " ","Insurance: ",'Level 1'!A57) -> Detail: Procedure is not a covered benefit; Why? Not covered under pt plan; Call Ref#:Can can 3/18/2022 Payment 0 0 Additional Notes: Rep states that clm #2129240113, clm has been denied due to not covered under patient plan & COB. Insurance: Delta Dental Of Wisconsin | C57: ='Level 1'!Y57 -> Task Client - Denied Claim Queue | D57: =VLOOKUP(C57,Table2[#All],3,FALSE) -> What We Need From You: Pls confirm if we can close the claims Reason: To close claim | E57: INSB NV Team Task | F57: SN
A58: =CONCATENATE("Pt Id:",'Level 1'!E58," ","Pt Name: ",'Level 1'!F58," ","DOS: ", TEXT('Level 1'!H58,"mm-dd-yyyy")," "," Amnt: ","$",'Level 1'!J58," ", 'Level 1'!N58) -> Pt Id:8250 Pt Name: Sesham Haribabu, Saigopal DOS: 10-26-2021 Amnt: $332.4 Claim not on file. Patient is active ; | B58: =CONCATENATE("Detail: ",'Level 1'!N58," ",'Level 1'!O58,TEXT('Level 1'!P58," mm-dd-yyyy"),";"," ",'Level 1'!Q58,'Level 1'!R58," ",'Level 1'!T58," ","Payment "," ",'Level 1'!U58," ",'Level 1'!V58," ",'Level 1'!W58," ",'Level 1'!X58," ",'Level 1'!Z58, " ",'Level 1'!AA58, " ","Insurance: ",'Level 1'!A58) -> Detail: Claim not on file. Patient is active ; Payor ID & Address: 12-18-2006; Fax # (If Fax Yes): 15 month from dos Payment Call Ref#: can 3/18/2022 Cust Rep: Can Additional Notes: Claim Resubmitted electronically on 05/06/2022 - SN // Rep states that the clm is not on file for the Dos, pat is active from 8/1/2021, we can submitt claim trough electronically or by mailing add P.O box 828, Stevens Point, WI 54481. Insurance: Delta Dental Of Wisconsin | C58: ='Level 1'!Y58 -> Task Sub Pending Claims Queue | D58: =VLOOKUP(C58,Table2[#All],3,FALSE) -> N/A | E58: Review in next report | F58: SN/NE | G58: Claim Resubmitted electronically on 05/06/2022
A59: =CONCATENATE("Pt Id:",'Level 1'!E59," ","Pt Name: ",'Level 1'!F59," ","DOS: ", TEXT('Level 1'!H59,"mm-dd-yyyy")," "," Amnt: ","$",'Level 1'!J59," ", 'Level 1'!N59) -> Pt Id:6339 Pt Name: Malone , Kalahni DOS: 12-06-2021 Amnt: $712 Note | B59: =CONCATENATE("Detail: ",'Level 1'!N59," ",'Level 1'!O59,TEXT('Level 1'!P59," mm-dd-yyyy"),";"," ",'Level 1'!Q59,'Level 1'!R59," ",'Level 1'!T59," ","Payment "," ",'Level 1'!U59," ",'Level 1'!V59," ",'Level 1'!W59," ",'Level 1'!X59," ",'Level 1'!Z59, " ",'Level 1'!AA59, " ","Insurance: ",'Level 1'!A59) -> Detail: Note Q1 01-00-1900; Q2 Payment Q4 Q5 Additional Notes: Insurance: Delta Dental Of Wisconsin | C59: ='Level 1'!Y59 -> Action | D59: =VLOOKUP(C59,Table2[#All],3,FALSE) -> What we need from you/Reason | E59: Claim Status
A60: =CONCATENATE("Pt Id:",'Level 1'!E60," ","Pt Name: ",'Level 1'!F60," ","DOS: ", TEXT('Level 1'!H60,"mm-dd-yyyy")," "," Amnt: ","$",'Level 1'!J60," ", 'Level 1'!N60) -> Pt Id:8537 Pt Name: Gordon, Jamie DOS: 11-24-2021 Amnt: $199.2 Claim Paid by EFT; | B60: =CONCATENATE("Detail: ",'Level 1'!N60," ",'Level 1'!O60,TEXT('Level 1'!P60," mm-dd-yyyy"),";"," ",'Level 1'!Q60,'Level 1'!R60," ",'Level 1'!T60," ","Payment "," ",'Level 1'!U60," ",'Level 1'!V60," ",'Level 1'!W60," ",'Level 1'!X60," ",'Level 1'!Z60, " ",'Level 1'!AA60, " ","Insurance: ",'Level 1'!A60) -> Detail: Claim Paid by EFT; Issue Date: 12-08-2021; EFT#1050566 Bulk Payment Call Ref#: Lisa 3/8/2022 Cust Rep: Lisa Additional Notes: Rep states that clm #2-1336-398-73, paid amt $145.20, It’s a direct deposit, 2codes on the claim has been paid, Bulk amt $1,883.50. Insurance: Delta Dental Of Wisconsin | C60: ='Level 1'!Y60 -> Task Post Pmt Queue | D60: =VLOOKUP(C60,Table2[#All],3,FALSE) -> N/A | E60: INSB NV Team Task | F60: SN
A61: =CONCATENATE("Pt Id:",'Level 1'!E61," ","Pt Name: ",'Level 1'!F61," ","DOS: ", TEXT('Level 1'!H61,"mm-dd-yyyy")," "," Amnt: ","$",'Level 1'!J61," ", 'Level 1'!N61) -> Pt Id:7397 Pt Name: Rubach , Gretchen DOS: 11-19-2021 Amnt: $133.2 Claim Paid by EFT; | B61: =CONCATENATE("Detail: ",'Level 1'!N61," ",'Level 1'!O61,TEXT('Level 1'!P61," mm-dd-yyyy"),";"," ",'Level 1'!Q61,'Level 1'!R61," ",'Level 1'!T61," ","Payment "," ",'Level 1'!U61," ",'Level 1'!V61," ",'Level 1'!W61," ",'Level 1'!X61," ",'Level 1'!Z61, " ",'Level 1'!AA61, " ","Insurance: ",'Level 1'!A61) -> Detail: Claim Paid by EFT; Issue Date: 12-08-2021; EFT#1050566 Bulk Payment Call Ref#: Lisa 3/8/2022 Cust Rep: Lisa Additional Notes: Rep states that clm #2-1336-399-64, paid amt $86.40, It’s a direct deposit, Patient res $21.60, There is one code on the claim which is paid. Insurance: Delta Dental Of Wisconsin | C61: ='Level 1'!Y61 -> Task Post Pmt Queue | D61: =VLOOKUP(C61,Table2[#All],3,FALSE) -> N/A | E61: INSB NV Team Task | F61: SN
A62: =CONCATENATE("Pt Id:",'Level 1'!E62," ","Pt Name: ",'Level 1'!F62," ","DOS: ", TEXT('Level 1'!H62,"mm-dd-yyyy")," "," Amnt: ","$",'Level 1'!J62," ", 'Level 1'!N62) -> Pt Id:8419 Pt Name: Ramirez , Jazmin DOS: 11-11-2021 Amnt: $61.2 Primary Ins paid Max allowable; | B62: =CONCATENATE("Detail: ",'Level 1'!N62," ",'Level 1'!O62,TEXT('Level 1'!P62," mm-dd-yyyy"),";"," ",'Level 1'!Q62,'Level 1'!R62," ",'Level 1'!T62," ","Payment "," ",'Level 1'!U62," ",'Level 1'!V62," ",'Level 1'!W62," ",'Level 1'!X62," ",'Level 1'!Z62, " ",'Level 1'!AA62, " ","Insurance: ",'Level 1'!A62) -> Detail: Primary Ins paid Max allowable; Call Ref#:Cat 3/9/2022; Cust Rep:Cat Payment 0 0 Additional Notes: Coordination of Benefits Insurance: Delta Dental Of Wisconsin | C62: ='Level 1'!Y62 -> Task Post Pmt Queue | D62: =VLOOKUP(C62,Table2[#All],3,FALSE) -> N/A | E62: Claim Resolved | F62: SN/NE | G62: Claim Resolved on 05/06/2022
A63: =CONCATENATE("Pt Id:",'Level 1'!E63," ","Pt Name: ",'Level 1'!F63," ","DOS: ", TEXT('Level 1'!H63,"mm-dd-yyyy")," "," Amnt: ","$",'Level 1'!J63," ", 'Level 1'!N63) -> Pt Id:7216 Pt Name: Pedersen, Arianna DOS: 09-16-2021 Amnt: $342 Claim Paid by Check; | B63: =CONCATENATE("Detail: ",'Level 1'!N63," ",'Level 1'!O63,TEXT('Level 1'!P63," mm-dd-yyyy"),";"," ",'Level 1'!Q63,'Level 1'!R63," ",'Level 1'!T63," ","Payment "," ",'Level 1'!U63," ",'Level 1'!V63," ",'Level 1'!W63," ",'Level 1'!X63," ",'Level 1'!Z63, " ",'Level 1'!AA63, " ","Insurance: ",'Level 1'!A63) -> Detail: Claim Paid by Check; Issue Date: 03-16-2022; CHK#1656809 Sep Payment Call Ref#: Cust Rep: Additional Notes: Rep states confirm that the doctor is not an in-network so the payment made to subscriber, we need to call to the subscriber for the cashed date. Rep Crista, id #crista 4/5/2022.///CHECK WHY IT WAS SENT TO SUBSCRIBER AND CASHED DATE ? // CLM # 2206930006; Pd Amt $227; Paid to Subscriber. Insurance: Delta Dental Of Wisconsin | C63: ='Level 1'!Y63 -> Task Cashed Chk Queue | D63: =VLOOKUP(C63,Table2[#All],3,FALSE) -> What We Need From You: Please confirm Check was received. Reason: To close claim. | E63: Claim Status
A64: =CONCATENATE("Pt Id:",'Level 1'!E64," ","Pt Name: ",'Level 1'!F64," ","DOS: ", TEXT('Level 1'!H64,"mm-dd-yyyy")," "," Amnt: ","$",'Level 1'!J64," ", 'Level 1'!N64) -> Pt Id:6340 Pt Name: Malone , Kaleyah DOS: 09-18-2021 Amnt: $138 Claim Paid by Check; | B64: =CONCATENATE("Detail: ",'Level 1'!N64," ",'Level 1'!O64,TEXT('Level 1'!P64," mm-dd-yyyy"),";"," ",'Level 1'!Q64,'Level 1'!R64," ",'Level 1'!T64," ","Payment "," ",'Level 1'!U64," ",'Level 1'!V64," ",'Level 1'!W64," ",'Level 1'!X64," ",'Level 1'!Z64, " ",'Level 1'!AA64, " ","Insurance: ",'Level 1'!A64) -> Detail: Claim Paid by Check; Issue Date: 09-29-2021; CHK#1008274 Single Payment Call Ref#: Lisa 3/8/2022 Cust Rep: Lisa Additional Notes: Rep states that clm #2126547242, paid amt $80, it’s a direct deposit, D1208 - Denied due to Age Limitataion. Insurance: Delta Dental Of Wisconsin | C64: ='Level 1'!Y64 -> Task Cashed Chk Queue | D64: =VLOOKUP(C64,Table2[#All],3,FALSE) -> What We Need From You: Please confirm Check was received. Reason: To close claim. | E64: INSB NV Team Task | F64: SN
A65: =CONCATENATE("Pt Id:",'Level 1'!E65," ","Pt Name: ",'Level 1'!F65," ","DOS: ", TEXT('Level 1'!H65,"mm-dd-yyyy")," "," Amnt: ","$",'Level 1'!J65," ", 'Level 1'!N65) -> Pt Id:7729 Pt Name: Vanderwielen, Brenda DOS: 08-11-2021 Amnt: $61.2 Claim Paid by EFT; | B65: =CONCATENATE("Detail: ",'Level 1'!N65," ",'Level 1'!O65,TEXT('Level 1'!P65," mm-dd-yyyy"),";"," ",'Level 1'!Q65,'Level 1'!R65," ",'Level 1'!T65," ","Payment "," ",'Level 1'!U65," ",'Level 1'!V65," ",'Level 1'!W65," ",'Level 1'!X65," ",'Level 1'!Z65, " ",'Level 1'!AA65, " ","Insurance: ",'Level 1'!A65) -> Detail: Claim Paid by EFT; Issue Date: 08-25-2021; EFT#988435 Bulk Payment Call Ref#: Ami01272022 Cust Rep: Ami Additional Notes: Rep State that Claim Paid,Paid Amt:$23, Claim No: 2-1229-385-28, Paid by Bulk(Bulk Amt:$2446.60), Patient Resp:$25 Insurance: Delta Dental Of Wisconsin | C65: ='Level 1'!Y65 -> Task Post Pmt Queue | D65: =VLOOKUP(C65,Table2[#All],3,FALSE) -> N/A | E65: INSB NV Team Task | F65: SN
A66: =CONCATENATE("Pt Id:",'Level 1'!E66," ","Pt Name: ",'Level 1'!F66," ","DOS: ", TEXT('Level 1'!H66,"mm-dd-yyyy")," "," Amnt: ","$",'Level 1'!J66," ", 'Level 1'!N66) -> Pt Id:4691 Pt Name: Sanchez Esquive , Israel DOS: 07-31-2021 Amnt: $2750.4 Patient not active/no active policy; | B66: =CONCATENATE("Detail: ",'Level 1'!N66," ",'Level 1'!O66,TEXT('Level 1'!P66," mm-dd-yyyy"),";"," ",'Level 1'!Q66,'Level 1'!R66," ",'Level 1'!T66," ","Payment "," ",'Level 1'!U66," ",'Level 1'!V66," ",'Level 1'!W66," ",'Level 1'!X66," ",'Level 1'!Z66, " ",'Level 1'!AA66, " ","Insurance: ",'Level 1'!A66) -> Detail: Patient not active/no active policy; Policy Term Dt: 04-30-2021; Call Ref#:Amalia01272022 Amalia Payment 0 0 Additional Notes: Rep State that CNOF Patient Inactive, Effective Date:03/01/2018, Last Active Date:04/30/2021 Insurance: Delta Dental Of Wisconsin | C66: ='Level 1'!Y66 -> Task Denied Claims Queue | D66: =VLOOKUP(C66,Table2[#All],3,FALSE) -> What We Need From You: Reason: | E66: Claim Status
A67: =CONCATENATE("Pt Id:",'Level 1'!E67," ","Pt Name: ",'Level 1'!F67," ","DOS: ", TEXT('Level 1'!H67,"mm-dd-yyyy")," "," Amnt: ","$",'Level 1'!J67," ", 'Level 1'!N67) -> Pt Id:5011 Pt Name: Kyles , Amari DOS: 03-22-2021 Amnt: $869.2 Claim Paid by EFT; | B67: =CONCATENATE("Detail: ",'Level 1'!N67," ",'Level 1'!O67,TEXT('Level 1'!P67," mm-dd-yyyy"),";"," ",'Level 1'!Q67,'Level 1'!R67," ",'Level 1'!T67," ","Payment "," ",'Level 1'!U67," ",'Level 1'!V67," ",'Level 1'!W67," ",'Level 1'!X67," ",'Level 1'!Z67, " ",'Level 1'!AA67, " ","Insurance: ",'Level 1'!A67) -> Detail: Claim Paid by EFT; Issue Date: 04-07-2021; EFT#907363 Bulk Payment Call Ref#: Lisa 3/8/2022 Cust Rep: LISA Additional Notes: Rep states that clm #2-1090-396-68, paid amt $479.80, PR amt $232.20, cashed dt 4/7/2021, it’s a bulk amt $1,640.80, there are 13 codes on the claim in which 2 codes D1208 and the reason for the age limitation. D9230 is denied for not covered benefits for the dental plan. Insurance: Delta Dental Of Wisconsin | C67: ='Level 1'!Y67 -> Task Post Pmt Queue | D67: =VLOOKUP(C67,Table2[#All],3,FALSE) -> N/A | E67: INSB NV Team Task | F67: SN
A68: =CONCATENATE("Pt Id:",'Level 1'!E68," ","Pt Name: ",'Level 1'!F68," ","DOS: ", TEXT('Level 1'!H68,"mm-dd-yyyy")," "," Amnt: ","$",'Level 1'!J68," ", 'Level 1'!N68) -> Pt Id:5311 Pt Name: Franke , Ryan DOS: 10-23-2020 Amnt: $4439.6 Claim Paid by EFT; | B68: =CONCATENATE("Detail: ",'Level 1'!N68," ",'Level 1'!O68,TEXT('Level 1'!P68," mm-dd-yyyy"),";"," ",'Level 1'!Q68,'Level 1'!R68," ",'Level 1'!T68," ","Payment "," ",'Level 1'!U68," ",'Level 1'!V68," ",'Level 1'!W68," ",'Level 1'!X68," ",'Level 1'!Z68, " ",'Level 1'!AA68, " ","Insurance: ",'Level 1'!A68) -> Detail: Claim Paid by EFT; Issue Date: 10-27-2020; EFT#825000 Sep Payment Call Ref#: Amalia01272022 Cust Rep: Amalia Additional Notes: Rep State that Claim Paid,Paid Amt:$1147, Claim No: 2030139640, Patient Resp:$25($25 Deductable). DOS:12/14/2020 - D3310 & D2954 are denied Maxed out. DOS: 12/19/2020 - D4341 - LR - Paid AMT $23 & D4341 - UR - Maxed out. DOS: 12/22/2022 - D2750, D4341 (UL & LL) - Denied Maxed out. Insurance: Delta Dental Of Wisconsin | C68: ='Level 1'!Y68 -> Task Post Pmt Queue | D68: =VLOOKUP(C68,Table2[#All],3,FALSE) -> N/A | E68: INSB NV Team Task | F68: SN
A69: =CONCATENATE("Pt Id:",'Level 1'!E69," ","Pt Name: ",'Level 1'!F69," ","DOS: ", TEXT('Level 1'!H69,"mm-dd-yyyy")," "," Amnt: ","$",'Level 1'!J69," ", 'Level 1'!N69) -> Pt Id:1695 Pt Name: BLANTON, LOUISE DOS: 03-19-2021 Amnt: $1495.2 Patient not active/no active policy; | B69: =CONCATENATE("Detail: ",'Level 1'!N69," ",'Level 1'!O69,TEXT('Level 1'!P69," mm-dd-yyyy"),";"," ",'Level 1'!Q69,'Level 1'!R69," ",'Level 1'!T69," ","Payment "," ",'Level 1'!U69," ",'Level 1'!V69," ",'Level 1'!W69," ",'Level 1'!X69," ",'Level 1'!Z69, " ",'Level 1'!AA69, " ","Insurance: ",'Level 1'!A69) -> Detail: Patient not active/no active policy; Policy Term Dt: 02-28-2022; Call Ref#:Jerrone 3/8/2022 Jerrone Payment 0 0 Additional Notes: Patient not active for DOS. Patient has Molina Ins as Sec Ins, need to submit claim to Molina for processing. Insurance: Delta Dental Wisconsin Individual plan | C69: ='Level 1'!Y69 -> Task Denied Claims Queue | D69: =VLOOKUP(C69,Table2[#All],3,FALSE) -> What We Need From You: Reason: | E69: INSB NV Team Task | F69: SN
A70: =CONCATENATE("Pt Id:",'Level 1'!E70," ","Pt Name: ",'Level 1'!F70," ","DOS: ", TEXT('Level 1'!H70,"mm-dd-yyyy")," "," Amnt: ","$",'Level 1'!J70," ", 'Level 1'!N70) -> Pt Id:6130 Pt Name: Liggett, Carrie DOS: 08-20-2021 Amnt: $339.6 Note | B70: =CONCATENATE("Detail: ",'Level 1'!N70," ",'Level 1'!O70,TEXT('Level 1'!P70," mm-dd-yyyy"),";"," ",'Level 1'!Q70,'Level 1'!R70," ",'Level 1'!T70," ","Payment "," ",'Level 1'!U70," ",'Level 1'!V70," ",'Level 1'!W70," ",'Level 1'!X70," ",'Level 1'!Z70, " ",'Level 1'!AA70, " ","Insurance: ",'Level 1'!A70) -> Detail: Note Q1 01-00-1900; Q2 Payment Q4 Q5 Additional Notes: Insurance: Denta Trust | C70: ='Level 1'!Y70 -> Action | D70: =VLOOKUP(C70,Table2[#All],3,FALSE) -> What we need from you/Reason | E70: Claim Status
A71: =CONCATENATE("Pt Id:",'Level 1'!E71," ","Pt Name: ",'Level 1'!F71," ","DOS: ", TEXT('Level 1'!H71,"mm-dd-yyyy")," "," Amnt: ","$",'Level 1'!J71," ", 'Level 1'!N71) -> Pt Id:8678 Pt Name: Rivera , Reyes DOS: 12-16-2021 Amnt: $372.8 Write information in Addl Notes | B71: =CONCATENATE("Detail: ",'Level 1'!N71," ",'Level 1'!O71,TEXT('Level 1'!P71," mm-dd-yyyy"),";"," ",'Level 1'!Q71,'Level 1'!R71," ",'Level 1'!T71," ","Payment "," ",'Level 1'!U71," ",'Level 1'!V71," ",'Level 1'!W71," ",'Level 1'!X71," ",'Level 1'!Z71, " ",'Level 1'!AA71, " ","Insurance: ",'Level 1'!A71) -> #VALUE! | C71: ='Level 1'!Y71 -> Team Lead to review & Follow-Up | D71: =VLOOKUP(C71,Table2[#All],3,FALSE) -> #N/A | E71: INSB NV Team Task | F71: SN
A72: =CONCATENATE("Pt Id:",'Level 1'!E72," ","Pt Name: ",'Level 1'!F72," ","DOS: ", TEXT('Level 1'!H72,"mm-dd-yyyy")," "," Amnt: ","$",'Level 1'!J72," ", 'Level 1'!N72) -> Pt Id:8437 Pt Name: Washington , Valencia DOS: 11-12-2021 Amnt: $525.6 Claim Paid by EFT; | B72: =CONCATENATE("Detail: ",'Level 1'!N72," ",'Level 1'!O72,TEXT('Level 1'!P72," mm-dd-yyyy"),";"," ",'Level 1'!Q72,'Level 1'!R72," ",'Level 1'!T72," ","Payment "," ",'Level 1'!U72," ",'Level 1'!V72," ",'Level 1'!W72," ",'Level 1'!X72," ",'Level 1'!Z72, " ",'Level 1'!AA72, " ","Insurance: ",'Level 1'!A72) -> Detail: Claim Paid by EFT; Issue Date: 11-26-2021; EFT#5877982047 Sep Payment Call Ref#: 20220101760 Cust Rep: Casey Additional Notes: D7210 - Dnd for waiting period (1 yr) and waiting period was going to be end on 12/31/2021. Now patient is Inactive and $420 is patient's resp for this claim. Code D0220 was bundled with D0274. - 02/28/2022 - SN. // Need Waiting Period for D7210 and bundled Code for D0220 as this procedure is dnd stating bundled as FMX but there is no FMX code paid clm# 202132338791800, Paid $ 80.73. D0220 dnd as Service has been bundled with other procedure lines to a more cost effective full mouth series - Need to check for which is this code bundled with and D7210 is dnd due to waiting period for this benefit has not been met - Need to check what is the waiting period for this procedure. Insurance: Denta Trust | C72: ='Level 1'!Y72 -> Task Post Pmt Queue | D72: =VLOOKUP(C72,Table2[#All],3,FALSE) -> N/A | E72: INSB NV Team Task | F72: SN
A73: =CONCATENATE("Pt Id:",'Level 1'!E73," ","Pt Name: ",'Level 1'!F73," ","DOS: ", TEXT('Level 1'!H73,"mm-dd-yyyy")," "," Amnt: ","$",'Level 1'!J73," ", 'Level 1'!N73) -> Pt Id:7808 Pt Name: Arries, Daniel DOS: 08-24-2021 Amnt: $216 Claim Paid by EFT; | B73: =CONCATENATE("Detail: ",'Level 1'!N73," ",'Level 1'!O73,TEXT('Level 1'!P73," mm-dd-yyyy"),";"," ",'Level 1'!Q73,'Level 1'!R73," ",'Level 1'!T73," ","Payment "," ",'Level 1'!U73," ",'Level 1'!V73," ",'Level 1'!W73," ",'Level 1'!X73," ",'Level 1'!Z73, " ",'Level 1'!AA73, " ","Insurance: ",'Level 1'!A73) -> Detail: Claim Paid by EFT; Issue Date: 09-03-2021; EFT#5877908417 SEP Payment Call Ref#: 202200318022 Cust Rep: Ander Additional Notes: Rep States that Claim Paid,Claim NO: 202124238888600, Paid AMT:$80.73,Patient Resp: $135.27 Insurance: Denta Trust | C73: ='Level 1'!Y73 -> Task Post Pmt Queue | D73: =VLOOKUP(C73,Table2[#All],3,FALSE) -> N/A | E73: INSB NV Team Task | F73: SN
A74: =CONCATENATE("Pt Id:",'Level 1'!E74," ","Pt Name: ",'Level 1'!F74," ","DOS: ", TEXT('Level 1'!H74,"mm-dd-yyyy")," "," Amnt: ","$",'Level 1'!J74," ", 'Level 1'!N74) -> Pt Id:7899 Pt Name: Luttrell, Melanie DOS: 09-10-2021 Amnt: $178.4 Claim Paid by EFT; | B74: =CONCATENATE("Detail: ",'Level 1'!N74," ",'Level 1'!O74,TEXT('Level 1'!P74," mm-dd-yyyy"),";"," ",'Level 1'!Q74,'Level 1'!R74," ",'Level 1'!T74," ","Payment "," ",'Level 1'!U74," ",'Level 1'!V74," ",'Level 1'!W74," ",'Level 1'!X74," ",'Level 1'!Z74, " ",'Level 1'!AA74, " ","Insurance: ",'Level 1'!A74) -> Detail: Claim Paid by EFT; Issue Date: 09-24-2021; EFT#5877926593 SEP Payment Call Ref#: 202200318169 Cust Rep: Ander Additional Notes: Rep States that Claim Paid,Claim NO: 202125839780100, Paid AMT:$53.65. Insurance: Denta Trust | C74: ='Level 1'!Y74 -> Task Post Pmt Queue | D74: =VLOOKUP(C74,Table2[#All],3,FALSE) -> N/A | E74: INSB NV Team Task | F74: SN
A75: =CONCATENATE("Pt Id:",'Level 1'!E75," ","Pt Name: ",'Level 1'!F75," ","DOS: ", TEXT('Level 1'!H75,"mm-dd-yyyy")," "," Amnt: ","$",'Level 1'!J75," ", 'Level 1'!N75) -> Pt Id:7782 Pt Name: Goffe, Dennis DOS: 08-25-2021 Amnt: $505.2 Claim Paid by EFT; | B75: =CONCATENATE("Detail: ",'Level 1'!N75," ",'Level 1'!O75,TEXT('Level 1'!P75," mm-dd-yyyy"),";"," ",'Level 1'!Q75,'Level 1'!R75," ",'Level 1'!T75," ","Payment "," ",'Level 1'!U75," ",'Level 1'!V75," ",'Level 1'!W75," ",'Level 1'!X75," ",'Level 1'!Z75, " ",'Level 1'!AA75, " ","Insurance: ",'Level 1'!A75) -> Detail: Claim Paid by EFT; Issue Date: 09-08-2021; EFT#5877908417 SEP Payment Call Ref#: 202200318449 Cust Rep: Emily Additional Notes: Rep States that Claim Paid,Claim NO: 202124238867800, Paid AMT:$105.04 Insurance: Denta Trust | C75: ='Level 1'!Y75 -> Task Post Pmt Queue | D75: =VLOOKUP(C75,Table2[#All],3,FALSE) -> N/A | E75: INSB NV Team Task | F75: SN
A76: =CONCATENATE("Pt Id:",'Level 1'!E76," ","Pt Name: ",'Level 1'!F76," ","DOS: ", TEXT('Level 1'!H76,"mm-dd-yyyy")," "," Amnt: ","$",'Level 1'!J76," ", 'Level 1'!N76) -> Pt Id:7024 Pt Name: Prasser , Stephanie DOS: 05-06-2021 Amnt: $583.2 Procedure is not a covered benefit; | B76: =CONCATENATE("Detail: ",'Level 1'!N76," ",'Level 1'!O76,TEXT('Level 1'!P76," mm-dd-yyyy"),";"," ",'Level 1'!Q76,'Level 1'!R76," ",'Level 1'!T76," ","Payment "," ",'Level 1'!U76," ",'Level 1'!V76," ",'Level 1'!W76," ",'Level 1'!X76," ",'Level 1'!Z76, " ",'Level 1'!AA76, " ","Insurance: ",'Level 1'!A76) -> Detail: Procedure is not a covered benefit; Why? Not covered under pt plan; Call Ref#:202200318509 Emily Payment 0 0 Additional Notes: D2393 - Denied waiting period Issue & D1208 - Denied benefit not covered under pt plan. Payment posting already done. Need to close the claim. Insurance: Denta Trust | C76: ='Level 1'!Y76 -> Task Client - Denied Claim Queue | D76: =VLOOKUP(C76,Table2[#All],3,FALSE) -> What We Need From You: Pls confirm if we can close the claims Reason: To close claim | E76: INSB NV Team Task | F76: SN
A77: =CONCATENATE("Pt Id:",'Level 1'!E77," ","Pt Name: ",'Level 1'!F77," ","DOS: ", TEXT('Level 1'!H77,"mm-dd-yyyy")," "," Amnt: ","$",'Level 1'!J77," ", 'Level 1'!N77) -> Pt Id:2431 Pt Name: Rice, Matthew DOS: 04-01-2022 Amnt: $501.6 Note | B77: =CONCATENATE("Detail: ",'Level 1'!N77," ",'Level 1'!O77,TEXT('Level 1'!#REF!," mm-dd-yyyy"),";"," ",'Level 1'!Q77,'Level 1'!R77," ",'Level 1'!T77," ","Payment "," ",'Level 1'!U77," ",'Level 1'!V77," ",'Level 1'!W77," ",'Level 1'!X77," ",'Level 1'!Z77, " ",'Level 1'!AA77, " ","Insurance: ",'Level 1'!A77) -> #REF! | C77: ='Level 1'!Y77 -> Action | D77: =VLOOKUP(C77,Table2[#All],3,FALSE) -> What we need from you/Reason | E77: Claim Status
A78: =CONCATENATE("Pt Id:",'Level 1'!E78," ","Pt Name: ",'Level 1'!F78," ","DOS: ", TEXT('Level 1'!H78,"mm-dd-yyyy")," "," Amnt: ","$",'Level 1'!J78," ", 'Level 1'!N78) -> Pt Id:2432 Pt Name: Rice, Quiana DOS: 04-01-2022 Amnt: $669.6 Note | B78: =CONCATENATE("Detail: ",'Level 1'!N78," ",'Level 1'!O78,TEXT('Level 1'!P77," mm-dd-yyyy"),";"," ",'Level 1'!Q78,'Level 1'!R78," ",'Level 1'!T78," ","Payment "," ",'Level 1'!U78," ",'Level 1'!V78," ",'Level 1'!W78," ",'Level 1'!X78," ",'Level 1'!Z78, " ",'Level 1'!AA78, " ","Insurance: ",'Level 1'!A78) -> Detail: Note Q1 01-00-1900; Q2 Payment Q4 Q5 Additional Notes: Insurance: Dental Health and Wellness WI | C78: ='Level 1'!Y78 -> Action | D78: =VLOOKUP(C78,Table2[#All],3,FALSE) -> What we need from you/Reason | E78: Claim Status
A79: =CONCATENATE("Pt Id:",'Level 1'!E79," ","Pt Name: ",'Level 1'!F79," ","DOS: ", TEXT('Level 1'!H79,"mm-dd-yyyy")," "," Amnt: ","$",'Level 1'!J79," ", 'Level 1'!N79) -> Pt Id:3084 Pt Name: Mcneal, Gabrielle DOS: 04-01-2022 Amnt: $149.6 Note | B79: =CONCATENATE("Detail: ",'Level 1'!N79," ",'Level 1'!O79,TEXT('Level 1'!P78," mm-dd-yyyy"),";"," ",'Level 1'!Q79,'Level 1'!R79," ",'Level 1'!T79," ","Payment "," ",'Level 1'!U79," ",'Level 1'!V79," ",'Level 1'!W79," ",'Level 1'!X79," ",'Level 1'!Z79, " ",'Level 1'!AA79, " ","Insurance: ",'Level 1'!A79) -> Detail: Note Q1 01-00-1900; Q2 Payment Q4 Q5 Additional Notes: Insurance: Dental Health and Wellness WI | C79: ='Level 1'!Y79 -> Action | D79: =VLOOKUP(C79,Table2[#All],3,FALSE) -> What we need from you/Reason | E79: Claim Status
A80: =CONCATENATE("Pt Id:",'Level 1'!E80," ","Pt Name: ",'Level 1'!F80," ","DOS: ", TEXT('Level 1'!H80,"mm-dd-yyyy")," "," Amnt: ","$",'Level 1'!J80," ", 'Level 1'!N80) -> Pt Id:9219 Pt Name: Veasey, Zayden DOS: 03-29-2022 Amnt: $470 Note | B80: =CONCATENATE("Detail: ",'Level 1'!N80," ",'Level 1'!O80,TEXT('Level 1'!P79," mm-dd-yyyy"),";"," ",'Level 1'!Q80,'Level 1'!R80," ",'Level 1'!T80," ","Payment "," ",'Level 1'!U80," ",'Level 1'!V80," ",'Level 1'!W80," ",'Level 1'!X80," ",'Level 1'!Z80, " ",'Level 1'!AA80, " ","Insurance: ",'Level 1'!A80) -> Detail: Note Q1 01-00-1900; Q2 Payment Q4 Q5 Additional Notes: Insurance: Dental Health and Wellness WI | C80: ='Level 1'!Y80 -> Action | D80: =VLOOKUP(C80,Table2[#All],3,FALSE) -> What we need from you/Reason | E80: Claim Status
A81: =CONCATENATE("Pt Id:",'Level 1'!E81," ","Pt Name: ",'Level 1'!F81," ","DOS: ", TEXT('Level 1'!H81,"mm-dd-yyyy")," "," Amnt: ","$",'Level 1'!J81," ", 'Level 1'!N81) -> Pt Id:2943 Pt Name: Bell , Muhammed DOS: 03-25-2022 Amnt: $61.2 Note | B81: =CONCATENATE("Detail: ",'Level 1'!N81," ",'Level 1'!O81,TEXT('Level 1'!P80," mm-dd-yyyy"),";"," ",'Level 1'!Q81,'Level 1'!R81," ",'Level 1'!T81," ","Payment "," ",'Level 1'!U81," ",'Level 1'!V81," ",'Level 1'!W81," ",'Level 1'!X81," ",'Level 1'!Z81, " ",'Level 1'!AA81, " ","Insurance: ",'Level 1'!A81) -> Detail: Note Q1 01-00-1900; Q2 Payment Q4 Q5 Additional Notes: Insurance: Dental Health and Wellness WI | C81: ='Level 1'!Y81 -> Action | D81: =VLOOKUP(C81,Table2[#All],3,FALSE) -> What we need from you/Reason | E81: Claim Status
A82: =CONCATENATE("Pt Id:",'Level 1'!E82," ","Pt Name: ",'Level 1'!F82," ","DOS: ", TEXT('Level 1'!H82,"mm-dd-yyyy")," "," Amnt: ","$",'Level 1'!J82," ", 'Level 1'!N82) -> Pt Id:9077 Pt Name: Conner, Aaron DOS: 03-25-2022 Amnt: $506.4 Note | B82: =CONCATENATE("Detail: ",'Level 1'!N82," ",'Level 1'!O82,TEXT('Level 1'!P81," mm-dd-yyyy"),";"," ",'Level 1'!Q82,'Level 1'!R82," ",'Level 1'!T82," ","Payment "," ",'Level 1'!U82," ",'Level 1'!V82," ",'Level 1'!W82," ",'Level 1'!X82," ",'Level 1'!Z82, " ",'Level 1'!AA82, " ","Insurance: ",'Level 1'!A82) -> Detail: Note Q1 01-00-1900; Q2 Payment Q4 Q5 Additional Notes: Insurance: Dental Health and Wellness WI | C82: ='Level 1'!Y82 -> Action | D82: =VLOOKUP(C82,Table2[#All],3,FALSE) -> What we need from you/Reason | E82: Claim Status
A83: =CONCATENATE("Pt Id:",'Level 1'!E83," ","Pt Name: ",'Level 1'!F83," ","DOS: ", TEXT('Level 1'!H83,"mm-dd-yyyy")," "," Amnt: ","$",'Level 1'!J83," ", 'Level 1'!N83) -> Pt Id:9302 Pt Name: Brown, Jayce DOS: 03-19-2022 Amnt: $432 Note | B83: =CONCATENATE("Detail: ",'Level 1'!N83," ",'Level 1'!O83,TEXT('Level 1'!P82," mm-dd-yyyy"),";"," ",'Level 1'!Q83,'Level 1'!R83," ",'Level 1'!T83," ","Payment "," ",'Level 1'!U83," ",'Level 1'!V83," ",'Level 1'!W83," ",'Level 1'!X83," ",'Level 1'!Z83, " ",'Level 1'!AA83, " ","Insurance: ",'Level 1'!A83) -> Detail: Note Q1 01-00-1900; Q2 Payment Q4 Q5 Additional Notes: Insurance: Dental Health and Wellness WI | C83: ='Level 1'!Y83 -> Action | D83: =VLOOKUP(C83,Table2[#All],3,FALSE) -> What we need from you/Reason | E83: Claim Status
A84: =CONCATENATE("Pt Id:",'Level 1'!E84," ","Pt Name: ",'Level 1'!F84," ","DOS: ", TEXT('Level 1'!H84,"mm-dd-yyyy")," "," Amnt: ","$",'Level 1'!J84," ", 'Level 1'!N84) -> Pt Id:7851 Pt Name: Beqiri, Malik DOS: 03-23-2022 Amnt: $138 Note | B84: =CONCATENATE("Detail: ",'Level 1'!N84," ",'Level 1'!O84,TEXT('Level 1'!P83," mm-dd-yyyy"),";"," ",'Level 1'!Q84,'Level 1'!R84," ",'Level 1'!T84," ","Payment "," ",'Level 1'!U84," ",'Level 1'!V84," ",'Level 1'!W84," ",'Level 1'!X84," ",'Level 1'!Z84, " ",'Level 1'!AA84, " ","Insurance: ",'Level 1'!A84) -> Detail: Note Q1 01-00-1900; Q2 Payment Q4 Q5 Additional Notes: Insurance: Dental Health and Wellness WI | C84: ='Level 1'!Y84 -> Action | D84: =VLOOKUP(C84,Table2[#All],3,FALSE) -> What we need from you/Reason | E84: Claim Status
A85: =CONCATENATE("Pt Id:",'Level 1'!E85," ","Pt Name: ",'Level 1'!F85," ","DOS: ", TEXT('Level 1'!H85,"mm-dd-yyyy")," "," Amnt: ","$",'Level 1'!J85," ", 'Level 1'!N85) -> Pt Id:9278 Pt Name: Edmonds, Kelly DOS: 03-23-2022 Amnt: $178.4 Note | B85: =CONCATENATE("Detail: ",'Level 1'!N85," ",'Level 1'!O85,TEXT('Level 1'!P84," mm-dd-yyyy"),";"," ",'Level 1'!Q85,'Level 1'!R85," ",'Level 1'!T85," ","Payment "," ",'Level 1'!U85," ",'Level 1'!V85," ",'Level 1'!W85," ",'Level 1'!X85," ",'Level 1'!Z85, " ",'Level 1'!AA85, " ","Insurance: ",'Level 1'!A85) -> Detail: Note Q1 01-00-1900; Q2 Payment Q4 Q5 Additional Notes: Insurance: Dental Health and Wellness WI | C85: ='Level 1'!Y85 -> Action | D85: =VLOOKUP(C85,Table2[#All],3,FALSE) -> What we need from you/Reason | E85: Claim Status
A86: =CONCATENATE("Pt Id:",'Level 1'!E86," ","Pt Name: ",'Level 1'!F86," ","DOS: ", TEXT('Level 1'!H86,"mm-dd-yyyy")," "," Amnt: ","$",'Level 1'!J86," ", 'Level 1'!N86) -> Pt Id:9285 Pt Name: Howard , Jace DOS: 03-23-2022 Amnt: $166.8 Note | B86: =CONCATENATE("Detail: ",'Level 1'!N86," ",'Level 1'!O86,TEXT('Level 1'!P85," mm-dd-yyyy"),";"," ",'Level 1'!Q86,'Level 1'!R86," ",'Level 1'!T86," ","Payment "," ",'Level 1'!U86," ",'Level 1'!V86," ",'Level 1'!W86," ",'Level 1'!X86," ",'Level 1'!Z86, " ",'Level 1'!AA86, " ","Insurance: ",'Level 1'!A86) -> Detail: Note Q1 01-00-1900; Q2 Payment Q4 Q5 Additional Notes: Insurance: Dental Health and Wellness WI | C86: ='Level 1'!Y86 -> Action | D86: =VLOOKUP(C86,Table2[#All],3,FALSE) -> What we need from you/Reason | E86: Claim Status
A87: =CONCATENATE("Pt Id:",'Level 1'!E87," ","Pt Name: ",'Level 1'!F87," ","DOS: ", TEXT('Level 1'!H87,"mm-dd-yyyy")," "," Amnt: ","$",'Level 1'!J87," ", 'Level 1'!N87) -> Pt Id:8696 Pt Name: Hayes , Shequita DOS: 03-22-2022 Amnt: $506.4 Note | B87: =CONCATENATE("Detail: ",'Level 1'!N87," ",'Level 1'!O87,TEXT('Level 1'!P86," mm-dd-yyyy"),";"," ",'Level 1'!Q87,'Level 1'!R87," ",'Level 1'!T87," ","Payment "," ",'Level 1'!U87," ",'Level 1'!V87," ",'Level 1'!W87," ",'Level 1'!X87," ",'Level 1'!Z87, " ",'Level 1'!AA87, " ","Insurance: ",'Level 1'!A87) -> Detail: Note Q1 01-00-1900; Q2 Payment Q4 Q5 Additional Notes: Insurance: Dental Health and Wellness WI | C87: ='Level 1'!Y87 -> Action | D87: =VLOOKUP(C87,Table2[#All],3,FALSE) -> What we need from you/Reason | E87: Claim Status
A88: =CONCATENATE("Pt Id:",'Level 1'!E88," ","Pt Name: ",'Level 1'!F88," ","DOS: ", TEXT('Level 1'!H88,"mm-dd-yyyy")," "," Amnt: ","$",'Level 1'!J88," ", 'Level 1'!N88) -> Pt Id:9053 Pt Name: Baker, Marquis DOS: 03-22-2022 Amnt: $466.8 Note | B88: =CONCATENATE("Detail: ",'Level 1'!N88," ",'Level 1'!O88,TEXT('Level 1'!P87," mm-dd-yyyy"),";"," ",'Level 1'!Q88,'Level 1'!R88," ",'Level 1'!T88," ","Payment "," ",'Level 1'!U88," ",'Level 1'!V88," ",'Level 1'!W88," ",'Level 1'!X88," ",'Level 1'!Z88, " ",'Level 1'!AA88, " ","Insurance: ",'Level 1'!A88) -> Detail: Note Q1 01-00-1900; Q2 Payment Q4 Q5 Additional Notes: Insurance: Dental Health and Wellness WI | C88: ='Level 1'!Y88 -> Action | D88: =VLOOKUP(C88,Table2[#All],3,FALSE) -> What we need from you/Reason | E88: Claim Status
A89: =CONCATENATE("Pt Id:",'Level 1'!E89," ","Pt Name: ",'Level 1'!F89," ","DOS: ", TEXT('Level 1'!H89,"mm-dd-yyyy")," "," Amnt: ","$",'Level 1'!J89," ", 'Level 1'!N89) -> Pt Id:9302 Pt Name: Brown, Jayce DOS: 03-19-2022 Amnt: $273.2 Note | B89: =CONCATENATE("Detail: ",'Level 1'!N89," ",'Level 1'!O89,TEXT('Level 1'!P88," mm-dd-yyyy"),";"," ",'Level 1'!Q89,'Level 1'!R89," ",'Level 1'!T89," ","Payment "," ",'Level 1'!U89," ",'Level 1'!V89," ",'Level 1'!W89," ",'Level 1'!X89," ",'Level 1'!Z89, " ",'Level 1'!AA89, " ","Insurance: ",'Level 1'!A89) -> Detail: Note Q1 01-00-1900; Q2 Payment Q4 Q5 Additional Notes: Insurance: Dental Health and Wellness WI | C89: ='Level 1'!Y89 -> Action | D89: =VLOOKUP(C89,Table2[#All],3,FALSE) -> What we need from you/Reason | E89: Claim Status
... A113: =CONCATENATE("Pt Id:",'Level 1'!E113," ","Pt Name: ",'Level 1'!F113," ","DOS: ", TEXT('Level 1'!H113,"mm-dd-yyyy")," "," Amnt: ","$",'Level 1'!J113," ", 'Level 1'!N113) -> Pt Id:9055 Pt Name: Baker, Mariah DOS: 02-11-2022 Amnt: $273.2 Note | B113: =CONCATENATE("Detail: ",'Level 1'!N113," ",'Level 1'!O113,TEXT('Level 1'!P112," mm-dd-yyyy"),";"," ",'Level 1'!Q113,'Level 1'!R113," ",'Level 1'!T113," ","Payment "," ",'Level 1'!U113," ",'Level 1'!V113," ",'Level 1'!W113," ",'Level 1'!X113," ",'Level 1'!Z113, " ",'Level 1'!AA113, " ","Insurance: ",'Level 1'!A113) -> Detail: Note Q1 01-00-1900; Q2 Payment Q4 Q5 Additional Notes: Insurance: Dental Health and Wellness WI | C113: ='Level 1'!Y113 -> Action | D113: =VLOOKUP(C113,Table2[#All],3,FALSE) -> What we need from you/Reason | E113: Claim Status
A114: =CONCATENATE("Pt Id:",'Level 1'!E114," ","Pt Name: ",'Level 1'!F114," ","DOS: ", TEXT('Level 1'!H114,"mm-dd-yyyy")," "," Amnt: ","$",'Level 1'!J114," ", 'Level 1'!N114) -> Pt Id:6261 Pt Name: Cervantes, Giselle DOS: 02-08-2022 Amnt: $227.6 Ins needs more info, need to submit; | B114: =CONCATENATE("Detail: ",'Level 1'!N114," ",'Level 1'!O114,TEXT('Level 1'!P113," mm-dd-yyyy"),";"," ",'Level 1'!Q114,'Level 1'!V114," ",'Level 1'!T114," ","Payment "," ",'Level 1'!U114," ",'Level 1'!#REF!," ",'Level 1'!W114," ",'Level 1'!X114," ",'Level 1'!Z114, " ",'Level 1'!AA114, " ","Insurance: ",'Level 1'!A114) -> #REF! | C114: ='Level 1'!Y114 -> Task Sub Pending Claims Queue | D114: =VLOOKUP(C114,Table2[#All],3,FALSE) -> N/A | E114: INSB NV Team Task | F114: SN
A115: =CONCATENATE("Pt Id:",'Level 1'!E115," ","Pt Name: ",'Level 1'!F115," ","DOS: ", TEXT('Level 1'!H115,"mm-dd-yyyy")," "," Amnt: ","$",'Level 1'!J115," ", 'Level 1'!N115) -> Pt Id:9013 Pt Name: Reed, Christine DOS: 02-08-2022 Amnt: $408.8 Note | B115: =CONCATENATE("Detail: ",'Level 1'!N115," ",'Level 1'!O115,TEXT('Level 1'!P114," mm-dd-yyyy"),";"," ",'Level 1'!Q115,'Level 1'!R115," ",'Level 1'!T115," ","Payment "," ",'Level 1'!U115," ",'Level 1'!V115," ",'Level 1'!W115," ",'Level 1'!X115," ",'Level 1'!Z115, " ",'Level 1'!AA115, " ","Insurance: ",'Level 1'!A115) -> Detail: Note Q1Primary EOB Required; Q2 Payment Q4 Q5 Additional Notes: Insurance: Dental Health and Wellness WI | C115: ='Level 1'!Y115 -> Action | D115: =VLOOKUP(C115,Table2[#All],3,FALSE) -> What we need from you/Reason | E115: Claim Status
A116: =CONCATENATE("Pt Id:",'Level 1'!E116," ","Pt Name: ",'Level 1'!F116," ","DOS: ", TEXT('Level 1'!H116,"mm-dd-yyyy")," "," Amnt: ","$",'Level 1'!J116," ", 'Level 1'!N116) -> Pt Id:8958 Pt Name: Sloat , Breanna DOS: 02-08-2022 Amnt: $607.2 Ins needs more info, need to submit; | B116: =CONCATENATE("Detail: ",'Level 1'!N116," ",'Level 1'!O116,TEXT('Level 1'!P115," mm-dd-yyyy"),";"," ",'Level 1'!Q116,'Level 1'!R116," ",'Level 1'!T116," ","Payment "," ",'Level 1'!U116," ",'Level 1'!V116," ",'Level 1'!W116," ",'Level 1'!X116," ",'Level 1'!Z116, " ",'Level 1'!AA116, " ","Insurance: ",'Level 1'!A116) -> Detail: Ins needs more info, need to submit; Attachments/Info needed? 01-00-1900; Fax # (If Fax Yes): 607713 Payment Cust Rep: GLADYS 0 Additional Notes: Claim was denied due to No primary Insure EOB. Patient has primary Insurance . The Provider need to include EOB with the claim or term letter indicating the primary Insurance was terminated. Insurance: Dental Health and Wellness WI | C116: ='Level 1'!Y116 -> Task Sub Pending Claims Queue | D116: =VLOOKUP(C116,Table2[#All],3,FALSE) -> N/A | E116: INSB NV Team Task | F116: SN
A117: =CONCATENATE("Pt Id:",'Level 1'!E117," ","Pt Name: ",'Level 1'!F117," ","DOS: ", TEXT('Level 1'!H117,"mm-dd-yyyy")," "," Amnt: ","$",'Level 1'!J117," ", 'Level 1'!N117) -> Pt Id:2956 Pt Name: Groves, Nolan DOS: 01-27-2022 Amnt: $20 Duplicate Submission; | B117: =CONCATENATE("Detail: ",'Level 1'!N117," ",'Level 1'!O117,TEXT('Level 1'!P116," mm-dd-yyyy"),";"," ",'Level 1'!Q117,'Level 1'!R117," ",'Level 1'!T117," ","Payment "," ",'Level 1'!U117," ",'Level 1'!V117," ",'Level 1'!W117," ",'Level 1'!X117," ",'Level 1'!Z117, " ",'Level 1'!AA117, " ","Insurance: ",'Level 1'!A117) -> Detail: Duplicate Submission; Dt orig. claim submitted:Primary EOB Required; Status of original Claim: 575324 Payment Cust Rep: JAZZ 0 Additional Notes: Incorrectly denied as duplicate, Check with Stanley for clarification - SN. Insurance: Dental Health and Wellness WI | C117: ='Level 1'!Y117 -> No Action | D117: =VLOOKUP(C117,Table2[#All],3,FALSE) -> N/A | E117: Claim Status
A118: =CONCATENATE("Pt Id:",'Level 1'!E118," ","Pt Name: ",'Level 1'!F118," ","DOS: ", TEXT('Level 1'!H118,"mm-dd-yyyy")," "," Amnt: ","$",'Level 1'!J118," ", 'Level 1'!N118) -> Pt Id:8714 Pt Name: Lees, Vannessa DOS: 12-23-2021 Amnt: $813.6 Note | B118: =CONCATENATE("Detail: ",'Level 1'!N118," ",'Level 1'!O118,TEXT('Level 1'!P117," mm-dd-yyyy"),";"," ",'Level 1'!Q118,'Level 1'!R118," ",'Level 1'!T118," ","Payment "," ",'Level 1'!U118," ",'Level 1'!V118," ",'Level 1'!W118," ",'Level 1'!X118," ",'Level 1'!Z118, " ",'Level 1'!AA118, " ","Insurance: ",'Level 1'!A118) -> Detail: Note Q1 01-00-1900; Q2 Payment Q4 Q5 Additional Notes: Insurance: Dental Health and Wellness WI | C118: ='Level 1'!Y118 -> Action | D118: =VLOOKUP(C118,Table2[#All],3,FALSE) -> What we need from you/Reason | E118: Claim Status
A119: =CONCATENATE("Pt Id:",'Level 1'!E119," ","Pt Name: ",'Level 1'!F119," ","DOS: ", TEXT('Level 1'!H119,"mm-dd-yyyy")," "," Amnt: ","$",'Level 1'!J119," ", 'Level 1'!N119) -> Pt Id:8863 Pt Name: Johnson , Elliott DOS: 01-14-2022 Amnt: $408.8 Note | B119: =CONCATENATE("Detail: ",'Level 1'!N119," ",'Level 1'!O119,TEXT('Level 1'!P118," mm-dd-yyyy"),";"," ",'Level 1'!Q119,'Level 1'!R119," ",'Level 1'!T119," ","Payment "," ",'Level 1'!U119," ",'Level 1'!V119," ",'Level 1'!W119," ",'Level 1'!X119," ",'Level 1'!Z119, " ",'Level 1'!AA119, " ","Insurance: ",'Level 1'!A119) -> Detail: Note Q1 01-00-1900; Q2 Payment Q4 Q5 Additional Notes: Insurance: Dental Health and Wellness WI | C119: ='Level 1'!Y119 -> Action | D119: =VLOOKUP(C119,Table2[#All],3,FALSE) -> What we need from you/Reason | E119: Claim Status
A120: =CONCATENATE("Pt Id:",'Level 1'!E120," ","Pt Name: ",'Level 1'!F120," ","DOS: ", TEXT('Level 1'!H120,"mm-dd-yyyy")," "," Amnt: ","$",'Level 1'!J120," ", 'Level 1'!N120) -> Pt Id:629 Pt Name: Jaimes, Gener DOS: 01-14-2022 Amnt: $132.8 Claim Paid by Check; | B120: =CONCATENATE("Detail: ",'Level 1'!N120," ",'Level 1'!O120,TEXT('Level 1'!P119," mm-dd-yyyy"),";"," ",'Level 1'!Q120,'Level 1'!R120," ",'Level 1'!T120," ","Payment "," ",'Level 1'!U120," ",'Level 1'!V120," ",'Level 1'!W120," ",'Level 1'!X120," ",'Level 1'!Z120, " ",'Level 1'!AA120, " ","Insurance: ",'Level 1'!A120) -> Detail: Claim Paid by Check; Issue Date: 01-00-1900; CHK#904375 Bulk Payment Call Ref#: Cust Rep: Additional Notes: Cashed date 01/31/2022 CLM # 20220117144845; Pd Amt : $56.57; Pt Resp: 0; Bulk Amt : $1566.24; Check is outstanding. D0220, D0230 & D0274 are bundled to D0210 and paid Insurance: Dental Health and Wellness WI | C120: ='Level 1'!Y120 -> Task Cashed Chk Queue | D120: =VLOOKUP(C120,Table2[#All],3,FALSE) -> What We Need From You: Please confirm Check was received. Reason: To close claim. | E120: Claim Status
A121: =CONCATENATE("Pt Id:",'Level 1'!E121," ","Pt Name: ",'Level 1'!F121," ","DOS: ", TEXT('Level 1'!H121,"mm-dd-yyyy")," "," Amnt: ","$",'Level 1'!J121," ", 'Level 1'!N121) -> Pt Id:8765 Pt Name: Guzman, Daniel DOS: 01-14-2022 Amnt: $332.4 Claim Paid by Check; | B121: =CONCATENATE("Detail: ",'Level 1'!N121," ",'Level 1'!O121,TEXT('Level 1'!P120," mm-dd-yyyy"),";"," ",'Level 1'!Q121,'Level 1'!R121," ",'Level 1'!T121," ","Payment "," ",'Level 1'!U121," ",'Level 1'!V121," ",'Level 1'!W121," ",'Level 1'!X121," ",'Level 1'!Z121, " ",'Level 1'!AA121, " ","Insurance: ",'Level 1'!A121) -> Detail: Claim Paid by Check; Issue Date: 01-20-2022; CHK#904375 Bulk Payment Call Ref#: Cust Rep: Additional Notes: Cashed date 01/31/2022; CLM # 20220117144846; Pd Amt : $103.19; Pt Resp : $0; Bulk Amt $1566.24. Check is outstanding Insurance: Dental Health and Wellness WI | C121: ='Level 1'!Y121 -> Task Cashed Chk Queue | D121: =VLOOKUP(C121,Table2[#All],3,FALSE) -> What We Need From You: Please confirm Check was received. Reason: To close claim. | E121: Task Created | F121: SN
A122: =CONCATENATE("Pt Id:",'Level 1'!E122," ","Pt Name: ",'Level 1'!F122," ","DOS: ", TEXT('Level 1'!H122,"mm-dd-yyyy")," "," Amnt: ","$",'Level 1'!J122," ", 'Level 1'!N122) -> Pt Id:8807 Pt Name: Allen, Andre DOS: 01-14-2022 Amnt: $294.8 Claim Paid by Check; | B122: =CONCATENATE("Detail: ",'Level 1'!N122," ",'Level 1'!O122,TEXT('Level 1'!P121," mm-dd-yyyy"),";"," ",'Level 1'!Q122,'Level 1'!R122," ",'Level 1'!T122," ","Payment "," ",'Level 1'!U122," ",'Level 1'!V122," ",'Level 1'!W122," ",'Level 1'!X122," ",'Level 1'!Z122, " ",'Level 1'!AA122, " ","Insurance: ",'Level 1'!A122) -> Detail: Claim Paid by Check; Issue Date: 01-20-2022; CHK#904375 Bulk Payment Call Ref#: Cust Rep: Additional Notes: Cashed date 01/31/2022 //GET CASED DATE -MU ( Instead of 1/14/2022 for the DOS 1/06/2022 get the cashed date. ) ////CLM # 20220117142317; Pd Amt : $103.19; Pt Resp $0; Bulk Amt : $1566.24 Insurance: Dental Health and Wellness WI | C122: ='Level 1'!Y122 -> Task Cashed Chk Queue | D122: =VLOOKUP(C122,Table2[#All],3,FALSE) -> What We Need From You: Please confirm Check was received. Reason: To close claim. | E122: Task Created | F122: SN
A123: =CONCATENATE("Pt Id:",'Level 1'!E123," ","Pt Name: ",'Level 1'!F123," ","DOS: ", TEXT('Level 1'!H123,"mm-dd-yyyy")," "," Amnt: ","$",'Level 1'!J123," ", 'Level 1'!N123) -> Pt Id:8849 Pt Name: Williams, James DOS: 01-12-2022 Amnt: $612 Claim Paid by Check; | B123: =CONCATENATE("Detail: ",'Level 1'!N123," ",'Level 1'!O123,TEXT('Level 1'!P122," mm-dd-yyyy"),";"," ",'Level 1'!Q123,'Level 1'!R123," ",'Level 1'!T123," ","Payment "," ",'Level 1'!U123," ",'Level 1'!V123," ",'Level 1'!W123," ",'Level 1'!X123," ",'Level 1'!Z123, " ",'Level 1'!AA123, " ","Insurance: ",'Level 1'!A123) -> Detail: Claim Paid by Check; Issue Date: 01-20-2022; CHK#932617 Bulk Payment Call Ref#: Cust Rep: Additional Notes: Rep State that Cashed on 03/23/2022 Rep Name: Jahni, Call Ref: 541267,CLM # 20220114130481; Pd Amt $157.86; Pt Resp $0; Bulk Amt $1566.24 Insurance: Dental Health and Wellness WI | C123: ='Level 1'!Y123 -> Task Cashed Chk Queue | D123: =VLOOKUP(C123,Table2[#All],3,FALSE) -> What We Need From You: Please confirm Check was received. Reason: To close claim. | E123: Task Created | F123: MU
...

Sheet Data
A1: Patient Name | B1: Patient ID | C1: PatientDOB | D1: Subscriber | E1: TreatingProv | F1: SubscriberID | G1: SubscriberDOB | H1: DateService | I1: DateSent | J1: ClaimFee | K1: CarrierName | L1: Phone | M1: Location
A3: ⭣ Actual Patient data starts from the row below ⭣
A4: Passehl , Kayla | B4: 9200 | C4: 7/30/1991 | D4: Passehl , Kayla | F4: W237205096 | H4: 44635 | I4: 3/24/2022 | J4: 292.4 | K4: Aetna | L4: 8004517715
A5: Brown, Isabella | B5: 7412 | C5: 3/15/1962 | D5: Brown, Isabella | F5: 016776290 | H5: 44470 | I5: 10/7/2021 | J5: 1036.8 | K5: Ameritas | L5: 8006592223
A6: Thom, Keri | B6: 9330 | C6: 8/14/2006 | D6: Thom, Keri | F6: GQP130W03886 | H6: 44642 | I6: 3/25/2022 | J6: 294.8 | K6: Anthem | L6: 8447291565
A7: Wricks, Derrishia | B7: 4527 | C7: 9/28/1993 | D7: Wricks, Derrishia | F7: 201W03443 | H7: 44545 | I7: 2/10/2022 | J7: 266 | K7: Anthem | L7: 8447291565
A8: Allen, Janiyah | B8: 8543 | C8: 9/28/1993 | D8: Allen, Janiyah | F8: 201W03443 | H8: 44545 | I8: 2/11/2022 | J8: 307.2 | K8: Anthem | L8: 8447291565
A9: Sullivan, Jessica | B9: 9345 | C9: 7/12/1984 | D9: Sullivan, Jessica | F9: U47262786 | H9: 44644 | I9: 3/25/2022 | J9: 302.4 | K9: Cigna | L9: 8002446224
A10: Sullivan, Carter | B10: 2668 | C10: 7/12/1984 | D10: Sullivan, Carter | F10: U47262786 | H10: 44643 | I10: 3/24/2022 | J10: 102 | K10: Cigna | L10: 8002446224
A11: Arthur, Bernika | B11: 3727 | C11: 8/26/1988 | D11: Arthur, Bernika | F11: U49852743 | H11: 44639 | I11: 3/21/2022 | J11: 123.6 | K11: Cigna | L11: 8002446224
A12: Arthur, Lilyana | B12: 3729 | C12: 8/26/1988 | D12: Arthur, Lilyana | F12: U49852743 | H12: 44639 | I12: 3/21/2022 | J12: 58.8 | K12: Cigna | L12: 8002446224
A13: Arthur, Lilyana | B13: 3729 | C13: 8/26/1988 | D13: Arthur, Lilyana | F13: U49852743 | H13: 44639 | I13: 3/21/2022 | J13: 79.2 | K13: Cigna | L13: 8002446224
A14: Belle , Byron | B14: 4246 | C14: 6/10/1992 | D14: Belle , Byron | F14: U72051724 | H14: 44573 | I14: 1/13/2022 | J14: 266 | K14: Cigna | L14: 8002446224
A15: Arthur, Devin | B15: 3728 | C15: 8/26/1988 | D15: Arthur, Devin | F15: U49852743 | H15: 44478 | I15: 10/11/2021 | J15: 230 | K15: Cigna | L15: 8002446224
... A37: SHERMAN, STEPHANIE | B37: 3523 | C37: 5/20/1977 | D37: SHERMAN, STEPHANIE | F37: 3199644 | H37: 44265 | I37: 4/15/2021 | J37: 230 | K37: DELTA DENTAL OF IOWA | L37: 8005440718
